Workbook
Name SlicerCache_Table_1_Col_1: #N/A
Name SlicerCache_Table_1_Col_2: #N/A

Sheet Partnership Info
C2: Partner Name: | D2: Partner
C3: Davyn Limited | D3: ID
C5: Partner Development Manager | D5: Leon Ribeiro | F5: 🔗 Resources
C6: Partner Account Manager | D6: Edgar Balby | F6: Partner Portal
C7: Marketing Manager | D7: Agata Lech
C9: Partner Type | D9: Expert
C10: Market | D10: ROW
C11: Sale Commission % (12 months) | D11: 0.35
C12: Support | D12: TRUE
C13: Onboarding | D13: TRUE
C14: Avg. Onboarding amount | D14: 3000
C15: Support Commission % (lifetime) | D15: 0.2
C16: Connector/Integration Price (if any) | D16: 0
C18: Partner Customer base # | D18: 300
C19: Partner Customer base ICP (nº seats) | D19: 300

Sheet Plan Summary
C2: Plan Summary | D2: Q1 | G2: Q2 | J2: Q3 | M2: Q4 | Q2: Q1 | R2: Q2 | S2: Q3 | T2: Q4 | U2: Total Year 1 | W2: Year 2+ Services
D3: January | E3: February | F3: March | G3: April | H3: May | I3: June | J3: July | K3: August | L3: September | M3: October | N3: November | O3: December
C4: Won Customers # | D4: ='Business Plan'!E9 -> 1 | E4: ='Business Plan'!F9 -> 1 | F4: ='Business Plan'!G9 -> 2 | G4: ='Business Plan'!H9 -> 1 | H4: ='Business Plan'!I9 -> 2 | I4: ='Business Plan'!J9 -> 3 | J4: ='Business Plan'!K9 -> 2 | K4: ='Business Plan'!L9 -> 3 | ... O4: ='Business Plan'!P9 -> 1 | Q4: =SUM(D4:F4) -> 4 | R4: =SUM(G4:I4) -> 6 | S4: =SUM(J4:L4) -> 8 | T4: =SUM(M4:O4) -> 7 | U4: =SUM(D4:O4) -> 25 | W4: =SUM(F4:Q4) -> 27
E5: =D5 | F5: =E5 | G5: =F5 | H5: =G5 | I5: =H5 | J5: =I5 | K5: =J5 | L5: =K5 | ... O5: =N5
C6: Won MRR | D6: ='Business Plan'!E12 -> 1750 | E6: ='Business Plan'!F12 -> 2100 | F6: ='Business Plan'!G12 -> 2450 | G6: ='Business Plan'!H12 -> 2100 | H6: ='Business Plan'!I12 -> 2450 | I6: ='Business Plan'!J12 -> 4200 | J6: ='Business Plan'!K12 -> 2450 | K6: ='Business Plan'!L12 -> 2800 | ... O6: ='Business Plan'!P12 -> 2100 | Q6: =SUM(D6:F6) -> 6300 | R6: =SUM(G6:I6) -> 8750 | S6: =SUM(J6:L6) -> 9100 | T6: =SUM(M5:O6) -> 10850 | U6: =SUM(D6:O6) -> 35000
C7: Won ARR | D7: =D6*12 -> 21000 | E7: =E6*12 -> 25200 | F7: =F6*12 -> 29400 | G7: =G6*12 -> 25200 | H7: =H6*12 -> 29400 | I7: =I6*12 -> 50400 | J7: =J6*12 -> 29400 | K7: =K6*12 -> 33600 | ... O7: =O6*12 -> 25200 | Q7: =SUM(D7:F7) -> 75600 | R7: =SUM(G7:I7) -> 105000 | S7: =SUM(J7:L7) -> 109200 | T7: =SUM(M6:O7) -> 141050 | U7: =U6*12 -> 420000
C9: Total Commissions & Incentives | D9: =SUM(D19:D22) -> 8100 | E9: =SUM(E19:E22) -> 9570 | F9: =SUM(F19:F22) -> 28990 | G9: =SUM(G19:G22) -> 10320 | H9: =SUM(H19:H22) -> 13290 | I9: =SUM(I19:I22) -> 35690 | J9: =SUM(J19:J22) -> 16290 | K9: =SUM(K19:K22) -> 20760 | ... O9: =SUM(O19:O22) -> 26370 | Q9: =SUM(D9:F9) -> 46660 | R9: =SUM(G9:I9) -> 59300 | S9: =SUM(J9:L9) -> 76270 | T9: =SUM(M8:O9) -> 81120 | U9: =SUM(D9:O9) -> 263350 | W9: =U7*'Partnership Info'!D15 -> 84000
C11: Total Invested | D11: =(D25+D27)+D26 -> -15916.667 | E11: =(E25+E27)+E26 -> -25216.667 | F11: =(F25+F27)+F26 -> -15416.667 | G11: =(G25+G27)+G26 -> -15916.667 | H11: =(H25+H27)+H26 -> -22916.667 | I11: =(I25+I27)+I26 -> -15416.667 | J11: =(J25+J27)+J26 -> -23416.667 | K11: =(K25+K27)+K26 -> -15416.667 | ... O11: =(O25+O27)+O26 -> -15416.667 | Q11: =SUM(D11:F11) -> -56550 | R11: =SUM(G11:I11) -> -54250 | S11: =SUM(J11:L11) -> -54250 | T11: =SUM(M10:O11) -> -54250 | U11: =SUM(D11:O11) -> -219300 | W11: =Headcount!D37 -> 39750
C13: Total Balance (12-month P&L) | D13: =D9+D11 -> -7816.6667 | E13: =E9+E11 -> -15646.667 | F13: =F9+F11 -> 13573.333 | G13: =G9+G11 -> -5596.6667 | H13: =H9+H11 -> -9626.6667 | I13: =I9+I11 -> 20273.333 | J13: =J9+J11 -> -7126.6667 | K13: =K9+K11 -> 5343.3333 | ... O13: =O9+O11 -> 10953.333 | Q13: =SUM(D13:F13) -> -9890 | R13: =SUM(G13:I13) -> 5050 | S13: =SUM(J13:L13) -> 22020 | T13: =SUM(M12:O13) -> 26870 | U13: =SUM(D13:O13) -> 44050 | W13: =SUM(F13:Q13) -> 57623.333
C15: Commissions cashflow (new MRR only) | D15: ='Business Plan'!E26 -> 1362.5 | E15: ='Business Plan'!F26 -> 2097.5 | F15: ='Business Plan'!G26 -> 20905 | G15: ='Business Plan'!H26 -> 4440 | H15: ='Business Plan'!I26 -> 6797.5 | I15: ='Business Plan'!J26 -> 23317.5 | J15: ='Business Plan'!K26 -> 12125 | K15: ='Business Plan'!L26 -> 16105 | ... O15: ='Business Plan'!P26 -> 29800 | Q15: =SUM(D15:F15) -> 24365 | R15: =SUM(G15:I15) -> 34555 | S15: =SUM(J15:L15) -> 59732.5 | T15: =SUM(M14:O15) -> 69237.5 | U15: =SUM(D15:O15) -> 187890
C17: ='Business Plan'!C48 -> Approx net cashflow (sales FS only) | D17: ='Business Plan'!E48 -> -8254.1667 | E17: ='Business Plan'!F48 -> -16819.167 | F17: ='Business Plan'!G48 -> 11788.333 | G17: ='Business Plan'!H48 -> -5176.6667 | H17: ='Business Plan'!I48 -> -9819.1667 | I17: ='Business Plan'!J48 -> 14200.833 | J17: ='Business Plan'!K48 -> -4991.6667 | K17: ='Business Plan'!L48 -> 6988.3333 | ... O17: ='Business Plan'!P48 -> 20683.333 | Q17: =SUM(D17:F17) -> -13285 | R17: =SUM(G17:I17) -> -795 | S17: =SUM(J17:L17) -> 24382.5 | T17: =SUM(M16:O17) -> 33887.5 | U17: =SUM(D17:O17) -> 44190
C19: Commissions - Sales | D19: ='Business Plan'!E19 -> 7350 | E19: ='Business Plan'!F19 -> 8820 | F19: ='Business Plan'!G19 -> 10290 | G19: ='Business Plan'!H19 -> 8820 | H19: ='Business Plan'!I19 -> 10290 | I19: ='Business Plan'!J19 -> 17640 | J19: ='Business Plan'!K19 -> 10290 | K19: ='Business Plan'!L19 -> 11760 | ... O19: ='Business Plan'!P19 -> 8820 | Q19: =SUM(D19:F19) -> 26460 | R19: =SUM(G19:I19) -> 36750 | S19: =SUM(J19:L19) -> 38220 | T19: =SUM(M7:O19) -> 332635 | U19: =SUM(D19:O19) -> 147000 | W19: =SUM(F19:Q19) -> 157290
C20: Commissions - Integrations | D20: ='Business Plan'!E21 -> 0 | E20: ='Business Plan'!F21 -> 0 | F20: ='Business Plan'!G21 -> 0 | G20: ='Business Plan'!H21 -> 0 | H20: ='Business Plan'!I21 -> 0 | I20: ='Business Plan'!J21 -> 0 | J20: ='Business Plan'!K21 -> 0 | K20: ='Business Plan'!L21 -> 0 | ... O20: ='Business Plan'!P21 -> 0 | Q20: =SUM(D20:F20) -> 0 | R20: =SUM(G20:I20) -> 0 | S20: =SUM(J20:L20) -> 0 | T20: =SUM(M20:O20) -> 0 | U20: =SUM(D20:O20) -> 0 | W20: =SUM(F20:Q20) -> 0
C21: Onboardings | D21: ='Business Plan'!E22 -> 750 | E21: ='Business Plan'!F22 -> 750 | F21: ='Business Plan'!G22 -> 1500 | G21: ='Business Plan'!H22 -> 1500 | H21: ='Business Plan'!I22 -> 3000 | I21: ='Business Plan'!J22 -> 4500 | J21: ='Business Plan'!K22 -> 6000 | K21: ='Business Plan'!L22 -> 9000 | ... O21: ='Business Plan'!P22 -> 3000 | Q21: =SUM(D21:F21) -> 3000 | R21: =SUM(G21:I21) -> 9000 | S21: =SUM(J21:L21) -> 24000 | T21: =SUM(M20:O21) -> 21000 | U21: =SUM(D21:O21) -> 57000 | W21: =SUM(F21:Q21) -> 58500
C22: Bonus & Incentives | D22: ='Business Plan'!E20 -> 0 | E22: ='Business Plan'!F20 -> 0 | F22: ='Business Plan'!G20 -> 17200 | G22: ='Business Plan'!H20 -> 0 | H22: ='Business Plan'!I20 -> 0 | I22: ='Business Plan'!J20 -> 13550 | J22: ='Business Plan'!K20 -> 0 | K22: ='Business Plan'!L20 -> 0 | ... O22: ='Business Plan'!P20 -> 14550 | Q22: =SUM(D22:F22) -> 17200 | R22: =SUM(G22:I22) -> 13550 | S22: =SUM(J22:L22) -> 14050 | T22: =SUM(M19:O22) -> 81120 | U22: =SUM(D22:O22) -> 59350 | W22: =SUM(F22:Q22) -> 76550
C24: Headcount | D24: ='Business Plan'!E36 -> -14216.667 | E24: ='Business Plan'!F36 -> -14216.667 | F24: ='Business Plan'!G36 -> -14216.667 | G24: ='Business Plan'!H36 -> -14216.667 | H24: ='Business Plan'!I36 -> -14216.667 | I24: ='Business Plan'!J36 -> -14216.667 | J24: ='Business Plan'!K36 -> -14216.667 | K24: ='Business Plan'!L36 -> -14216.667 | ... O24: ='Business Plan'!P36 -> -14216.667 | Q24: =SUM(D24:F24) -> -42650 | R24: =SUM(G24:I24) -> -42650 | S24: =SUM(J24:L24) -> -42650 | T24: =SUM(M23:O24) -> -42650 | U24: =SUM(D24:O24) -> -170600 | W24: =SUM(F24:Q24) -> -184816.67
C25: Monthly Salary | D25: ='Business Plan'!E37 -> -14216.667 | E25: ='Business Plan'!F37 -> -14216.667 | F25: ='Business Plan'!G37 -> -14216.667 | G25: ='Business Plan'!H37 -> -14216.667 | H25: ='Business Plan'!I37 -> -14216.667 | I25: ='Business Plan'!J37 -> -14216.667 | J25: ='Business Plan'!K37 -> -14216.667 | K25: ='Business Plan'!L37 -> -14216.667 | ... O25: ='Business Plan'!P37 -> -14216.667 | Q25: =SUM(D25:F25) -> -42650 | R25: =SUM(G25:I25) -> -42650 | S25: =SUM(J25:L25) -> -42650 | T25: =SUM(M24:O25) -> -85300 | U25: =SUM(D25:O25) -> -170600 | W25: =SUM(F25:Q25) -> -184816.67
C26: Budget | D26: =-sumif('Demand Generation Plan'!$D$4:$D27,D3,'Demand Generation Plan'!$F$4:$F27) -> -1700 | E26: =-sumif('Demand Generation Plan'!$D$4:$D27,E3,'Demand Generation Plan'!$F$4:$F27) -> -11000 | F26: =-sumif('Demand Generation Plan'!$D$4:$D27,F3,'Demand Generation Plan'!$F$4:$F27) -> -1200 | G26: =-sumif('Demand Generation Plan'!$D$4:$D27,G3,'Demand Generation Plan'!$F$4:$F27) -> -1700 | H26: =-sumif('Demand Generation Plan'!$D$4:$D27,H3,'Demand Generation Plan'!$F$4:$F27) -> -8700 | I26: =-sumif('Demand Generation Plan'!$D$4:$D27,I3,'Demand Generation Plan'!$F$4:$F27) -> -1200 | J26: =-sumif('Demand Generation Plan'!$D$4:$D27,J3,'Demand Generation Plan'!$F$4:$F27) -> -9200 | K26: =-sumif('Demand Generation Plan'!$D$4:$D27,K3,'Demand Generation Plan'!$F$4:$F27) -> -1200 | ... O26: =-sumif('Demand Generation Plan'!$D$4:$D27,O3,'Demand Generation Plan'!$F$4:$F27) -> -1200 | Q26: =SUM(D26:F26) -> -13900 | R26: =SUM(G26:I26) -> -11600 | S26: =SUM(J26:L26) -> -11600 | T26: =SUM(M26:O26) -> -11600 | U26: =SUM(D26:O26) -> -48700 | W26: =SUM(F26:Q26) -> -49900
C27: Factorial Support | D27: ='Business Plan'!E38 -> 0 | E27: ='Business Plan'!F38 -> 0 | F27: ='Business Plan'!G38 -> 0 | G27: ='Business Plan'!H38 -> 0 | H27: ='Business Plan'!I38 -> 0 | I27: ='Business Plan'!J38 -> 0 | J27: ='Business Plan'!K38 -> 0 | K27: ='Business Plan'!L38 -> 0 | ... O27: ='Business Plan'!P38 -> 0 | Q27: =SUM(D27:F27) -> 0 | R27: =SUM(G27:I27) -> 0 | S27: =SUM(J27:L27) -> 0 | T27: =SUM(M25:O27) -> -54250 | U27: =SUM(D27:O27) -> 0 | W27: =SUM(F27:Q27) -> 0

Sheet Business Plan
D2: Total | E2: Q1 | H2: Q2 | K2: Q3 | N2: Q4 | R2: Q1 | S2: Q2 | T2: Q3 | U2: Q4
E3: January | F3: February | G3: March | H3: April | I3: May | J3: June | K3: July | L3: August | M3: September | N3: October | O3: November | P3: December
C4: Required Demos # | D4: =SUM(E4:P4) -> 133 | E4: =INT(E9/E5) -> 5 | F4: =INT(F9/F5) -> 5 | G4: =INT(G9/G5) -> 11 | H4: =INT(H9/H5) -> 5 | I4: =INT(I9/I5) -> 11 | J4: =INT(J9/J5) -> 16 | K4: =INT(K9/K5) -> 11 | L4: =INT(L9/L5) -> 16 | ... P4: =INT(P9/P5) -> 5 | R4: =SUM(E4:G4) -> 21 | S4: =SUM(H4:J4) -> 32 | T4: =SUM(K4:M4) -> 43 | U4: =SUM(N3:P4) -> 37
C5: % Demo to Customer | E5: 0.18 | F5: 0.18 | G5: 0.18 | H5: 0.18 | I5: 0.18 | J5: 0.18 | K5: 0.18 | L5: 0.18 | M5: 0.18 | N5: 0.18 | O5: 0.18 | P5: =O5 -> 0.18 | R5: =R9/R4 -> 0.19047619 | S5: =S9/S4 -> 0.1875 | T5: =T9/T4 -> 0.18604651 | U5: =U9/U4 -> 0.18918919
C6: Planned Demos | D6: =SUM(E6:P6) -> 220 | E6: =SUMIF(E50,"=" & 'Business Plan'!E3,E51) -> 10 | F6: =SUMIF(F50,"=" & 'Business Plan'!F3,F51) -> 11 | G6: =SUMIF(G50,"=" & 'Business Plan'!G3,G51) -> 34 | H6: =SUMIF(H50,"=" & 'Business Plan'!H3,H51) -> 12 | I6: =SUMIF(I50,"=" & 'Business Plan'!I3,I51) -> 22 | J6: =SUMIF(J50,"=" & 'Business Plan'!J3,J51) -> 17 | K6: =SUMIF(K50,"=" & 'Business Plan'!K3,K51) -> 23 | L6: =SUMIF(L50,"=" & 'Business Plan'!L3,L51) -> 18 | ... P6: =SUMIF(P50,"=" & 'Business Plan'!P3,P51) -> 14 | R6: =SUM(E6:G6) -> 55 | S6: =SUM(H6:J6) -> 51 | T6: =SUM(K6:M6) -> 57 | U6: =SUM(N5:P6) -> 57.54
C7: Action Review | D7: =IF(SUM(E8:P8)=12,"CORRECT","REVIEW DATA") -> REVIEW DATA | E7: =IF((SUMIF(E50,"=" & 'Business Plan'!E3,E51))>=E4, "CORRECT", CONCATENATE(E$4-(SUMIF(E50,"=" & 'Business Plan'!E3,E51))," Demos Missing in Plan")) -> CORRECT | F7: =IF((SUMIF(F50,"=" & 'Business Plan'!F3,F51))>=F4, "CORRECT", CONCATENATE(F$4-(SUMIF(F50,"=" & 'Business Plan'!F3,F51))," Demos Missing in Plan")) -> CORRECT | G7: =IF((SUMIF(G50,"=" & 'Business Plan'!G3,G51))>=G4, "CORRECT", CONCATENATE(G$4-(SUMIF(G50,"=" & 'Business Plan'!G3,G51))," Demos Missing in Plan")) -> CORRECT | H7: =IF((SUMIF(H50,"=" & 'Business Plan'!H3,H51))>=H4, "CORRECT", CONCATENATE(H$4-(SUMIF(H50,"=" & 'Business Plan'!H3,H51))," Demos Missing in Plan")) -> CORRECT | I7: =IF((SUMIF(I50,"=" & 'Business Plan'!I3,I51))>=I4, "CORRECT", CONCATENATE(I$4-(SUMIF(I50,"=" & 'Business Plan'!I3,I51))," Demos Missing in Plan")) -> CORRECT | J7: =IF((SUMIF(J50,"=" & 'Business Plan'!J3,J51))>=J4, "CORRECT", CONCATENATE(J$4-(SUMIF(J50,"=" & 'Business Plan'!J3,J51))," Demos Missing in Plan")) -> CORRECT | K7: =IF((SUMIF(K50,"=" & 'Business Plan'!K3,K51))>=K4, "CORRECT", CONCATENATE(K$4-(SUMIF(K50,"=" & 'Business Plan'!K3,K51))," Demos Missing in Plan")) -> CORRECT | L7: =IF((SUMIF(L50,"=" & 'Business Plan'!L3,L51))>=L4, "CORRECT", CONCATENATE(L$4-(SUMIF(L50,"=" & 'Business Plan'!L3,L51))," Demos Missing in Plan")) -> CORRECT | ... P7: =IF((SUMIF(P50,"=" & 'Business Plan'!P3,P51))>=P4, "CORRECT", CONCATENATE(P$4-(SUMIF(P50,"=" & 'Business Plan'!P3,P51))," Demos Missing in Plan")) -> CORRECT
E8: =IF(E7="CORRECT","1","0") -> 1 | F8: =IF(F7="CORRECT","1","0") -> 1 | G8: =IF(G7="CORRECT","1","0") -> 1 | H8: =IF(H7="CORRECT","1","0") -> 1 | I8: =IF(I7="CORRECT","1","0") -> 1 | J8: =IF(J7="CORRECT","1","0") -> 1 | K8: =IF(K7="CORRECT","1","0") -> 1 | L8: =IF(L7="CORRECT","1","0") -> 1 | ... P8: =IF(P7="CORRECT","1","0") -> 1
C9: Won Customers # | D9: =SUM(E9:P9) -> 25 | E9: =INT(E12/E14) -> 1 | F9: =INT(F12/F14) -> 1 | G9: =INT(G12/G14) -> 2 | H9: =INT(H12/H14) -> 1 | I9: =INT(I12/I14) -> 2 | J9: =INT(J12/J14) -> 3 | K9: =INT(K12/K14) -> 2 | L9: 3 | M9: =INT(M12/M14) -> 3 | N9: =INT(N12/N14) -> 3 | O9: =INT(O12/O14) -> 3 | P9: 1 | R9: =SUM(E9:G9) -> 4 | S9: =SUM(H9:J9) -> 6 | T9: =SUM(K9:M9) -> 8 | U9: =SUM(N8:P9) -> 7
C10: Quality Check | D10: =CONCATENATE(IFS( D9/'Partnership Info'!D18 < 0.1, "<10%", D9/'Partnership Info'!D18 < 0.25, "10-25%", D9/'Partnership Info'!D18 < 0.45, "25-45%", D9/'Partnership Info'!D18 < 0.65, "45-65%", D9/'Partnership Info'!D18 < 0.85, "65-85%", TRUE, ">85%" )," of your customer base") -> <10% of your customer base
C12: Won MRR | D12: 35000 | E12: =$D$12*E13 -> 1750 | F12: =$D$12*F13 -> 2100 | G12: =$D$12*G13 -> 2450 | H12: =$D$12*H13 -> 2100 | I12: =$D$12*I13 -> 2450 | J12: =$D$12*J13 -> 4200 | K12: =$D$12*K13 -> 2450 | L12: =$D$12*L13 -> 2800 | ... P12: =$D$12*P13 -> 2100 | R12: =SUM(E12:G12) -> 6300 | S12: =SUM(H12:J12) -> 8750 | T12: =SUM(K12:M12) -> 9100 | U12: =SUM(N11:P12) -> 10850
C13: Seasonality | D13: =SUM(E13:P13) -> 1 | E13: 0.05 | F13: 0.06 | G13: 0.07 | H13: 0.06 | I13: 0.07 | J13: 0.12 | K13: 0.07 | L13: 0.08 | M13: 0.11 | N13: 0.12 | O13: 0.13 | P13: 0.06
C14: ARPU | D14: 1200 | E14: 1200 | F14: =E14 -> 1200 | G14: =F14 -> 1200 | H14: =G14 -> 1200 | I14: =H14 -> 1200 | J14: =I14 -> 1200 | K14: =J14 -> 1200 | L14: =K14 -> 1200 | M14: =L14 -> 1200 | ... P14: =O14 -> 1200 | R14: =R12/R9 -> 1575 | S14: =S12/S9 -> 1458.3333 | T14: =T12/T9 -> 1137.5 | U14: =U12/U9 -> 1550
C15: Won ARR | D15: =D12*12 -> 420000 | E15: =E12*12 -> 21000 | F15: =F12*12 -> 25200 | G15: =G12*12 -> 29400 | H15: =H12*12 -> 25200 | I15: =I12*12 -> 29400 | J15: =J12*12 -> 50400 | K15: =K12*12 -> 29400 | ... P15: =P12*12 -> 25200 | R15: =SUM(E15:G15) -> 75600 | S15: =SUM(H15:J15) -> 105000 | T15: =SUM(K15:M15) -> 109200 | U15: =SUM(N14:P15) -> 133800
C16: Won ARR (agg) | E16: =sum($E12:E12)*12 -> 21000 | F16: =sum($E12:F12)*12 -> 46200 | G16: =sum($E12:G12)*12 -> 75600 | H16: =sum($E12:H12)*12 -> 100800 | I16: =sum($E12:I12)*12 -> 130200 | J16: =sum($E12:J12)*12 -> 180600 | K16: =sum($E12:K12)*12 -> 210000 | L16: =sum($E12:L12)*12 -> 243600 | ... P16: =sum($E12:P12)*12 -> 420000 | R16: =R12 -> 6300 | S16: =R16+S12 -> 15050 | T16: =S16+T12 -> 24150 | U16: =T16+U12 -> 35000
C18: Commissions Total | D18: =SUM(E18:P18) -> 263350 | E18: =sum(E19:E22) -> 8100 | F18: =sum(F19:F22) -> 9570 | G18: =sum(G19:G22) -> 28990 | H18: =sum(H19:H22) -> 10320 | I18: =sum(I19:I22) -> 13290 | J18: =sum(J19:J22) -> 35690 | K18: =sum(K19:K22) -> 16290 | L18: =sum(L19:L22) -> 20760 | ... P18: =sum(P19:P22) -> 26370 | R18: =SUM(E18:G18) -> 46660 | S18: =SUM(H18:J18) -> 59300 | T18: =SUM(K18:M18) -> 76270 | U18: =SUM(N17:P18) -> 81120
C19: Commissions - Sales | D19: =SUM(E19:P19) -> 147000 | E19: ='Partnership Info'!$D$11*E15 -> 7350 | F19: ='Partnership Info'!$D$11*F15 -> 8820 | G19: ='Partnership Info'!$D$11*G15 -> 10290 | H19: ='Partnership Info'!$D$11*H15 -> 8820 | I19: ='Partnership Info'!$D$11*I15 -> 10290 | J19: ='Partnership Info'!$D$11*J15 -> 17640 | K19: ='Partnership Info'!$D$11*K15 -> 10290 | L19: ='Partnership Info'!$D$11*L15 -> 11760 | ... P19: ='Partnership Info'!$D$11*P15 -> 8820 | R19: =SUM(E19:G19) -> 26460 | S19: =SUM(H19:J19) -> 36750 | T19: =SUM(K19:M19) -> 38220 | U19: =SUM(N18:P19) -> 126690
C20: Bonus & Incentives | D20: =SUM(E20:P20) -> 59350 | E20: =SUMIF('B&I'!$G$3:$G58,E3,'B&I'!$F$3:$F58) -> 0 | F20: =SUMIF('B&I'!$G$3:$G58,F3,'B&I'!$F$3:$F58) -> 0 | G20: =SUMIF('B&I'!$G$3:$G58,G3,'B&I'!$F$3:$F58) -> 17200 | H20: =SUMIF('B&I'!$G$3:$G58,H3,'B&I'!$F$3:$F58) -> 0 | I20: =SUMIF('B&I'!$G$3:$G58,I3,'B&I'!$F$3:$F58) -> 0 | J20: =SUMIF('B&I'!$G$3:$G58,J3,'B&I'!$F$3:$F58) -> 13550 | K20: =SUMIF('B&I'!$G$3:$G58,K3,'B&I'!$F$3:$F58) -> 0 | L20: =SUMIF('B&I'!$G$3:$G58,L3,'B&I'!$F$3:$F58) -> 0 | ... P20: =SUMIF('B&I'!$G$3:$G58,P3,'B&I'!$F$3:$F58) -> 14550 | R20: =SUM(E20:G20) -> 17200 | S20: =SUM(H20:J20) -> 13550 | T20: =SUM(K20:M20) -> 14050 | U20: =SUM(N19:P20) -> 60120
C21: Own Integrations | D21: =SUM(E21:P21) -> 0 | E21: =E9*'Partnership Info'!$D$16 -> 0 | F21: =F9*'Partnership Info'!$D$16 -> 0 | G21: =G9*'Partnership Info'!$D$16 -> 0 | H21: =H9*'Partnership Info'!$D$16 -> 0 | I21: =I9*'Partnership Info'!$D$16 -> 0 | J21: =J9*'Partnership Info'!$D$16 -> 0 | K21: =K9*'Partnership Info'!$D$16 -> 0 | L21: =L9*'Partnership Info'!$D$16 -> 0 | ... P21: =P9*'Partnership Info'!$D$16 -> 0 | R21: =SUM(E21:G21) -> 0 | S21: =SUM(H21:J21) -> 0 | T21: =SUM(K21:M21) -> 0 | U21: =SUM(N20:P21) -> 14550
C22: Onboardings | D22: =SUM(E22:P22) -> 57000 | E22: =IF('Partnership Info'!$D$13=TRUE,E9*'Partnership Info'!$D$14*E23,"") -> 750 | F22: =IF('Partnership Info'!$D$13=TRUE,F9*'Partnership Info'!$D$14*F23,"") -> 750 | G22: =IF('Partnership Info'!$D$13=TRUE,G9*'Partnership Info'!$D$14*G23,"") -> 1500 | H22: =IF('Partnership Info'!$D$13=TRUE,H9*'Partnership Info'!$D$14*H23,"") -> 1500 | I22: =IF('Partnership Info'!$D$13=TRUE,I9*'Partnership Info'!$D$14*I23,"") -> 3000 | J22: =IF('Partnership Info'!$D$13=TRUE,J9*'Partnership Info'!$D$14*J23,"") -> 4500 | K22: =IF('Partnership Info'!$D$13=TRUE,K9*'Partnership Info'!$D$14*K23,"") -> 6000 | L22: =IF('Partnership Info'!$D$13=TRUE,L9*'Partnership Info'!$D$14*L23,"") -> 9000 | ... P22: =IF('Partnership Info'!$D$13=TRUE,P9*'Partnership Info'!$D$14*P23,"") -> 3000 | R22: =SUM(E22:G22) -> 3000 | S22: =SUM(H22:J22) -> 9000 | T22: =SUM(K22:M22) -> 24000 | U22: =SUM(N21:P22) -> 21000
C23: Onboarding % | E23: 0.25 | F23: 0.25 | G23: 0.25 | H23: 0.5 | I23: 0.5 | J23: 0.5 | K23: 1 | L23: 1 | M23: 1 | N23: 1 | O23: 1 | P23: 1
C24: Commissions Total (agg) | D24: =P24 -> 263350 | E24: =E18 -> 8100 | F24: =F18+E24 -> 17670 | G24: =G18+F24 -> 46660 | H24: =H18+G24 -> 56980 | I24: =I18+H24 -> 70270 | J24: =J18+I24 -> 105960 | K24: =K18+J24 -> 122250 | L24: =L18+K24 -> 143010 | M24: =M18+L24 -> 182230 | ... P24: =P18+O24 -> 263350 | R24: =R18 -> 46660 | S24: =R24+S18 -> 105960 | T24: =S24+T18 -> 182230 | U24: =T24+U18 -> 263350
C26: Commissions cashflow (new MRR only) | D26: =SUM(D27:D30) -> 187890 | E26: =Sum(E28:E30) -> 1362.5 | F26: =Sum(F28:F30) -> 2097.5 | G26: =Sum(G28:G30) -> 20905 | H26: =Sum(H28:H30) -> 4440 | I26: =Sum(I28:I30) -> 6797.5 | J26: =Sum(J28:J30) -> 23317.5 | K26: =Sum(K28:K30) -> 12125 | L26: =Sum(L28:L30) -> 16105 | ... P26: =Sum(P28:P30) -> 29800 | R26: =SUM(E26:G26) -> 24365 | S26: =SUM(H26:J26) -> 34555 | T26: =SUM(K26:M26) -> 59732.5 | U26: =SUM(N26:P26) -> 69237.5
C27: Commissions - Sales new | E27: =E12*'Partnership Info'!$D11 -> 612.5 | F27: =F12*'Partnership Info'!$D11 -> 735 | G27: =G12*'Partnership Info'!$D11 -> 857.5 | H27: =H12*'Partnership Info'!$D11 -> 735 | I27: =I12*'Partnership Info'!$D11 -> 857.5 | J27: =J12*'Partnership Info'!$D11 -> 1470 | K27: =K12*'Partnership Info'!$D11 -> 857.5 | L27: =L12*'Partnership Info'!$D11 -> 980 | ... P27: =P12*'Partnership Info'!$D11 -> 735
C28: Commissions - Sales agg | D28: =SUM(E28:P28) -> 71540 | E28: =SUM(E27) -> 612.5 | F28: =E28+F27 -> 1347.5 | G28: =F28+G27 -> 2205 | H28: =G28+H27 -> 2940 | I28: =H28+I27 -> 3797.5 | J28: =I28+J27 -> 5267.5 | K28: =J28+K27 -> 6125 | L28: =K28+L27 -> 7105 | M28: =L28+M27 -> 8452.5 | ... P28: =O28+P27 -> 12250 | R28: =SUM(E28:G28) -> 4165 | S28: =SUM(H28:J28) -> 12005 | T28: =SUM(K28:M28) -> 21682.5 | U28: =SUM(N27:P28) -> 37485
C29: B&I | D29: =SUM(E29:P29) -> 59350 | E29: =E20 -> 0 | F29: =F20 -> 0 | G29: =G20 -> 17200 | H29: =H20 -> 0 | I29: =I20 -> 0 | J29: =J20 -> 13550 | K29: =K20 -> 0 | L29: =L20 -> 0 | ... P29: =P20 -> 14550 | R29: =SUM(E29:G29) -> 17200 | S29: =SUM(H29:J29) -> 13550 | T29: =SUM(K29:M29) -> 14050 | U29: =SUM(N28:P29) -> 48237.5
C30: Onboardings | D30: =SUM(E30:P30) -> 57000 | E30: =E22 -> 750 | F30: =F22 -> 750 | G30: =G22 -> 1500 | H30: =H22 -> 1500 | I30: =I22 -> 3000 | J30: =J22 -> 4500 | K30: =K22 -> 6000 | L30: =L22 -> 9000 | ... P30: =P22 -> 3000 | R30: =SUM(E30:G30) -> 3000 | S30: =SUM(H30:J30) -> 9000 | T30: =SUM(K30:M30) -> 24000 | U30: =SUM(N29:P30) -> 35550
C32: Demand Generation Plan
C33: Actions # | D33: =SUM(E33:P33) -> 32 | E33: =COUNTIF('Demand Generation Plan'!$D$4:$D58,E3) -> 3 | F33: =COUNTIF('Demand Generation Plan'!$D$4:$D58,F3) -> 3 | G33: =COUNTIF('Demand Generation Plan'!$D$4:$D58,G3) -> 2 | H33: =COUNTIF('Demand Generation Plan'!$D$4:$D58,H3) -> 3 | I33: =COUNTIF('Demand Generation Plan'!$D$4:$D58,I3) -> 3 | J33: =COUNTIF('Demand Generation Plan'!$D$4:$D58,J3) -> 2 | K33: =COUNTIF('Demand Generation Plan'!$D$4:$D58,K3) -> 4 | L33: =COUNTIF('Demand Generation Plan'!$D$4:$D58,L3) -> 2 | ... P33: =COUNTIF('Demand Generation Plan'!$D$4:$D58,P3) -> 2 | R33: =SUM(E33:G33) -> 8 | S33: =SUM(H33:J33) -> 8 | T33: =SUM(K33:M33) -> 8 | U33: =SUM(N32:P33) -> 8
C34: Budget | D34: =SUM(E34:P34) -> -48700 | E34: =-sumif('Demand Generation Plan'!$D$4:$D58,E3,'Demand Generation Plan'!$F$4:$F58) -> -1700 | F34: =-sumif('Demand Generation Plan'!$D$4:$D58,F3,'Demand Generation Plan'!$F$4:$F58) -> -11000 | G34: =-sumif('Demand Generation Plan'!$D$4:$D58,G3,'Demand Generation Plan'!$F$4:$F58) -> -1200 | H34: =-sumif('Demand Generation Plan'!$D$4:$D58,H3,'Demand Generation Plan'!$F$4:$F58) -> -1700 | I34: =-sumif('Demand Generation Plan'!$D$4:$D58,I3,'Demand Generation Plan'!$F$4:$F58) -> -8700 | J34: =-sumif('Demand Generation Plan'!$D$4:$D58,J3,'Demand Generation Plan'!$F$4:$F58) -> -1200 | K34: =-sumif('Demand Generation Plan'!$D$4:$D58,K3,'Demand Generation Plan'!$F$4:$F58) -> -9200 | L34: =-sumif('Demand Generation Plan'!$D$4:$D58,L3,'Demand Generation Plan'!$F$4:$F58) -> -1200 | ... P34: =-sumif('Demand Generation Plan'!$D$4:$D58,P3,'Demand Generation Plan'!$F$4:$F58) -> -1200 | R34: =SUM(E34:G34) -> -13900 | S34: =SUM(H34:J34) -> -11600 | T34: =SUM(K34:M34) -> -11600 | U34: =SUM(N33:P34) -> -11592
C36: Headcount | D36: =D37+D38 -> -170600 | E36: =E37+E38 -> -14216.667 | F36: =F37+F38 -> -14216.667 | G36: =G37+G38 -> -14216.667 | H36: =H37+H38 -> -14216.667 | I36: =I37+I38 -> -14216.667 | J36: =J37+J38 -> -14216.667 | K36: =K37+K38 -> -14216.667 | ... P36: =P37+P38 -> -14216.667 | R36: =SUM(E36:G36) -> -42650 | S36: =SUM(H36:J36) -> -42650 | T36: =SUM(K36:M36) -> -42650 | U36: =SUM(N36:P36) -> -42650
C37: Salary | D37: =SUM(E37:P37) -> -170600 | E37: =Headcount!G4 -> -14216.667 | F37: =Headcount!H4 -> -14216.667 | G37: =Headcount!I4 -> -14216.667 | H37: =Headcount!J4 -> -14216.667 | I37: =Headcount!K4 -> -14216.667 | J37: =Headcount!L4 -> -14216.667 | K37: =Headcount!M4 -> -14216.667 | L37: =Headcount!N4 -> -14216.667 | ... P37: =Headcount!R4 -> -14216.667 | R37: =SUM(E37:G37) -> -42650 | S37: =SUM(H37:J37) -> -42650 | T37: =SUM(K37:M37) -> -42650 | U37: =SUM(N37:P37) -> -42650
C38: Factorial Support | D38: =SUM(E38:P38) -> 0 | E38: =Headcount!G5 -> 0 | F38: =Headcount!H5 -> 0 | G38: =Headcount!I5 -> 0 | H38: =Headcount!J5 -> 0 | I38: =Headcount!K5 -> 0 | J38: =Headcount!L5 -> 0 | K38: =Headcount!M5 -> 0 | L38: =Headcount!N5 -> 0 | ... P38: =Headcount!R5 -> 0 | R38: =SUM(E38:G38) -> 0 | S38: =SUM(H38:J38) -> 0 | T38: =SUM(K38:M38) -> 0 | U38: =SUM(N37:P38) -> -42650
C39: Fixed salary | D39: =SUM(E39:P39) -> -95000 | E39: =-14000/7*1.25-25000*1.25/12-27000*1.25/12 -> -7916.6667 | F39: =-14000/7*1.25-25000*1.25/12-27000*1.25/12 -> -7916.6667 | G39: =-14000/7*1.25-25000*1.25/12-27000*1.25/12 -> -7916.6667 | H39: =-14000/7*1.25-25000*1.25/12-27000*1.25/12 -> -7916.6667 | I39: =-14000/7*1.25-25000*1.25/12-27000*1.25/12 -> -7916.6667 | J39: =-14000/7*1.25-25000*1.25/12-27000*1.25/12 -> -7916.6667 | K39: =-14000/7*1.25-25000*1.25/12-27000*1.25/12 -> -7916.6667 | L39: =-14000/7*1.25-25000*1.25/12-27000*1.25/12 -> -7916.6667 | ... P39: =-14000/7*1.25-25000*1.25/12-27000*1.25/12 -> -7916.6667 | R39: =SUM(E39:G39) -> -23750 | S39: =SUM(H39:J39) -> -23750 | T39: =SUM(K39:M39) -> -23750 | U39: =SUM(N39:P39) -> -23750
C40: Variable salary | D40: =SUM(E40:P40) -> -75600 | E40: =E37-E39 -> -6300 | F40: =F37-F39 -> -6300 | G40: =G37-G39 -> -6300 | H40: =H37-H39 -> -6300 | I40: =I37-I39 -> -6300 | J40: =J37-J39 -> -6300 | K40: =K37-K39 -> -6300 | L40: =L37-L39 -> -6300 | ... P40: =P37-P39 -> -6300 | R40: =SUM(E40:G40) -> -18900 | S40: =SUM(H40:J40) -> -18900 | T40: =SUM(K40:M40) -> -18900 | U40: =SUM(N40:P40) -> -18900
C42: Total Commissions + Incentives | D42: =SUM(E42:P42) -> 263350 | E42: =E18 -> 8100 | F42: =F18 -> 9570 | G42: =G18 -> 28990 | H42: =H18 -> 10320 | I42: =I18 -> 13290 | J42: =J18 -> 35690 | K42: =K18 -> 16290 | L42: =L18 -> 20760 | ... P42: =P18 -> 26370 | R42: =SUM(E42:G42) -> 46660 | S42: =SUM(H42:J42) -> 59300 | T42: =SUM(K42:M42) -> 76270 | U42: =SUM(N41:P42) -> 81120
C44: Total Invested | D44: =SUM(E44:P44) -> -219300 | E44: =E36+E34 -> -15916.667 | F44: =F36+F34 -> -25216.667 | G44: =G36+G34 -> -15416.667 | H44: =H36+H34 -> -15916.667 | I44: =I36+I34 -> -22916.667 | J44: =J36+J34 -> -15416.667 | K44: =K36+K34 -> -23416.667 | L44: =L36+L34 -> -15416.667 | ... P44: =P36+P34 -> -15416.667 | R44: =SUM(E44:G44) -> -56550 | S44: =SUM(H44:J44) -> -54250 | T44: =SUM(K44:M44) -> -54250 | U44: =SUM(N43:P44) -> -54250
C46: Total Balance (12-month P&L) | D46: =SUM(E46:P46) -> 44050 | E46: =E42+E44 -> -7816.6667 | F46: =F42+F44 -> -15646.667 | G46: =G42+G44 -> 13573.333 | H46: =H42+H44 -> -5596.6667 | I46: =I42+I44 -> -9626.6667 | J46: =J42+J44 -> 20273.333 | K46: =K42+K44 -> -7126.6667 | L46: =L42+L44 -> 5343.3333 | ... P46: =P42+P44 -> 10953.333 | R46: =SUM(E46:G46) -> -9890 | S46: =SUM(H46:J46) -> 5050 | T46: =SUM(K46:M46) -> 22020 | U46: =SUM(N45:P46) -> 26870
C48: Approx net cashflow (sales FS only) | D48: =SUM(E48:P48) -> 44190 | E48: =E26+E34+E39 -> -8254.1667 | F48: =F26+F34+F39 -> -16819.167 | G48: =G26+G34+G39 -> 11788.333 | H48: =H26+H34+H39 -> -5176.6667 | I48: =I26+I34+I39 -> -9819.1667 | J48: =J26+J34+J39 -> 14200.833 | K48: =K26+K34+K39 -> -4991.6667 | L48: =L26+L34+L39 -> 6988.3333 | ... P48: =P26+P34+P39 -> 20683.333 | R48: =SUM(E48:G48) -> -13285 | S48: =SUM(H48:J48) -> -795 | T48: =SUM(K48:M48) -> 24382.5 | U48: =SUM(N47:P48) -> 33887.5
C49: DEMGEN PLAN CHECK | E49: 1 | F49: 2 | G49: 3 | H49: 4 | I49: 5 | J49: 6 | K49: 7 | L49: 8 | M49: 9 | N49: 10 | O49: 11 | P49: 12
E50: January | F50: February | G50: March | H50: April | I50: May | J50: June | K50: July | L50: August | M50: September | N50: October | O50: November | P50: December
E51: =SUMPRODUCT((IFERROR(MATCH('Demand Generation Plan'!$D$4:$D999, $E$50:$P$50, 0),"") = MOD(E$49 - 'Demand Generation Plan'!$H$1 - 1, 12) + 1) * ('Demand Generation Plan'!$D$4:$D999 <> ""), 'Demand Generation Plan'!$H$4:$H999) + SUMPRODUCT((IFERROR(MATCH('Demand Generation Plan'!$D$4:$D999, $E$50:$P$50, 0),"") = MOD(E$49 - 'Demand Generation Plan'!$I$1 - 1, 12) + 1) * ('Demand Generation Plan'!$D$4:$D999 <> ""), 'Demand Generation Plan'!$I$4:$I999) + SUMPRODUCT((IFERROR(MATCH('Demand Generation Plan'!$D$4:$D999, $E$50:$P$50, 0),"") = MOD(E$49 - 'Demand Generation Plan'!$J$1 - 1, 12) + 1) * ('Demand Generation Plan'!$D$4:$D999 <> ""), 'Demand Generation Plan'!$J$4:$J999) -> 10 | F51: =SUMPRODUCT((IFERROR(MATCH('Demand Generation Plan'!$D$4:$D999, $E$50:$P$50, 0),"") = MOD(F$49 - 'Demand Generation Plan'!$H$1 - 1, 12) + 1) * ('Demand Generation Plan'!$D$4:$D999 <> ""), 'Demand Generation Plan'!$H$4:$H999) + SUMPRODUCT((IFERROR(MATCH('Demand Generation Plan'!$D$4:$D999, $E$50:$P$50, 0),"") = MOD(F$49 - 'Demand Generation Plan'!$I$1 - 1, 12) + 1) * ('Demand Generation Plan'!$D$4:$D999 <> ""), 'Demand Generation Plan'!$I$4:$I999) + SUMPRODUCT((IFERROR(MATCH('Demand Generation Plan'!$D$4:$D999, $E$50:$P$50, 0),"") = MOD(F$49 - 'Demand Generation Plan'!$J$1 - 1, 12) + 1) * ('Demand Generation Plan'!$D$4:$D999 <> ""), 'Demand Generation Plan'!$J$4:$J999) -> 11 | G51: =SUMPRODUCT((IFERROR(MATCH('Demand Generation Plan'!$D$4:$D999, $E$50:$P$50, 0),"") = MOD(G$49 - 'Demand Generation Plan'!$H$1 - 1, 12) + 1) * ('Demand Generation Plan'!$D$4:$D999 <> ""), 'Demand Generation Plan'!$H$4:$H999) + SUMPRODUCT((IFERROR(MATCH('Demand Generation Plan'!$D$4:$D999, $E$50:$P$50, 0),"") = MOD(G$49 - 'Demand Generation Plan'!$I$1 - 1, 12) + 1) * ('Demand Generation Plan'!$D$4:$D999 <> ""), 'Demand Generation Plan'!$I$4:$I999) + SUMPRODUCT((IFERROR(MATCH('Demand Generation Plan'!$D$4:$D999, $E$50:$P$50, 0),"") = MOD(G$49 - 'Demand Generation Plan'!$J$1 - 1, 12) + 1) * ('Demand Generation Plan'!$D$4:$D999 <> ""), 'Demand Generation Plan'!$J$4:$J999) -> 34 | H51: =SUMPRODUCT((IFERROR(MATCH('Demand Generation Plan'!$D$4:$D999, $E$50:$P$50, 0),"") = MOD(H$49 - 'Demand Generation Plan'!$H$1 - 1, 12) + 1) * ('Demand Generation Plan'!$D$4:$D999 <> ""), 'Demand Generation Plan'!$H$4:$H999) + SUMPRODUCT((IFERROR(MATCH('Demand Generation Plan'!$D$4:$D999, $E$50:$P$50, 0),"") = MOD(H$49 - 'Demand Generation Plan'!$I$1 - 1, 12) + 1) * ('Demand Generation Plan'!$D$4:$D999 <> ""), 'Demand Generation Plan'!$I$4:$I999) + SUMPRODUCT((IFERROR(MATCH('Demand Generation Plan'!$D$4:$D999, $E$50:$P$50, 0),"") = MOD(H$49 - 'Demand Generation Plan'!$J$1 - 1, 12) + 1) * ('Demand Generation Plan'!$D$4:$D999 <> ""), 'Demand Generation Plan'!$J$4:$J999) -> 12 | I51: =SUMPRODUCT((IFERROR(MATCH('Demand Generation Plan'!$D$4:$D999, $E$50:$P$50, 0),"") = MOD(I$49 - 'Demand Generation Plan'!$H$1 - 1, 12) + 1) * ('Demand Generation Plan'!$D$4:$D999 <> ""), 'Demand Generation Plan'!$H$4:$H999) + SUMPRODUCT((IFERROR(MATCH('Demand Generation Plan'!$D$4:$D999, $E$50:$P$50, 0),"") = MOD(I$49 - 'Demand Generation Plan'!$I$1 - 1, 12) + 1) * ('Demand Generation Plan'!$D$4:$D999 <> ""), 'Demand Generation Plan'!$I$4:$I999) + SUMPRODUCT((IFERROR(MATCH('Demand Generation Plan'!$D$4:$D999, $E$50:$P$50, 0),"") = MOD(I$49 - 'Demand Generation Plan'!$J$1 - 1, 12) + 1) * ('Demand Generation Plan'!$D$4:$D999 <> ""), 'Demand Generation Plan'!$J$4:$J999) -> 22 | J51: =SUMPRODUCT((IFERROR(MATCH('Demand Generation Plan'!$D$4:$D999, $E$50:$P$50, 0),"") = MOD(J$49 - 'Demand Generation Plan'!$H$1 - 1, 12) + 1) * ('Demand Generation Plan'!$D$4:$D999 <> ""), 'Demand Generation Plan'!$H$4:$H999) + SUMPRODUCT((IFERROR(MATCH('Demand Generation Plan'!$D$4:$D999, $E$50:$P$50, 0),"") = MOD(J$49 - 'Demand Generation Plan'!$I$1 - 1, 12) + 1) * ('Demand Generation Plan'!$D$4:$D999 <> ""), 'Demand Generation Plan'!$I$4:$I999) + SUMPRODUCT((IFERROR(MATCH('Demand Generation Plan'!$D$4:$D999, $E$50:$P$50, 0),"") = MOD(J$49 - 'Demand Generation Plan'!$J$1 - 1, 12) + 1) * ('Demand Generation Plan'!$D$4:$D999 <> ""), 'Demand Generation Plan'!$J$4:$J999) -> 17 | K51: =SUMPRODUCT((IFERROR(MATCH('Demand Generation Plan'!$D$4:$D999, $E$50:$P$50, 0),"") = MOD(K$49 - 'Demand Generation Plan'!$H$1 - 1, 12) + 1) * ('Demand Generation Plan'!$D$4:$D999 <> ""), 'Demand Generation Plan'!$H$4:$H999) + SUMPRODUCT((IFERROR(MATCH('Demand Generation Plan'!$D$4:$D999, $E$50:$P$50, 0),"") = MOD(K$49 - 'Demand Generation Plan'!$I$1 - 1, 12) + 1) * ('Demand Generation Plan'!$D$4:$D999 <> ""), 'Demand Generation Plan'!$I$4:$I999) + SUMPRODUCT((IFERROR(MATCH('Demand Generation Plan'!$D$4:$D999, $E$50:$P$50, 0),"") = MOD(K$49 - 'Demand Generation Plan'!$J$1 - 1, 12) + 1) * ('Demand Generation Plan'!$D$4:$D999 <> ""), 'Demand Generation Plan'!$J$4:$J999) -> 23 | L51: =SUMPRODUCT((IFERROR(MATCH('Demand Generation Plan'!$D$4:$D999, $E$50:$P$50, 0),"") = MOD(L$49 - 'Demand Generation Plan'!$H$1 - 1, 12) + 1) * ('Demand Generation Plan'!$D$4:$D999 <> ""), 'Demand Generation Plan'!$H$4:$H999) + SUMPRODUCT((IFERROR(MATCH('Demand Generation Plan'!$D$4:$D999, $E$50:$P$50, 0),"") = MOD(L$49 - 'Demand Generation Plan'!$I$1 - 1, 12) + 1) * ('Demand Generation Plan'!$D$4:$D999 <> ""), 'Demand Generation Plan'!$I$4:$I999) + SUMPRODUCT((IFERROR(MATCH('Demand Generation Plan'!$D$4:$D999, $E$50:$P$50, 0),"") = MOD(L$49 - 'Demand Generation Plan'!$J$1 - 1, 12) + 1) * ('Demand Generation Plan'!$D$4:$D999 <> ""), 'Demand Generation Plan'!$J$4:$J999) -> 18 | ... P51: =SUMPRODUCT((IFERROR(MATCH('Demand Generation Plan'!$D$4:$D999, $E$50:$P$50, 0),"") = MOD(P$49 - 'Demand Generation Plan'!$H$1 - 1, 12) + 1) * ('Demand Generation Plan'!$D$4:$D999 <> ""), 'Demand Generation Plan'!$H$4:$H999) + SUMPRODUCT((IFERROR(MATCH('Demand Generation Plan'!$D$4:$D999, $E$50:$P$50, 0),"") = MOD(P$49 - 'Demand Generation Plan'!$I$1 - 1, 12) + 1) * ('Demand Generation Plan'!$D$4:$D999 <> ""), 'Demand Generation Plan'!$I$4:$I999) + SUMPRODUCT((IFERROR(MATCH('Demand Generation Plan'!$D$4:$D999, $E$50:$P$50, 0),"") = MOD(P$49 - 'Demand Generation Plan'!$J$1 - 1, 12) + 1) * ('Demand Generation Plan'!$D$4:$D999 <> ""), 'Demand Generation Plan'!$J$4:$J999) -> 14

Sheet Demand Generation Plan
H1: 0 | I1: 1 | J1: 2 | M1: 0 | N1: 1 | O1: 2
C2: Planned Actions | L2: Results | U2: Analysis
B3: Action Name | C3: Quarter | D3: Month | E3: Type of action | F3: Planned Cost | G3: Demos Goal | H3: M0 | I3: M1 | J3: M2 | K3: Cost per demo | L3: Demos Actual | M3: M0 | N3: M1 | O3: M2 | P3: Leads Actual | Q3: Clients Won | R3: Total Cost | S3: Partner Actual Cost | T3: MRR won | U3: ROI (on ARR) | V3: % Lead to Demo | W3: % Demo to Won | X3: CAC | Y3: Cost per Demo
A4: =iferror(DATEVALUE(D4 & " 1"),"") -> 45658 | B4: Outbound Q1 | C4: =IF(D4="","", IF(A4<DATE(2025, 4, 1),"Q1",if(A4<DATE(2025, 7, 1),"Q2",IF(A4<DATE(2025, 10, 1),"Q3","Q4")))) -> Q1 | D4: January | E4: Outbound Actions | F4: 500 | G4: 9 | H4: 3 | I4: 3 | J4: 3 | K4: =IFERROR(F4/G4,"") -> 55.555556 | L4: =SUM(M4:O4) -> 0 | M4: 0 | N4: 0 | O4: 0 | P4: 0 | Q4: 0 | R4: 0 | T4: 0 | U4: =if(T4<=0,"",((T4*12)-R4)/R4) | V4: =iferror(L4/P4,"") | W4: =iferror(Q4/L4,"") | X4: =iferror(R4/Q4,"") | Y4: =iferror(R4/L4,"")
A5: =iferror(DATEVALUE(D5 & " 1"),"") -> 45748 | B5: Outbound Q2 | C5: =IF(D5="","", IF(A5<DATE(2025, 4, 1),"Q1",if(A5<DATE(2025, 7, 1),"Q2",IF(A5<DATE(2025, 10, 1),"Q3","Q4")))) -> Q2 | D5: April | E5: Outbound Actions | F5: 500 | G5: =SUM(H5:J5) -> 12 | H5: 4 | I5: 4 | J5: 4 | K5: =IFERROR(F5/G5,"") -> 41.666667 | L5: =SUM(M5:O5) -> 0 | U5: =if(T5<=0,"",((T5*12)-F5)/F5) | V5: =iferror(L5/P5,"") | W5: =iferror(Q5/L5,"") | X5: =iferror(R5/Q5,"") | Y5: =iferror(R5/L5,"")
A6: =iferror(DATEVALUE(D6 & " 1"),"") -> 45839 | B6: Outbound Q3 | C6: =IF(D6="","", IF(A6<DATE(2025, 4, 1),"Q1",if(A6<DATE(2025, 7, 1),"Q2",IF(A6<DATE(2025, 10, 1),"Q3","Q4")))) -> Q3 | D6: July | E6: Outbound Actions | F6: 500 | G6: =SUM(H6:J6) -> 15 | H6: 5 | I6: 5 | J6: 5 | K6: =IFERROR(F6/G6,"") -> 33.333333 | L6: =SUM(M6:O6) -> 0 | U6: =if(T6<=0,"",((T6*12)-F6)/F6) | V6: =iferror(L6/P6,"") | W6: =iferror(Q6/L6,"") | X6: =iferror(R6/Q6,"") | Y6: =iferror(R6/L6,"")
A7: =iferror(DATEVALUE(D7 & " 1"),"") -> 45931 | B7: Outbound Q4 | C7: =IF(D7="","", IF(A7<DATE(2025, 4, 1),"Q1",if(A7<DATE(2025, 7, 1),"Q2",IF(A7<DATE(2025, 10, 1),"Q3","Q4")))) -> Q4 | D7: October | E7: Outbound Actions | F7: 500 | G7: =SUM(H7:J7) -> 18 | H7: 6 | I7: 6 | J7: 6 | K7: =IFERROR(F7/G7,"") -> 27.777778 | L7: =SUM(M7:O7) -> 0 | U7: =if(T7<=0,"",((T7*12)-F7)/F7) | V7: =iferror(L7/P7,"") | W7: =iferror(Q7/L7,"") | X7: =iferror(R7/Q7,"") | Y7: =iferror(R7/L7,"")
A8: =iferror(DATEVALUE(D8 & " 1"),"") -> 45658 | B8: Webinar | C8: =IF(D8="","", IF(A8<DATE(2025, 4, 1),"Q1",if(A8<DATE(2025, 7, 1),"Q2",IF(A8<DATE(2025, 10, 1),"Q3","Q4")))) -> Q1 | D8: January | E8: Webinar | F8: 200 | G8: 5 | H8: 5 | K8: =IFERROR(F8/G8,"") -> 40 | L8: =SUM(M8:O8) -> 0 | U8: =if(T8<=0,"",((T8*12)-F8)/F8) | V8: =iferror(L8/P8,"") | W8: =iferror(Q8/L8,"") | X8: =iferror(R8/Q8,"") | Y8: =iferror(R8/L8,"")
A9: =iferror(DATEVALUE(D9 & " 1"),"") -> 45689 | B9: Webinar | C9: =IF(D9="","", IF(A9<DATE(2025, 4, 1),"Q1",if(A9<DATE(2025, 7, 1),"Q2",IF(A9<DATE(2025, 10, 1),"Q3","Q4")))) -> Q1 | D9: February | K9: =IFERROR(F9/G9,"") | L9: =SUM(M9:O9) -> 0 | U9: =if(T9<=0,"",((T9*12)-F9)/F9) | V9: =iferror(L9/P9,"") | W9: =iferror(Q9/L9,"") | X9: =iferror(R9/Q9,"") | Y9: =iferror(R9/L9,"")
A10: =iferror(DATEVALUE(D10 & " 1"),"") -> 45717 | B10: Webinar | C10: =IF(D10="","", IF(A10<DATE(2025, 4, 1),"Q1",if(A10<DATE(2025, 7, 1),"Q2",IF(A10<DATE(2025, 10, 1),"Q3","Q4")))) -> Q1 | D10: March | E10: Webinar | F10: 200 | G10: 2 | H10: 2 | K10: =IFERROR(F10/G10,"") -> 100 | L10: =SUM(M10:O10) -> 0 | U10: =if(T10<=0,"",((T10*12)-F10)/F10) | V10: =iferror(L10/P10,"") | W10: =iferror(Q10/L10,"") | X10: =iferror(R10/Q10,"") | Y10: =iferror(R10/L10,"")
A11: =iferror(DATEVALUE(D11 & " 1"),"") -> 45748 | B11: Webinar | C11: =IF(D11="","", IF(A11<DATE(2025, 4, 1),"Q1",if(A11<DATE(2025, 7, 1),"Q2",IF(A11<DATE(2025, 10, 1),"Q3","Q4")))) -> Q2 | D11: April | E11: Webinar | F11: 200 | G11: 3 | H11: 3 | K11: =IFERROR(F11/G11,"") -> 66.666667 | L11: =SUM(M11:O11) -> 0 | U11: =if(T11<=0,"",((T11*12)-F11)/F11) | V11: =iferror(L11/P11,"") | W11: =iferror(Q11/L11,"") | X11: =iferror(R11/Q11,"") | Y11: =iferror(R11/L11,"")
A12: =iferror(DATEVALUE(D12 & " 1"),"") -> 45778 | B12: Webinar | C12: =IF(D12="","", IF(A12<DATE(2025, 4, 1),"Q1",if(A12<DATE(2025, 7, 1),"Q2",IF(A12<DATE(2025, 10, 1),"Q3","Q4")))) -> Q2 | D12: May | E12: Webinar | F12: 200 | G12: 3 | H12: 3 | K12: =IFERROR(F12/G12,"") -> 66.666667 | L12: =SUM(M12:O12) -> 0 | U12: =if(T12<=0,"",((T12*12)-F12)/F12) | V12: =iferror(L12/P12,"") | W12: =iferror(Q12/L12,"") | X12: =iferror(R12/Q12,"") | Y12: =iferror(R12/L12,"")
A13: =iferror(DATEVALUE(D13 & " 1"),"") -> 45809 | B13: Webinar | C13: =IF(D13="","", IF(A13<DATE(2025, 4, 1),"Q1",if(A13<DATE(2025, 7, 1),"Q2",IF(A13<DATE(2025, 10, 1),"Q3","Q4")))) -> Q2 | D13: June | E13: Webinar | F13: 200 | G13: 3 | H13: 3 | K13: =IFERROR(F13/G13,"") -> 66.666667 | L13: =SUM(M13:O13) -> 0 | U13: =if(T13<=0,"",((T13*12)-F13)/F13) | V13: =iferror(L13/P13,"") | W13: =iferror(Q13/L13,"") | X13: =iferror(R13/Q13,"") | Y13: =iferror(R13/L13,"")
A14: =iferror(DATEVALUE(D14 & " 1"),"") -> 45839 | B14: Webinar | C14: =IF(D14="","", IF(A14<DATE(2025, 4, 1),"Q1",if(A14<DATE(2025, 7, 1),"Q2",IF(A14<DATE(2025, 10, 1),"Q3","Q4")))) -> Q3 | D14: July | E14: Webinar | F14: 200 | G14: 3 | H14: 3 | K14: =IFERROR(F14/G14,"") -> 66.666667 | L14: =SUM(M14:O14) -> 0 | U14: =if(T14<=0,"",((T14*12)-F14)/F14) | V14: =iferror(L14/P14,"") | W14: =iferror(Q14/L14,"") | X14: =iferror(R14/Q14,"") | Y14: =iferror(R14/L14,"")
A15: =iferror(DATEVALUE(D15 & " 1"),"") -> 45870 | B15: Webinar | C15: =IF(D15="","", IF(A15<DATE(2025, 4, 1),"Q1",if(A15<DATE(2025, 7, 1),"Q2",IF(A15<DATE(2025, 10, 1),"Q3","Q4")))) -> Q3 | D15: August | E15: Webinar | F15: 200 | G15: 3 | H15: 3 | K15: =IFERROR(F15/G15,"") -> 66.666667 | L15: =SUM(M15:O15) -> 0 | U15: =if(T15<=0,"",((T15*12)-F15)/F15) | V15: =iferror(L15/P15,"") | W15: =iferror(Q15/L15,"") | X15: =iferror(R15/Q15,"") | Y15: =iferror(R15/L15,"")
A16: =iferror(DATEVALUE(D16 & " 1"),"") -> 45901 | B16: Webinar | C16: =IF(D16="","", IF(A16<DATE(2025, 4, 1),"Q1",if(A16<DATE(2025, 7, 1),"Q2",IF(A16<DATE(2025, 10, 1),"Q3","Q4")))) -> Q3 | D16: September | E16: Webinar | F16: 200 | G16: 5 | H16: 5 | K16: =IFERROR(F16/G16,"") -> 40 | L16: =SUM(M16:O16) -> 0 | U16: =if(T16<=0,"",((T16*12)-F16)/F16) | V16: =iferror(L16/P16,"") | W16: =iferror(Q16/L16,"") | X16: =iferror(R16/Q16,"") | Y16: =iferror(R16/L16,"")
A17: =iferror(DATEVALUE(D17 & " 1"),"") -> 45931 | B17: Webinar | C17: =IF(D17="","", IF(A17<DATE(2025, 4, 1),"Q1",if(A17<DATE(2025, 7, 1),"Q2",IF(A17<DATE(2025, 10, 1),"Q3","Q4")))) -> Q4 | D17: October | E17: Webinar | F17: 200 | G17: 3 | H17: 3 | K17: =IFERROR(F17/G17,"") -> 66.666667 | L17: =SUM(M17:O17) -> 0 | U17: =if(T17<=0,"",((T17*12)-F17)/F17) | V17: =iferror(L17/P17,"") | W17: =iferror(Q17/L17,"") | X17: =iferror(R17/Q17,"") | Y17: =iferror(R17/L17,"")
A18: =iferror(DATEVALUE(D18 & " 1"),"") -> 45962 | B18: Webinar | C18: =IF(D18="","", IF(A18<DATE(2025, 4, 1),"Q1",if(A18<DATE(2025, 7, 1),"Q2",IF(A18<DATE(2025, 10, 1),"Q3","Q4")))) -> Q4 | D18: November | E18: Webinar | F18: 200 | G18: 3 | H18: 3 | K18: =IFERROR(F18/G18,"") -> 66.666667 | L18: =SUM(M18:O18) -> 0 | U18: =if(T18<=0,"",((T18*12)-F18)/F18) | V18: =iferror(L18/P18,"") | W18: =iferror(Q18/L18,"") | X18: =iferror(R18/Q18,"") | Y18: =iferror(R18/L18,"")
A19: =iferror(DATEVALUE(D19 & " 1"),"") -> 45992 | B19: Webinar | C19: =IF(D19="","", IF(A19<DATE(2025, 4, 1),"Q1",if(A19<DATE(2025, 7, 1),"Q2",IF(A19<DATE(2025, 10, 1),"Q3","Q4")))) -> Q4 | D19: December | E19: Webinar | F19: 200 | G19: 3 | H19: 3 | K19: =IFERROR(F19/G19,"") -> 66.666667 | L19: =SUM(M19:O19) -> 0 | U19: =if(T19<=0,"",((T19*12)-F19)/F19) | V19: =iferror(L19/P19,"") | W19: =iferror(Q19/L19,"") | X19: =iferror(R19/Q19,"") | Y19: =iferror(R19/L19,"")
A20: =iferror(DATEVALUE(D20 & " 1"),"") -> 45689 | B20: Roadshow | C20: =IF(D20="","", IF(A20<DATE(2025, 4, 1),"Q1",if(A20<DATE(2025, 7, 1),"Q2",IF(A20<DATE(2025, 10, 1),"Q3","Q4")))) -> Q1 | D20: February | E20: Co-hosted | F20: 10000 | G20: =SUM(H20:J20) -> 30 | H20: 5 | I20: 25 | K20: =IFERROR(F20/G20,"") -> 333.33333 | L20: =SUM(M20:O20) -> 0 | U20: =if(T20<=0,"",((T20*12)-#REF!)/#REF!) | V20: =iferror(L20/P20,"") | W20: =iferror(Q20/L20,"") | X20: =iferror(R20/Q20,"") | Y20: =iferror(R20/L20,"")
A21: =iferror(DATEVALUE(D21 & " 1"),"") -> 45778 | B21: Event 2 | C21: =IF(D21="","", IF(A21<DATE(2025, 4, 1),"Q1",if(A21<DATE(2025, 7, 1),"Q2",IF(A21<DATE(2025, 10, 1),"Q3","Q4")))) -> Q2 | D21: May | E21: Fair / Trade Show | F21: 7500 | G21: =SUM(H21:J21) -> 15 | H21: 10 | I21: 5 | K21: =IFERROR(F21/G21,"") -> 500 | L21: =SUM(M21:O21) -> 0 | U21: =if(T21<=0,"",((T21*12)-F21)/F21) | V21: =iferror(L21/P21,"") | W21: =iferror(Q21/L21,"") | X21: =iferror(R21/Q21,"") | Y21: =iferror(R21/L21,"")
A22: =iferror(DATEVALUE(D22 & " 1"),"") -> 45839 | B22: Event 3 | C22: =IF(D22="","", IF(A22<DATE(2025, 4, 1),"Q1",if(A22<DATE(2025, 7, 1),"Q2",IF(A22<DATE(2025, 10, 1),"Q3","Q4")))) -> Q3 | D22: July | E22: Fair / Trade Show | F22: 7500 | G22: =SUM(H22:J22) -> 15 | H22: 10 | I22: 5 | K22: =IFERROR(F22/G22,"") -> 500 | L22: =SUM(M22:O22) -> 0 | U22: =if(T22<=0,"",((T22*12)-F22)/F22) | V22: =iferror(L22/P22,"") | W22: =iferror(Q22/L22,"") | X22: =iferror(R22/Q22,"") | Y22: =iferror(R22/L22,"")
A23: =iferror(DATEVALUE(D23 & " 1"),"") -> 45931 | B23: Event 4 | C23: =IF(D23="","", IF(A23<DATE(2025, 4, 1),"Q1",if(A23<DATE(2025, 7, 1),"Q2",IF(A23<DATE(2025, 10, 1),"Q3","Q4")))) -> Q4 | D23: October | E23: Fair / Trade Show | F23: 7500 | G23: =SUM(H23:J23) -> 15 | H23: 10 | I23: 5 | K23: =IFERROR(F23/G23,"") -> 500 | L23: =SUM(M23:O23) -> 0 | U23: =if(T23<=0,"",((T23*12)-F23)/F23) | V23: =iferror(L23/P23,"") | W23: =iferror(Q23/L23,"") | X23: =iferror(R23/Q23,"") | Y23: =iferror(R23/L23,"")
A24: =iferror(DATEVALUE(D24 & " 1"),"") | C24: =IF(D24="","", IF(A24<DATE(2025, 4, 1),"Q1",if(A24<DATE(2025, 7, 1),"Q2",IF(A24<DATE(2025, 10, 1),"Q3","Q4")))) | K24: =IFERROR(F24/G24,"") | L24: =SUM(M24:O24) -> 0 | U24: =if(T24<=0,"",((T24*12)-F24)/F24) | V24: =iferror(L24/P24,"") | W24: =iferror(Q24/L24,"") | X24: =iferror(R24/Q24,"") | Y24: =iferror(R24/L24,"")
A25: =iferror(DATEVALUE(D25 & " 1"),"") -> 45658 | B25: Paid | C25: =IF(D25="","", IF(A25<DATE(2025, 4, 1),"Q1",if(A25<DATE(2025, 7, 1),"Q2",IF(A25<DATE(2025, 10, 1),"Q3","Q4")))) -> Q1 | D25: January | E25: Other Inbound | F25: 1000 | G25: =SUM(H25:J25) -> 2 | H25: 2 | K25: =IFERROR(F25/G25,"") -> 500 | L25: =SUM(M25:O25) -> 0 | U25: =if(T25<=0,"",((T25*12)-F25)/F25) | V25: =iferror(L25/P25,"") | W25: =iferror(Q25/L25,"") | X25: =iferror(R25/Q25,"") | Y25: =iferror(R25/L25,"")
A26: =iferror(DATEVALUE(D26 & " 1"),"") -> 45689 | B26: Paid | C26: =IF(D26="","", IF(A26<DATE(2025, 4, 1),"Q1",if(A26<DATE(2025, 7, 1),"Q2",IF(A26<DATE(2025, 10, 1),"Q3","Q4")))) -> Q1 | D26: February | E26: Other Inbound | F26: 1000 | G26: =SUM(H26:J26) -> 3 | H26: 3 | K26: =IFERROR(F26/G26,"") -> 333.33333 | L26: =SUM(M26:O26) -> 0 | U26: =if(T26<=0,"",((T26*12)-F26)/F26) | V26: =iferror(L26/P26,"") | W26: =iferror(Q26/L26,"") | X26: =iferror(R26/Q26,"") | Y26: =iferror(R26/L26,"")
A27: =iferror(DATEVALUE(D27 & " 1"),"") -> 45717 | B27: Paid | C27: =IF(D27="","", IF(A27<DATE(2025, 4, 1),"Q1",if(A27<DATE(2025, 7, 1),"Q2",IF(A27<DATE(2025, 10, 1),"Q3","Q4")))) -> Q1 | D27: March | E27: Other Inbound | F27: 1000 | G27: =SUM(H27:J27) -> 4 | H27: 4 | K27: =IFERROR(F27/G27,"") -> 250 | L27: =SUM(M27:O27) -> 0 | U27: =if(T27<=0,"",((T27*12)-F27)/F27) | V27: =iferror(L27/P27,"") | W27: =iferror(Q27/L27,"") | X27: =iferror(R27/Q27,"") | Y27: =iferror(R27/L27,"")
A28: =iferror(DATEVALUE(D28 & " 1"),"") -> 45748 | B28: Paid | C28: =IF(D28="","", IF(A28<DATE(2025, 4, 1),"Q1",if(A28<DATE(2025, 7, 1),"Q2",IF(A28<DATE(2025, 10, 1),"Q3","Q4")))) -> Q2 | D28: April | E28: Other Inbound | F28: 1000 | G28: =SUM(H28:J28) -> 5 | H28: 5 | K28: =IFERROR(F28/G28,"") -> 200 | L28: =SUM(M28:O28) -> 0 | U28: =if(T28<=0,"",((T28*12)-F28)/F28) | V28: =iferror(L28/P28,"") | W28: =iferror(Q28/L28,"") | X28: =iferror(R28/Q28,"") | Y28: =iferror(R28/L28,"")
B29: Paid | C29: =IF(D29="","", IF(A29<DATE(2025, 4, 1),"Q1",if(A29<DATE(2025, 7, 1),"Q2",IF(A29<DATE(2025, 10, 1),"Q3","Q4")))) -> Q1 | D29: May | E29: Other Inbound | F29: 1000 | G29: =SUM(H29:J29) -> 5 | H29: 5 | K29: =IFERROR(F29/G29,"") -> 200
B30: Paid | C30: =IF(D30="","", IF(A30<DATE(2025, 4, 1),"Q1",if(A30<DATE(2025, 7, 1),"Q2",IF(A30<DATE(2025, 10, 1),"Q3","Q4")))) -> Q1 | D30: June | E30: Other Inbound | F30: 1000 | G30: =SUM(H30:J30) -> 5 | H30: 5 | K30: =IFERROR(F30/G30,"") -> 200
B31: Paid | C31: =IF(D31="","", IF(A31<DATE(2025, 4, 1),"Q1",if(A31<DATE(2025, 7, 1),"Q2",IF(A31<DATE(2025, 10, 1),"Q3","Q4")))) -> Q1 | D31: July | E31: Other Inbound | F31: 1000 | G31: =SUM(H31:J31) -> 5 | H31: 5 | K31: =IFERROR(F31/G31,"") -> 200
A32: =iferror(DATEVALUE(D32 & " 1"),"") -> 45870 | B32: Paid | C32: =IF(D32="","", IF(A32<DATE(2025, 4, 1),"Q1",if(A32<DATE(2025, 7, 1),"Q2",IF(A32<DATE(2025, 10, 1),"Q3","Q4")))) -> Q3 | D32: August | E32: Other Inbound | F32: 1000 | G32: =SUM(H32:J32) -> 5 | H32: 5 | K32: =IFERROR(F32/G32,"") -> 200 | L32: =SUM(M32:O32) -> 0 | U32: =if(T32<=0,"",((T32*12)-F32)/F32) | V32: =iferror(L32/P32,"") | W32: =iferror(Q32/L32,"") | X32: =iferror(R32/Q32,"") | Y32: =iferror(R32/L32,"")
A33: =iferror(DATEVALUE(D33 & " 1"),"") -> 45901 | B33: Paid | C33: =IF(D33="","", IF(A33<DATE(2025, 4, 1),"Q1",if(A33<DATE(2025, 7, 1),"Q2",IF(A33<DATE(2025, 10, 1),"Q3","Q4")))) -> Q3 | D33: September | E33: Other Inbound | F33: 1000 | G33: 6 | H33: 6 | K33: =IFERROR(F33/G33,"") -> 166.66667 | L33: =SUM(M33:O33) -> 0 | U33: =if(T33<=0,"",((T33*12)-F33)/F33) | V33: =iferror(L33/P33,"") | W33: =iferror(Q33/L33,"") | X33: =iferror(R33/Q33,"") | Y33: =iferror(R33/L33,"")
A34: =iferror(DATEVALUE(D34 & " 1"),"") -> 45931 | B34: Paid | C34: =IF(D34="","", IF(A34<DATE(2025, 4, 1),"Q1",if(A34<DATE(2025, 7, 1),"Q2",IF(A34<DATE(2025, 10, 1),"Q3","Q4")))) -> Q4 | D34: October | E34: Other Inbound | F34: 1000 | G34: =SUM(H34:J34) -> 5 | H34: 5 | K34: =IFERROR(F34/G34,"") -> 200 | L34: =SUM(M34:O34) -> 0 | U34: =if(T34<=0,"",((T34*12)-F34)/F34) | V34: =iferror(L34/P34,"") | W34: =iferror(Q34/L34,"") | X34: =iferror(R34/Q34,"") | Y34: =iferror(R34/L34,"")
A35: =iferror(DATEVALUE(D35 & " 1"),"") -> 45962 | B35: Paid | C35: =IF(D35="","", IF(A35<DATE(2025, 4, 1),"Q1",if(A35<DATE(2025, 7, 1),"Q2",IF(A35<DATE(2025, 10, 1),"Q3","Q4")))) -> Q4 | D35: November | E35: Other Inbound | F35: 1000 | G35: =SUM(H35:J35) -> 5 | H35: 5 | K35: =IFERROR(F35/G35,"") -> 200 | L35: =SUM(M35:O35) -> 0 | U35: =if(T35<=0,"",((T35*12)-F35)/F35) | V35: =iferror(L35/P35,"") | W35: =iferror(Q35/L35,"") | X35: =iferror(R35/Q35,"") | Y35: =iferror(R35/L35,"")
A36: =iferror(DATEVALUE(D36 & " 1"),"") -> 45992 | B36: Paid | C36: =IF(D36="","", IF(A36<DATE(2025, 4, 1),"Q1",if(A36<DATE(2025, 7, 1),"Q2",IF(A36<DATE(2025, 10, 1),"Q3","Q4")))) -> Q4 | D36: December | E36: Other Inbound | F36: 1000 | G36: =SUM(H36:J36) -> 5 | H36: 5 | K36: =IFERROR(F36/G36,"") -> 200 | L36: =SUM(M36:O36) -> 0 | U36: =if(T36<=0,"",((T36*12)-F36)/F36) | V36: =iferror(L36/P36,"") | W36: =iferror(Q36/L36,"") | X36: =iferror(R36/Q36,"") | Y36: =iferror(R36/L36,"")
A37: =iferror(DATEVALUE(D37 & " 1"),"") | C37: =IF(D37="","", IF(A37<DATE(2025, 4, 1),"Q1",if(A37<DATE(2025, 7, 1),"Q2",IF(A37<DATE(2025, 10, 1),"Q3","Q4")))) | K37: =IFERROR(F37/G37,"") | L37: =SUM(M37:O37) -> 0 | U37: =if(T37<=0,"",((T37*12)-F37)/F37) | V37: =iferror(L37/P37,"") | W37: =iferror(Q37/L37,"") | X37: =iferror(R37/Q37,"") | Y37: =iferror(R37/L37,"")
A38: =iferror(DATEVALUE(D38 & " 1"),"") | C38: =IF(D38="","", IF(A38<DATE(2025, 4, 1),"Q1",if(A38<DATE(2025, 7, 1),"Q2",IF(A38<DATE(2025, 10, 1),"Q3","Q4")))) | K38: =IFERROR(F38/G38,"") | L38: =SUM(M38:O38) -> 0 | U38: =if(T38<=0,"",((T38*12)-F38)/F38) | V38: =iferror(L38/P38,"") | W38: =iferror(Q38/L38,"") | X38: =iferror(R38/Q38,"") | Y38: =iferror(R38/L38,"")
A39: =iferror(DATEVALUE(D39 & " 1"),"") | C39: =IF(D39="","", IF(A39<DATE(2025, 4, 1),"Q1",if(A39<DATE(2025, 7, 1),"Q2",IF(A39<DATE(2025, 10, 1),"Q3","Q4")))) | K39: =IFERROR(F39/G39,"") | L39: =SUM(M39:O39) -> 0 | U39: =if(T39<=0,"",((T39*12)-F39)/F39) | V39: =iferror(L39/P39,"") | W39: =iferror(Q39/L39,"") | X39: =iferror(R39/Q39,"") | Y39: =iferror(R39/L39,"")
A40: =iferror(DATEVALUE(D40 & " 1"),"") | C40: =IF(D40="","", IF(A40<DATE(2025, 4, 1),"Q1",if(A40<DATE(2025, 7, 1),"Q2",IF(A40<DATE(2025, 10, 1),"Q3","Q4")))) | K40: =IFERROR(F40/G40,"") | L40: =SUM(M40:O40) -> 0 | U40: =if(T40<=0,"",((T40*12)-F40)/F40) | V40: =iferror(L40/P40,"") | W40: =iferror(Q40/L40,"") | X40: =iferror(R40/Q40,"") | Y40: =iferror(R40/L40,"")
A41: =iferror(DATEVALUE(D41 & " 1"),"") | C41: =IF(D41="","", IF(A41<DATE(2025, 4, 1),"Q1",if(A41<DATE(2025, 7, 1),"Q2",IF(A41<DATE(2025, 10, 1),"Q3","Q4")))) | K41: =IFERROR(F41/G41,"") | L41: =SUM(M41:O41) -> 0 | U41: =if(T41<=0,"",((T41*12)-F41)/F41) | V41: =iferror(L41/P41,"") | W41: =iferror(Q41/L41,"") | X41: =iferror(R41/Q41,"") | Y41: =iferror(R41/L41,"")
A42: =iferror(DATEVALUE(D42 & " 1"),"") | C42: =IF(D42="","", IF(A42<DATE(2025, 4, 1),"Q1",if(A42<DATE(2025, 7, 1),"Q2",IF(A42<DATE(2025, 10, 1),"Q3","Q4")))) | K42: =IFERROR(F42/G42,"") | L42: =SUM(M42:O42) -> 0 | U42: =if(T42<=0,"",((T42*12)-F42)/F42) | V42: =iferror(L42/P42,"") | W42: =iferror(Q42/L42,"") | X42: =iferror(R42/Q42,"") | Y42: =iferror(R42/L42,"")
A43: =iferror(DATEVALUE(D43 & " 1"),"") | C43: =IF(D43="","", IF(A43<DATE(2025, 4, 1),"Q1",if(A43<DATE(2025, 7, 1),"Q2",IF(A43<DATE(2025, 10, 1),"Q3","Q4")))) | K43: =IFERROR(F43/G43,"") | L43: =SUM(M43:O43) -> 0 | U43: =if(T43<=0,"",((T43*12)-F43)/F43) | V43: =iferror(L43/P43,"") | W43: =iferror(Q43/L43,"") | X43: =iferror(R43/Q43,"") | Y43: =iferror(R43/L43,"")
A44: =iferror(DATEVALUE(D44 & " 1"),"") | C44: =IF(D44="","", IF(A44<DATE(2025, 4, 1),"Q1",if(A44<DATE(2025, 7, 1),"Q2",IF(A44<DATE(2025, 10, 1),"Q3","Q4")))) | K44: =IFERROR(F44/G44,"") | L44: =SUM(M44:O44) -> 0 | U44: =if(T44<=0,"",((T44*12)-F44)/F44) | V44: =iferror(L44/P44,"") | W44: =iferror(Q44/L44,"") | X44: =iferror(R44/Q44,"") | Y44: =iferror(R44/L44,"")
A45: =iferror(DATEVALUE(D45 & " 1"),"") | C45: =IF(D45="","", IF(A45<DATE(2025, 4, 1),"Q1",if(A45<DATE(2025, 7, 1),"Q2",IF(A45<DATE(2025, 10, 1),"Q3","Q4")))) | K45: =IFERROR(F45/G45,"") | L45: =SUM(M45:O45) -> 0 | U45: =if(T45<=0,"",((T45*12)-F45)/F45) | V45: =iferror(L45/P45,"") | W45: =iferror(Q45/L45,"") | X45: =iferror(R45/Q45,"") | Y45: =iferror(R45/L45,"")
A46: =iferror(DATEVALUE(D46 & " 1"),"") | C46: =IF(D46="","", IF(A46<DATE(2025, 4, 1),"Q1",if(A46<DATE(2025, 7, 1),"Q2",IF(A46<DATE(2025, 10, 1),"Q3","Q4")))) | K46: =IFERROR(F46/G46,"") | L46: =SUM(M46:O46) -> 0 | U46: =if(T46<=0,"",((T46*12)-F46)/F46) | V46: =iferror(L46/P46,"") | W46: =iferror(Q46/L46,"") | X46: =iferror(R46/Q46,"") | Y46: =iferror(R46/L46,"")
A47: =iferror(DATEVALUE(D47 & " 1"),"") | C47: =IF(D47="","", IF(A47<DATE(2025, 4, 1),"Q1",if(A47<DATE(2025, 7, 1),"Q2",IF(A47<DATE(2025, 10, 1),"Q3","Q4")))) | K47: =IFERROR(F47/G47,"") | L47: =SUM(M47:O47) -> 0 | U47: =if(T47<=0,"",((T47*12)-F47)/F47) | V47: =iferror(L47/P47,"") | W47: =iferror(Q47/L47,"") | X47: =iferror(R47/Q47,"") | Y47: =iferror(R47/L47,"")
A48: =iferror(DATEVALUE(D48 & " 1"),"") | C48: =IF(D48="","", IF(A48<DATE(2025, 4, 1),"Q1",if(A48<DATE(2025, 7, 1),"Q2",IF(A48<DATE(2025, 10, 1),"Q3","Q4")))) | K48: =IFERROR(F48/G48,"") | L48: =SUM(M48:O48) -> 0 | U48: =if(T48<=0,"",((T48*12)-F48)/F48) | V48: =iferror(L48/P48,"") | W48: =iferror(Q48/L48,"") | X48: =iferror(R48/Q48,"") | Y48: =iferror(R48/L48,"")
... A214: =iferror(DATEVALUE(D214 & " 1"),"") | C214: =IF(D214="","", IF(A214<DATE(2025, 4, 1),"Q1",if(A214<DATE(2025, 7, 1),"Q2",IF(A214<DATE(2025, 10, 1),"Q3","Q4")))) | K214: =IFERROR(F214/G214,"") | L214: =SUM(M214:O214) -> 0 | U214: =if(T214<=0,"",((T214*12)-F214)/F214) | V214: =iferror(L214/P214,"") | W214: =iferror(Q214/L214,"") | X214: =iferror(R214/Q214,"") | Y214: =iferror(R214/L214,"")
A215: =iferror(DATEVALUE(D215 & " 1"),"") | C215: =IF(D215="","", IF(A215<DATE(2025, 4, 1),"Q1",if(A215<DATE(2025, 7, 1),"Q2",IF(A215<DATE(2025, 10, 1),"Q3","Q4")))) | L215: =SUM(M215:O215) -> 0 | U215: =if(T215<=0,"",((T215*12)-F215)/F215) | V215: =iferror(L215/P215,"") | W215: =iferror(Q215/L215,"") | X215: =iferror(R215/Q215,"") | Y215: =iferror(R215/L215,"")
A216: =iferror(DATEVALUE(D216 & " 1"),"") | C216: =IF(D216="","", IF(A216<DATE(2025, 4, 1),"Q1",if(A216<DATE(2025, 7, 1),"Q2",IF(A216<DATE(2025, 10, 1),"Q3","Q4")))) | L216: =SUM(M216:O216) -> 0 | U216: =if(T216<=0,"",((T216*12)-F216)/F216) | V216: =iferror(L216/P216,"") | W216: =iferror(Q216/L216,"") | X216: =iferror(R216/Q216,"") | Y216: =iferror(R216/L216,"")
A217: =iferror(DATEVALUE(D217 & " 1"),"") | C217: =IF(D217="","", IF(A217<DATE(2025, 4, 1),"Q1",if(A217<DATE(2025, 7, 1),"Q2",IF(A217<DATE(2025, 10, 1),"Q3","Q4")))) | L217: =SUM(M217:O217) -> 0 | U217: =if(T217<=0,"",((T217*12)-F217)/F217) | V217: =iferror(L217/P217,"") | W217: =iferror(Q217/L217,"") | X217: =iferror(R217/Q217,"") | Y217: =iferror(R217/L217,"")
A218: =iferror(DATEVALUE(D218 & " 1"),"") | C218: =IF(D218="","", IF(A218<DATE(2025, 4, 1),"Q1",if(A218<DATE(2025, 7, 1),"Q2",IF(A218<DATE(2025, 10, 1),"Q3","Q4")))) | L218: =SUM(M218:O218) -> 0 | U218: =if(T218<=0,"",((T218*12)-F218)/F218) | V218: =iferror(L218/P218,"") | W218: =iferror(Q218/L218,"") | X218: =iferror(R218/Q218,"") | Y218: =iferror(R218/L218,"")
A219: =iferror(DATEVALUE(D219 & " 1"),"") | C219: =IF(D219="","", IF(A219<DATE(2025, 4, 1),"Q1",if(A219<DATE(2025, 7, 1),"Q2",IF(A219<DATE(2025, 10, 1),"Q3","Q4")))) | L219: =SUM(M219:O219) -> 0 | U219: =if(T219<=0,"",((T219*12)-F219)/F219) | V219: =iferror(L219/P219,"") | W219: =iferror(Q219/L219,"") | X219: =iferror(R219/Q219,"") | Y219: =iferror(R219/L219,"")
A220: =iferror(DATEVALUE(D220 & " 1"),"") | C220: =IF(D220="","", IF(A220<DATE(2025, 4, 1),"Q1",if(A220<DATE(2025, 7, 1),"Q2",IF(A220<DATE(2025, 10, 1),"Q3","Q4")))) | L220: =SUM(M220:O220) -> 0 | U220: =if(T220<=0,"",((T220*12)-F220)/F220) | V220: =iferror(L220/P220,"") | W220: =iferror(Q220/L220,"") | X220: =iferror(R220/Q220,"") | Y220: =iferror(R220/L220,"")
A221: =iferror(DATEVALUE(D221 & " 1"),"") | C221: =IF(D221="","", IF(A221<DATE(2025, 4, 1),"Q1",if(A221<DATE(2025, 7, 1),"Q2",IF(A221<DATE(2025, 10, 1),"Q3","Q4")))) | L221: =SUM(M221:O221) -> 0 | U221: =if(T221<=0,"",((T221*12)-F221)/F221) | V221: =iferror(L221/P221,"") | W221: =iferror(Q221/L221,"") | X221: =iferror(R221/Q221,"") | Y221: =iferror(R221/L221,"")
A222: =iferror(DATEVALUE(D222 & " 1"),"") | C222: =IF(D222="","", IF(A222<DATE(2025, 4, 1),"Q1",if(A222<DATE(2025, 7, 1),"Q2",IF(A222<DATE(2025, 10, 1),"Q3","Q4")))) | L222: =SUM(M222:O222) -> 0 | U222: =if(T222<=0,"",((T222*12)-F222)/F222) | V222: =iferror(L222/P222,"") | W222: =iferror(Q222/L222,"") | X222: =iferror(R222/Q222,"") | Y222: =iferror(R222/L222,"")
A223: =iferror(DATEVALUE(D223 & " 1"),"") | C223: =IF(D223="","", IF(A223<DATE(2025, 4, 1),"Q1",if(A223<DATE(2025, 7, 1),"Q2",IF(A223<DATE(2025, 10, 1),"Q3","Q4")))) | L223: =SUM(M223:O223) -> 0 | U223: =if(T223<=0,"",((T223*12)-F223)/F223) | V223: =iferror(L223/P223,"") | W223: =iferror(Q223/L223,"") | X223: =iferror(R223/Q223,"") | Y223: =iferror(R223/L223,"")
A224: =iferror(DATEVALUE(D224 & " 1"),"") | C224: =IF(D224="","", IF(A224<DATE(2025, 4, 1),"Q1",if(A224<DATE(2025, 7, 1),"Q2",IF(A224<DATE(2025, 10, 1),"Q3","Q4")))) | L224: =SUM(M224:O224) -> 0 | U224: =if(T224<=0,"",((T224*12)-F224)/F224) | V224: =iferror(L224/P224,"") | W224: =iferror(Q224/L224,"") | X224: =iferror(R224/Q224,"") | Y224: =iferror(R224/L224,"")
A225: =iferror(DATEVALUE(D225 & " 1"),"") | C225: =IF(D225="","", IF(A225<DATE(2025, 4, 1),"Q1",if(A225<DATE(2025, 7, 1),"Q2",IF(A225<DATE(2025, 10, 1),"Q3","Q4")))) | L225: =SUM(M225:O225) -> 0 | U225: =if(T225<=0,"",((T225*12)-F225)/F225) | V225: =iferror(L225/P225,"") | W225: =iferror(Q225/L225,"") | X225: =iferror(R225/Q225,"") | Y225: =iferror(R225/L225,"")
A226: =iferror(DATEVALUE(D226 & " 1"),"") | C226: =IF(D226="","", IF(A226<DATE(2025, 4, 1),"Q1",if(A226<DATE(2025, 7, 1),"Q2",IF(A226<DATE(2025, 10, 1),"Q3","Q4")))) | L226: =SUM(M226:O226) -> 0 | U226: =if(T226<=0,"",((T226*12)-F226)/F226) | V226: =iferror(L226/P226,"") | W226: =iferror(Q226/L226,"") | X226: =iferror(R226/Q226,"") | Y226: =iferror(R226/L226,"")
... A999: =iferror(DATEVALUE(D999 & " 1"),"") | C999: =IF(D999="","", IF(A999<DATE(2025, 4, 1),"Q1",if(A999<DATE(2025, 7, 1),"Q2",IF(A999<DATE(2025, 10, 1),"Q3","Q4")))) | L999: =SUM(M999:O999) -> 0 | U999: =if(T999<=0,"",((T999*12)-F999)/F999) | V999: =iferror(L999/P999,"") | W999: =iferror(Q999/L999,"") | X999: =iferror(R999/Q999,"") | Y999: =iferror(R999/L999,"")

Sheet Headcount
G1: 1 | H1: 2 | I1: 3 | J1: 4 | K1: 5 | L1: 6 | M1: 7 | N1: 8 | O1: 9 | P1: 10 | Q1: 11 | R1: 12 | T1: 12
C2: Dedicated Staff | D2: YES | G2: January | H2: February | I2: March | J2: April | K2: May | L2: June | M2: July | N2: August | O2: September | P2: October | Q2: November | R2: December | T2: TOTAL
C3: Total Annual Investment | D3: =SUM(G3:R3) -> -170600 | F3: Total Staff | G3: =if($D$2="YES",G9+G18+G27+G36+G45,"") -> -14216.667 | H3: =if($D$2="YES",H9+H18+H27+H36+H45,"") -> -14216.667 | I3: =if($D$2="YES",I9+I18+I27+I36+I45,"") -> -14216.667 | J3: =if($D$2="YES",J9+J18+J27+J36+J45,"") -> -14216.667 | K3: =if($D$2="YES",K9+K18+K27+K36+K45,"") -> -14216.667 | L3: =if($D$2="YES",L9+L18+L27+L36+L45,"") -> -14216.667 | M3: =if($D$2="YES",M9+M18+M27+M36+M45,"") -> -14216.667 | N3: =if($D$2="YES",N9+N18+N27+N36+N45,"") -> -14216.667 | ... R3: =if($D$2="YES",R9+R18+R27+R36+R45,"") -> -14216.667 | T3: =SUM(G3:R3) -> -170600
F4: Salary | G4: =if($D$2="YES",G10+G19+G28+G37+G46+G55+G64+G73+G82+G91+G100+G109,"") -> -14216.667 | H4: =if($D$2="YES",H10+H19+H28+H37+H46+H55+H64+H73+H82+H91+H100+H109,"") -> -14216.667 | I4: =if($D$2="YES",I10+I19+I28+I37+I46+I55+I64+I73+I82+I91+I100+I109,"") -> -14216.667 | J4: =if($D$2="YES",J10+J19+J28+J37+J46+J55+J64+J73+J82+J91+J100+J109,"") -> -14216.667 | K4: =if($D$2="YES",K10+K19+K28+K37+K46+K55+K64+K73+K82+K91+K100+K109,"") -> -14216.667 | L4: =if($D$2="YES",L10+L19+L28+L37+L46+L55+L64+L73+L82+L91+L100+L109,"") -> -14216.667 | M4: =if($D$2="YES",M10+M19+M28+M37+M46+M55+M64+M73+M82+M91+M100+M109,"") -> -14216.667 | N4: =if($D$2="YES",N10+N19+N28+N37+N46+N55+N64+N73+N82+N91+N100+N109,"") -> -14216.667 | ... R4: =if($D$2="YES",R10+R19+R28+R37+R46+R55+R64+R73+R82+R91+R100+R109,"") -> -14216.667 | T4: =SUM(G4:R4) -> -170600
F5: Factorial Support | G5: =if($D$2="YES",G11+G20+G29+G38+G47+G56+G65+G74+G83+G92+G101+G110,"") -> 0 | H5: =if($D$2="YES",H11+H20+H29+H38+H47+H56+H65+H74+H83+H92+H101+H110,"") -> 0 | I5: =if($D$2="YES",I11+I20+I29+I38+I47+I56+I65+I74+I83+I92+I101+I110,"") -> 0 | J5: =if($D$2="YES",J11+J20+J29+J38+J47+J56+J65+J74+J83+J92+J101+J110,"") -> 0 | K5: =if($D$2="YES",K11+K20+K29+K38+K47+K56+K65+K74+K83+K92+K101+K110,"") -> 0 | L5: =if($D$2="YES",L11+L20+L29+L38+L47+L56+L65+L74+L83+L92+L101+L110,"") -> 0 | M5: =if($D$2="YES",M11+M20+M29+M38+M47+M56+M65+M74+M83+M92+M101+M110,"") -> 0 | N5: =if($D$2="YES",N11+N20+N29+N38+N47+N56+N65+N74+N83+N92+N101+N110,"") -> 0 | ... R5: =if($D$2="YES",R11+R20+R29+R38+R47+R56+R65+R74+R83+R92+R101+R110,"") -> 0 | T5: =SUM(G5:R5) -> 0
C7: Dedicated Staff Member #1 | D7: YES
C8: Start date | D8: January
C9: Role name | D9: AE 1 (Umar) | F9: =D9 -> AE 1 (Umar) | G9: =G10+G11 -> -7050 | H9: =H10+H11 -> -7050 | I9: =I10+I11 -> -7050 | J9: =J10+J11 -> -7050 | K9: =K10+K11 -> -7050 | L9: =L10+L11 -> -7050 | M9: =M10+M11 -> -7050 | N9: =N10+N11 -> -7050 | ... R9: =R10+R11 -> -7050 | T9: =SUM(G9:R9) -> -84600
C10: Final Annual Cost | D10: =(14000/7*12*1.25+0.3*0.35*35000*12+35000*0.3) -> 84600 | F10: Salary | G10: =IF($D7="YES", IF($D8>0,IF(AND(G$1 >= MATCH($D8, $G$2:$R$2, 0)), -($D10/12), ""),""), "") -> -7050 | H10: =IF($D7="YES", IF($D8>0,IF(AND(H$1 >= MATCH($D8, $G$2:$R$2, 0)), -($D10/12), ""),""), "") -> -7050 | I10: =IF($D7="YES", IF($D8>0,IF(AND(I$1 >= MATCH($D8, $G$2:$R$2, 0)), -($D10/12), ""),""), "") -> -7050 | J10: =IF($D7="YES", IF($D8>0,IF(AND(J$1 >= MATCH($D8, $G$2:$R$2, 0)), -($D10/12), ""),""), "") -> -7050 | K10: =IF($D7="YES", IF($D8>0,IF(AND(K$1 >= MATCH($D8, $G$2:$R$2, 0)), -($D10/12), ""),""), "") -> -7050 | L10: =IF($D7="YES", IF($D8>0,IF(AND(L$1 >= MATCH($D8, $G$2:$R$2, 0)), -($D10/12), ""),""), "") -> -7050 | M10: =IF($D7="YES", IF($D8>0,IF(AND(M$1 >= MATCH($D8, $G$2:$R$2, 0)), -($D10/12), ""),""), "") -> -7050 | N10: =IF($D7="YES", IF($D8>0,IF(AND(N$1 >= MATCH($D8, $G$2:$R$2, 0)), -($D10/12), ""),""), "") -> -7050 | ... R10: =IF($D7="YES", IF($D8>0,IF(AND(R$1 >= MATCH($D8, $G$2:$R$2, 0)), -($D10/12), ""),""), "") -> -7050 | T10: =SUM(G10:R10) -> -84600
C11: Factorial funds? | D11: NO | F11: Factorial Support | G11: =IF($D7="YES", if($D11="YES", IF(AND(G$1 >= MATCH($D14, $G$2:$R$2, 0), G$1 <= (MATCH($D14, $G$2:$R$2, 0) + $D13 - 1)), (($D10/12)*$D12),""),""), "") | H11: =IF($D7="YES", if($D11="YES", IF(AND(H$1 >= MATCH($D14, $G$2:$R$2, 0), H$1 <= (MATCH($D14, $G$2:$R$2, 0) + $D13 - 1)), (($D10/12)*$D12),""),""), "") | I11: =IF($D7="YES", if($D11="YES", IF(AND(I$1 >= MATCH($D14, $G$2:$R$2, 0), I$1 <= (MATCH($D14, $G$2:$R$2, 0) + $D13 - 1)), (($D10/12)*$D12),""),""), "") | J11: =IF($D7="YES", if($D11="YES", IF(AND(J$1 >= MATCH($D14, $G$2:$R$2, 0), J$1 <= (MATCH($D14, $G$2:$R$2, 0) + $D13 - 1)), (($D10/12)*$D12),""),""), "") | K11: =IF($D7="YES", if($D11="YES", IF(AND(K$1 >= MATCH($D14, $G$2:$R$2, 0), K$1 <= (MATCH($D14, $G$2:$R$2, 0) + $D13 - 1)), (($D10/12)*$D12),""),""), "") | L11: =IF($D7="YES", if($D11="YES", IF(AND(L$1 >= MATCH($D14, $G$2:$R$2, 0), L$1 <= (MATCH($D14, $G$2:$R$2, 0) + $D13 - 1)), (($D10/12)*$D12),""),""), "") | M11: =IF($D7="YES", if($D11="YES", IF(AND(M$1 >= MATCH($D14, $G$2:$R$2, 0), M$1 <= (MATCH($D14, $G$2:$R$2, 0) + $D13 - 1)), (($D10/12)*$D12),""),""), "") | N11: =IF($D7="YES", if($D11="YES", IF(AND(N$1 >= MATCH($D14, $G$2:$R$2, 0), N$1 <= (MATCH($D14, $G$2:$R$2, 0) + $D13 - 1)), (($D10/12)*$D12),""),""), "") | ... R11: =IF($D7="YES", if($D11="YES", IF(AND(R$1 >= MATCH($D14, $G$2:$R$2, 0), R$1 <= (MATCH($D14, $G$2:$R$2, 0) + $D13 - 1)), (($D10/12)*$D12),""),""), "") | T11: =SUM(G11:R11) -> 0
C12: % of Factorial Support?
C13: How many months?
C14: First month of funding | D14: January
C16: Dedicated Staff Member #2 | D16: YES
C17: Start date | D17: January
C18: Role name | D18: SDR 1 | F18: =D18 -> SDR 1 | G18: =G19+G20 -> -3854.1667 | H18: =H19+H20 -> -3854.1667 | I18: =I19+I20 -> -3854.1667 | J18: =J19+J20 -> -3854.1667 | K18: =K19+K20 -> -3854.1667 | L18: =L19+L20 -> -3854.1667 | M18: =M19+M20 -> -3854.1667 | N18: =N19+N20 -> -3854.1667 | ... R18: =R19+R20 -> -3854.1667 | T18: =SUM(G18:R18) -> -46250
C19: Final Annual Cost | D19: =25000*1.25+15000 -> 46250 | F19: Salary | G19: =IF($D16="YES", IF($D17>0,IF(AND(G$1 >= MATCH($D17, $G$2:$R$2, 0)), -($D19/12), ""),""), "") -> -3854.1667 | H19: =IF($D16="YES", IF($D17>0,IF(AND(H$1 >= MATCH($D17, $G$2:$R$2, 0)), -($D19/12), ""),""), "") -> -3854.1667 | I19: =IF($D16="YES", IF($D17>0,IF(AND(I$1 >= MATCH($D17, $G$2:$R$2, 0)), -($D19/12), ""),""), "") -> -3854.1667 | J19: =IF($D16="YES", IF($D17>0,IF(AND(J$1 >= MATCH($D17, $G$2:$R$2, 0)), -($D19/12), ""),""), "") -> -3854.1667 | K19: =IF($D16="YES", IF($D17>0,IF(AND(K$1 >= MATCH($D17, $G$2:$R$2, 0)), -($D19/12), ""),""), "") -> -3854.1667 | L19: =IF($D16="YES", IF($D17>0,IF(AND(L$1 >= MATCH($D17, $G$2:$R$2, 0)), -($D19/12), ""),""), "") -> -3854.1667 | M19: =IF($D16="YES", IF($D17>0,IF(AND(M$1 >= MATCH($D17, $G$2:$R$2, 0)), -($D19/12), ""),""), "") -> -3854.1667 | N19: =IF($D16="YES", IF($D17>0,IF(AND(N$1 >= MATCH($D17, $G$2:$R$2, 0)), -($D19/12), ""),""), "") -> -3854.1667 | ... R19: =IF($D16="YES", IF($D17>0,IF(AND(R$1 >= MATCH($D17, $G$2:$R$2, 0)), -($D19/12), ""),""), "") -> -3854.1667 | T19: =SUM(G19:R19) -> -46250
C20: Factorial funds? | D20: NO | F20: Factorial Support | G20: =IF($D16="YES", if($D20="YES", IF(AND(G$1 >= MATCH($D23, $G$2:$R$2, 0), G$1 <= (MATCH($D23, $G$2:$R$2, 0) + $D22 - 1)), (($D19/12)*$D21),""),""), "") | H20: =IF($D16="YES", if($D20="YES", IF(AND(H$1 >= MATCH($D23, $G$2:$R$2, 0), H$1 <= (MATCH($D23, $G$2:$R$2, 0) + $D22 - 1)), (($D19/12)*$D21),""),""), "") | I20: =IF($D16="YES", if($D20="YES", IF(AND(I$1 >= MATCH($D23, $G$2:$R$2, 0), I$1 <= (MATCH($D23, $G$2:$R$2, 0) + $D22 - 1)), (($D19/12)*$D21),""),""), "") | J20: =IF($D16="YES", if($D20="YES", IF(AND(J$1 >= MATCH($D23, $G$2:$R$2, 0), J$1 <= (MATCH($D23, $G$2:$R$2, 0) + $D22 - 1)), (($D19/12)*$D21),""),""), "") | K20: =IF($D16="YES", if($D20="YES", IF(AND(K$1 >= MATCH($D23, $G$2:$R$2, 0), K$1 <= (MATCH($D23, $G$2:$R$2, 0) + $D22 - 1)), (($D19/12)*$D21),""),""), "") | L20: =IF($D16="YES", if($D20="YES", IF(AND(L$1 >= MATCH($D23, $G$2:$R$2, 0), L$1 <= (MATCH($D23, $G$2:$R$2, 0) + $D22 - 1)), (($D19/12)*$D21),""),""), "") | M20: =IF($D16="YES", if($D20="YES", IF(AND(M$1 >= MATCH($D23, $G$2:$R$2, 0), M$1 <= (MATCH($D23, $G$2:$R$2, 0) + $D22 - 1)), (($D19/12)*$D21),""),""), "") | N20: =IF($D16="YES", if($D20="YES", IF(AND(N$1 >= MATCH($D23, $G$2:$R$2, 0), N$1 <= (MATCH($D23, $G$2:$R$2, 0) + $D22 - 1)), (($D19/12)*$D21),""),""), "") | ... R20: =IF($D16="YES", if($D20="YES", IF(AND(R$1 >= MATCH($D23, $G$2:$R$2, 0), R$1 <= (MATCH($D23, $G$2:$R$2, 0) + $D22 - 1)), (($D19/12)*$D21),""),""), "") | T20: =SUM(G20:R20) -> 0
C21: % of Factorial Support? | D21: 0.5
C22: How many months?
C23: First month of funding | D23: January
C25: Dedicated Staff Member #3 | D25: YES
C26: Start date | D26: January
C27: Role name | D27: AE 2 50% | F27: =D27 -> AE 2 50% | G27: =G28+G29 -> 0 | H27: =H28+H29 -> 0 | I27: =I28+I29 -> 0 | J27: =J28+J29 -> 0 | K27: =K28+K29 -> 0 | L27: =L28+L29 -> 0 | M27: =M28+M29 -> 0 | N27: =N28+N29 -> 0 | ... R27: =R28+R29 -> 0 | T27: =SUM(G27:R27) -> 0
C28: Final Annual Cost | D28: 0 | F28: Salary | G28: =IF($D25="YES", IF($D26>0,IF(AND(G$1 >= MATCH($D26, $G$2:$R$2, 0)), -($D28/12), ""),""), "") -> 0 | H28: =IF($D25="YES", IF($D26>0,IF(AND(H$1 >= MATCH($D26, $G$2:$R$2, 0)), -($D28/12), ""),""), "") -> 0 | I28: =IF($D25="YES", IF($D26>0,IF(AND(I$1 >= MATCH($D26, $G$2:$R$2, 0)), -($D28/12), ""),""), "") -> 0 | J28: =IF($D25="YES", IF($D26>0,IF(AND(J$1 >= MATCH($D26, $G$2:$R$2, 0)), -($D28/12), ""),""), "") -> 0 | K28: =IF($D25="YES", IF($D26>0,IF(AND(K$1 >= MATCH($D26, $G$2:$R$2, 0)), -($D28/12), ""),""), "") -> 0 | L28: =IF($D25="YES", IF($D26>0,IF(AND(L$1 >= MATCH($D26, $G$2:$R$2, 0)), -($D28/12), ""),""), "") -> 0 | M28: =IF($D25="YES", IF($D26>0,IF(AND(M$1 >= MATCH($D26, $G$2:$R$2, 0)), -($D28/12), ""),""), "") -> 0 | N28: =IF($D25="YES", IF($D26>0,IF(AND(N$1 >= MATCH($D26, $G$2:$R$2, 0)), -($D28/12), ""),""), "") -> 0 | ... R28: =IF($D25="YES", IF($D26>0,IF(AND(R$1 >= MATCH($D26, $G$2:$R$2, 0)), -($D28/12), ""),""), "") -> 0 | T28: =SUM(G28:R28) -> 0
C29: Factorial funds? | D29: NO | F29: Factorial Support | G29: =IF($D25="YES", if($D29="YES", IF(AND(G$1 >= MATCH($D32, $G$2:$R$2, 0), G$1 <= (MATCH($D32, $G$2:$R$2, 0) + $D31 - 1)), (($D28/12)*$D30),""),""), "") | H29: =IF($D25="YES", if($D29="YES", IF(AND(H$1 >= MATCH($D32, $G$2:$R$2, 0), H$1 <= (MATCH($D32, $G$2:$R$2, 0) + $D31 - 1)), (($D28/12)*$D30),""),""), "") | I29: =IF($D25="YES", if($D29="YES", IF(AND(I$1 >= MATCH($D32, $G$2:$R$2, 0), I$1 <= (MATCH($D32, $G$2:$R$2, 0) + $D31 - 1)), (($D28/12)*$D30),""),""), "") | J29: =IF($D25="YES", if($D29="YES", IF(AND(J$1 >= MATCH($D32, $G$2:$R$2, 0), J$1 <= (MATCH($D32, $G$2:$R$2, 0) + $D31 - 1)), (($D28/12)*$D30),""),""), "") | K29: =IF($D25="YES", if($D29="YES", IF(AND(K$1 >= MATCH($D32, $G$2:$R$2, 0), K$1 <= (MATCH($D32, $G$2:$R$2, 0) + $D31 - 1)), (($D28/12)*$D30),""),""), "") | L29: =IF($D25="YES", if($D29="YES", IF(AND(L$1 >= MATCH($D32, $G$2:$R$2, 0), L$1 <= (MATCH($D32, $G$2:$R$2, 0) + $D31 - 1)), (($D28/12)*$D30),""),""), "") | M29: =IF($D25="YES", if($D29="YES", IF(AND(M$1 >= MATCH($D32, $G$2:$R$2, 0), M$1 <= (MATCH($D32, $G$2:$R$2, 0) + $D31 - 1)), (($D28/12)*$D30),""),""), "") | N29: =IF($D25="YES", if($D29="YES", IF(AND(N$1 >= MATCH($D32, $G$2:$R$2, 0), N$1 <= (MATCH($D32, $G$2:$R$2, 0) + $D31 - 1)), (($D28/12)*$D30),""),""), "") | ... R29: =IF($D25="YES", if($D29="YES", IF(AND(R$1 >= MATCH($D32, $G$2:$R$2, 0), R$1 <= (MATCH($D32, $G$2:$R$2, 0) + $D31 - 1)), (($D28/12)*$D30),""),""), "") | T29: =SUM(G29:R29) -> 0
C30: % of Factorial Support?
C31: How many months?
C32: First month of funding | D32: January
C34: Dedicated Staff Member #4 | D34: YES
C35: Start date | D35: January
C36: Role name | D36: OB/AM specialist | F36: =D36 -> OB/AM specialist | G36: =G37+G38 -> -3312.5 | H36: =H37+H38 -> -3312.5 | I36: =I37+I38 -> -3312.5 | J36: =J37+J38 -> -3312.5 | K36: =K37+K38 -> -3312.5 | L36: =L37+L38 -> -3312.5 | M36: =M37+M38 -> -3312.5 | N36: =N37+N38 -> -3312.5 | ... R36: =R37+R38 -> -3312.5 | T36: =SUM(G36:R36) -> -39750
C37: Final Annual Cost | D37: =27000*1.25+6000 -> 39750 | F37: Salary | G37: =IF($D34="YES", IF($D35>0,IF(AND(G$1 >= MATCH($D35, $G$2:$R$2, 0)), -($D37/12), ""),""), "") -> -3312.5 | H37: =IF($D34="YES", IF($D35>0,IF(AND(H$1 >= MATCH($D35, $G$2:$R$2, 0)), -($D37/12), ""),""), "") -> -3312.5 | I37: =IF($D34="YES", IF($D35>0,IF(AND(I$1 >= MATCH($D35, $G$2:$R$2, 0)), -($D37/12), ""),""), "") -> -3312.5 | J37: =IF($D34="YES", IF($D35>0,IF(AND(J$1 >= MATCH($D35, $G$2:$R$2, 0)), -($D37/12), ""),""), "") -> -3312.5 | K37: =IF($D34="YES", IF($D35>0,IF(AND(K$1 >= MATCH($D35, $G$2:$R$2, 0)), -($D37/12), ""),""), "") -> -3312.5 | L37: =IF($D34="YES", IF($D35>0,IF(AND(L$1 >= MATCH($D35, $G$2:$R$2, 0)), -($D37/12), ""),""), "") -> -3312.5 | M37: =IF($D34="YES", IF($D35>0,IF(AND(M$1 >= MATCH($D35, $G$2:$R$2, 0)), -($D37/12), ""),""), "") -> -3312.5 | N37: =IF($D34="YES", IF($D35>0,IF(AND(N$1 >= MATCH($D35, $G$2:$R$2, 0)), -($D37/12), ""),""), "") -> -3312.5 | ... R37: =IF($D34="YES", IF($D35>0,IF(AND(R$1 >= MATCH($D35, $G$2:$R$2, 0)), -($D37/12), ""),""), "") -> -3312.5 | T37: =SUM(G37:R37) -> -39750
C38: Factorial funds? | D38: NO | F38: Factorial Support | G38: =IF($D34="YES", if($D38="YES", IF(AND(G$1 >= MATCH($D41, $G$2:$R$2, 0), G$1 <= (MATCH($D41, $G$2:$R$2, 0) + $D40 - 1)), (($D37/12)*$D39),""),""), "") | H38: =IF($D34="YES", if($D38="YES", IF(AND(H$1 >= MATCH($D41, $G$2:$R$2, 0), H$1 <= (MATCH($D41, $G$2:$R$2, 0) + $D40 - 1)), (($D37/12)*$D39),""),""), "") | I38: =IF($D34="YES", if($D38="YES", IF(AND(I$1 >= MATCH($D41, $G$2:$R$2, 0), I$1 <= (MATCH($D41, $G$2:$R$2, 0) + $D40 - 1)), (($D37/12)*$D39),""),""), "") | J38: =IF($D34="YES", if($D38="YES", IF(AND(J$1 >= MATCH($D41, $G$2:$R$2, 0), J$1 <= (MATCH($D41, $G$2:$R$2, 0) + $D40 - 1)), (($D37/12)*$D39),""),""), "") | K38: =IF($D34="YES", if($D38="YES", IF(AND(K$1 >= MATCH($D41, $G$2:$R$2, 0), K$1 <= (MATCH($D41, $G$2:$R$2, 0) + $D40 - 1)), (($D37/12)*$D39),""),""), "") | L38: =IF($D34="YES", if($D38="YES", IF(AND(L$1 >= MATCH($D41, $G$2:$R$2, 0), L$1 <= (MATCH($D41, $G$2:$R$2, 0) + $D40 - 1)), (($D37/12)*$D39),""),""), "") | M38: =IF($D34="YES", if($D38="YES", IF(AND(M$1 >= MATCH($D41, $G$2:$R$2, 0), M$1 <= (MATCH($D41, $G$2:$R$2, 0) + $D40 - 1)), (($D37/12)*$D39),""),""), "") | N38: =IF($D34="YES", if($D38="YES", IF(AND(N$1 >= MATCH($D41, $G$2:$R$2, 0), N$1 <= (MATCH($D41, $G$2:$R$2, 0) + $D40 - 1)), (($D37/12)*$D39),""),""), "") | ... R38: =IF($D34="YES", if($D38="YES", IF(AND(R$1 >= MATCH($D41, $G$2:$R$2, 0), R$1 <= (MATCH($D41, $G$2:$R$2, 0) + $D40 - 1)), (($D37/12)*$D39),""),""), "") | T38: =SUM(G38:R38) -> 0
C39: % of Factorial Support?
C40: How many months?
C41: First month of funding
C43: Dedicated Staff Member #5 | D43: NO
C44: Start date
C45: Role name | F45: =D45 | G45: =G46+G47 -> 0 | H45: =H46+H47 -> 0 | I45: =I46+I47 -> 0 | J45: =J46+J47 -> 0 | K45: =K46+K47 -> 0 | L45: =L46+L47 -> 0 | M45: =M46+M47 -> 0 | N45: =N46+N47 -> 0 | ... R45: =R46+R47 -> 0 | T45: =SUM(G45:R45) -> 0
C46: Final Annual Cost | F46: Salary | G46: =IF($D43="YES", IF($D44>0,IF(AND(G$1 >= MATCH($D44, $G$2:$R$2, 0)), -($D46/12), ""),""), "") | H46: =IF($D43="YES", IF($D44>0,IF(AND(H$1 >= MATCH($D44, $G$2:$R$2, 0)), -($D46/12), ""),""), "") | I46: =IF($D43="YES", IF($D44>0,IF(AND(I$1 >= MATCH($D44, $G$2:$R$2, 0)), -($D46/12), ""),""), "") | J46: =IF($D43="YES", IF($D44>0,IF(AND(J$1 >= MATCH($D44, $G$2:$R$2, 0)), -($D46/12), ""),""), "") | K46: =IF($D43="YES", IF($D44>0,IF(AND(K$1 >= MATCH($D44, $G$2:$R$2, 0)), -($D46/12), ""),""), "") | L46: =IF($D43="YES", IF($D44>0,IF(AND(L$1 >= MATCH($D44, $G$2:$R$2, 0)), -($D46/12), ""),""), "") | M46: =IF($D43="YES", IF($D44>0,IF(AND(M$1 >= MATCH($D44, $G$2:$R$2, 0)), -($D46/12), ""),""), "") | N46: =IF($D43="YES", IF($D44>0,IF(AND(N$1 >= MATCH($D44, $G$2:$R$2, 0)), -($D46/12), ""),""), "") | ... R46: =IF($D43="YES", IF($D44>0,IF(AND(R$1 >= MATCH($D44, $G$2:$R$2, 0)), -($D46/12), ""),""), "") | T46: =SUM(G46:R46) -> 0
C47: Factorial funds? | F47: Factorial Support | G47: =IF($D43="YES", if($D47="YES", IF(AND(G$1 >= MATCH($D50, $G$2:$R$2, 0), G$1 <= (MATCH($D50, $G$2:$R$2, 0) + $D49 - 1)), (($D46/12)*$D48),""),""), "") | H47: =IF($D43="YES", if($D47="YES", IF(AND(H$1 >= MATCH($D50, $G$2:$R$2, 0), H$1 <= (MATCH($D50, $G$2:$R$2, 0) + $D49 - 1)), (($D46/12)*$D48),""),""), "") | I47: =IF($D43="YES", if($D47="YES", IF(AND(I$1 >= MATCH($D50, $G$2:$R$2, 0), I$1 <= (MATCH($D50, $G$2:$R$2, 0) + $D49 - 1)), (($D46/12)*$D48),""),""), "") | J47: =IF($D43="YES", if($D47="YES", IF(AND(J$1 >= MATCH($D50, $G$2:$R$2, 0), J$1 <= (MATCH($D50, $G$2:$R$2, 0) + $D49 - 1)), (($D46/12)*$D48),""),""), "") | K47: =IF($D43="YES", if($D47="YES", IF(AND(K$1 >= MATCH($D50, $G$2:$R$2, 0), K$1 <= (MATCH($D50, $G$2:$R$2, 0) + $D49 - 1)), (($D46/12)*$D48),""),""), "") | L47: =IF($D43="YES", if($D47="YES", IF(AND(L$1 >= MATCH($D50, $G$2:$R$2, 0), L$1 <= (MATCH($D50, $G$2:$R$2, 0) + $D49 - 1)), (($D46/12)*$D48),""),""), "") | M47: =IF($D43="YES", if($D47="YES", IF(AND(M$1 >= MATCH($D50, $G$2:$R$2, 0), M$1 <= (MATCH($D50, $G$2:$R$2, 0) + $D49 - 1)), (($D46/12)*$D48),""),""), "") | N47: =IF($D43="YES", if($D47="YES", IF(AND(N$1 >= MATCH($D50, $G$2:$R$2, 0), N$1 <= (MATCH($D50, $G$2:$R$2, 0) + $D49 - 1)), (($D46/12)*$D48),""),""), "") | ... R47: =IF($D43="YES", if($D47="YES", IF(AND(R$1 >= MATCH($D50, $G$2:$R$2, 0), R$1 <= (MATCH($D50, $G$2:$R$2, 0) + $D49 - 1)), (($D46/12)*$D48),""),""), "") | T47: =SUM(G47:R47) -> 0
C48: % of Factorial Support?
C49: How many months?
C50: First month of funding
C52: Dedicated Staff Member #6 | D52: NO
C53: Start date
C54: Role name | F54: =D54 | G54: =G55+G56 -> 0 | H54: =H55+H56 -> 0 | I54: =I55+I56 -> 0 | J54: =J55+J56 -> 0 | K54: =K55+K56 -> 0 | L54: =L55+L56 -> 0 | M54: =M55+M56 -> 0 | N54: =N55+N56 -> 0 | ... R54: =R55+R56 -> 0 | T54: =SUM(G54:R54) -> 0
C55: Final Annual Cost | F55: Salary | G55: =IF($D52="YES", IF($D53>0,IF(AND(G$1 >= MATCH($D53, $G$2:$R$2, 0)), -($D55/12), ""),""), "") | H55: =IF($D52="YES", IF($D53>0,IF(AND(H$1 >= MATCH($D53, $G$2:$R$2, 0)), -($D55/12), ""),""), "") | I55: =IF($D52="YES", IF($D53>0,IF(AND(I$1 >= MATCH($D53, $G$2:$R$2, 0)), -($D55/12), ""),""), "") | J55: =IF($D52="YES", IF($D53>0,IF(AND(J$1 >= MATCH($D53, $G$2:$R$2, 0)), -($D55/12), ""),""), "") | K55: =IF($D52="YES", IF($D53>0,IF(AND(K$1 >= MATCH($D53, $G$2:$R$2, 0)), -($D55/12), ""),""), "") | L55: =IF($D52="YES", IF($D53>0,IF(AND(L$1 >= MATCH($D53, $G$2:$R$2, 0)), -($D55/12), ""),""), "") | M55: =IF($D52="YES", IF($D53>0,IF(AND(M$1 >= MATCH($D53, $G$2:$R$2, 0)), -($D55/12), ""),""), "") | N55: =IF($D52="YES", IF($D53>0,IF(AND(N$1 >= MATCH($D53, $G$2:$R$2, 0)), -($D55/12), ""),""), "") | ... R55: =IF($D52="YES", IF($D53>0,IF(AND(R$1 >= MATCH($D53, $G$2:$R$2, 0)), -($D55/12), ""),""), "") | T55: =SUM(G55:R55) -> 0
C56: Factorial funds? | F56: Factorial Support | G56: =IF($D52="YES", if($D56="YES", IF(AND(G$1 >= MATCH($D59, $G$2:$R$2, 0), G$1 <= (MATCH($D59, $G$2:$R$2, 0) + $D58 - 1)), (($D55/12)*$D57),""),""), "") | H56: =IF($D52="YES", if($D56="YES", IF(AND(H$1 >= MATCH($D59, $G$2:$R$2, 0), H$1 <= (MATCH($D59, $G$2:$R$2, 0) + $D58 - 1)), (($D55/12)*$D57),""),""), "") | I56: =IF($D52="YES", if($D56="YES", IF(AND(I$1 >= MATCH($D59, $G$2:$R$2, 0), I$1 <= (MATCH($D59, $G$2:$R$2, 0) + $D58 - 1)), (($D55/12)*$D57),""),""), "") | J56: =IF($D52="YES", if($D56="YES", IF(AND(J$1 >= MATCH($D59, $G$2:$R$2, 0), J$1 <= (MATCH($D59, $G$2:$R$2, 0) + $D58 - 1)), (($D55/12)*$D57),""),""), "") | K56: =IF($D52="YES", if($D56="YES", IF(AND(K$1 >= MATCH($D59, $G$2:$R$2, 0), K$1 <= (MATCH($D59, $G$2:$R$2, 0) + $D58 - 1)), (($D55/12)*$D57),""),""), "") | L56: =IF($D52="YES", if($D56="YES", IF(AND(L$1 >= MATCH($D59, $G$2:$R$2, 0), L$1 <= (MATCH($D59, $G$2:$R$2, 0) + $D58 - 1)), (($D55/12)*$D57),""),""), "") | M56: =IF($D52="YES", if($D56="YES", IF(AND(M$1 >= MATCH($D59, $G$2:$R$2, 0), M$1 <= (MATCH($D59, $G$2:$R$2, 0) + $D58 - 1)), (($D55/12)*$D57),""),""), "") | N56: =IF($D52="YES", if($D56="YES", IF(AND(N$1 >= MATCH($D59, $G$2:$R$2, 0), N$1 <= (MATCH($D59, $G$2:$R$2, 0) + $D58 - 1)), (($D55/12)*$D57),""),""), "") | ... R56: =IF($D52="YES", if($D56="YES", IF(AND(R$1 >= MATCH($D59, $G$2:$R$2, 0), R$1 <= (MATCH($D59, $G$2:$R$2, 0) + $D58 - 1)), (($D55/12)*$D57),""),""), "") | T56: =SUM(G56:R56) -> 0
C57: % of Factorial Support?
C58: How many months?
C59: First month of funding
C61: Dedicated Staff Member #7 | D61: NO
C62: Start date
C63: Role name | F63: =D63 | G63: =G64+G65 -> 0 | H63: =H64+H65 -> 0 | I63: =I64+I65 -> 0 | J63: =J64+J65 -> 0 | K63: =K64+K65 -> 0 | L63: =L64+L65 -> 0 | M63: =M64+M65 -> 0 | N63: =N64+N65 -> 0 | ... R63: =R64+R65 -> 0 | T63: =SUM(G63:R63) -> 0
C64: Final Annual Cost | F64: Salary | G64: =IF($D61="YES", IF($D62>0,IF(AND(G$1 >= MATCH($D62, $G$2:$R$2, 0)), -($D64/12), ""),""), "") | H64: =IF($D61="YES", IF($D62>0,IF(AND(H$1 >= MATCH($D62, $G$2:$R$2, 0)), -($D64/12), ""),""), "") | I64: =IF($D61="YES", IF($D62>0,IF(AND(I$1 >= MATCH($D62, $G$2:$R$2, 0)), -($D64/12), ""),""), "") | J64: =IF($D61="YES", IF($D62>0,IF(AND(J$1 >= MATCH($D62, $G$2:$R$2, 0)), -($D64/12), ""),""), "") | K64: =IF($D61="YES", IF($D62>0,IF(AND(K$1 >= MATCH($D62, $G$2:$R$2, 0)), -($D64/12), ""),""), "") | L64: =IF($D61="YES", IF($D62>0,IF(AND(L$1 >= MATCH($D62, $G$2:$R$2, 0)), -($D64/12), ""),""), "") | M64: =IF($D61="YES", IF($D62>0,IF(AND(M$1 >= MATCH($D62, $G$2:$R$2, 0)), -($D64/12), ""),""), "") | N64: =IF($D61="YES", IF($D62>0,IF(AND(N$1 >= MATCH($D62, $G$2:$R$2, 0)), -($D64/12), ""),""), "") | ... R64: =IF($D61="YES", IF($D62>0,IF(AND(R$1 >= MATCH($D62, $G$2:$R$2, 0)), -($D64/12), ""),""), "") | T64: =SUM(G64:R64) -> 0
C65: Factorial funds? | F65: Factorial Support | G65: =IF($D61="YES", if($D65="YES", IF(AND(G$1 >= MATCH($D68, $G$2:$R$2, 0), G$1 <= (MATCH($D68, $G$2:$R$2, 0) + $D67 - 1)), (($D64/12)*$D66),""),""), "") | H65: =IF($D61="YES", if($D65="YES", IF(AND(H$1 >= MATCH($D68, $G$2:$R$2, 0), H$1 <= (MATCH($D68, $G$2:$R$2, 0) + $D67 - 1)), (($D64/12)*$D66),""),""), "") | I65: =IF($D61="YES", if($D65="YES", IF(AND(I$1 >= MATCH($D68, $G$2:$R$2, 0), I$1 <= (MATCH($D68, $G$2:$R$2, 0) + $D67 - 1)), (($D64/12)*$D66),""),""), "") | J65: =IF($D61="YES", if($D65="YES", IF(AND(J$1 >= MATCH($D68, $G$2:$R$2, 0), J$1 <= (MATCH($D68, $G$2:$R$2, 0) + $D67 - 1)), (($D64/12)*$D66),""),""), "") | K65: =IF($D61="YES", if($D65="YES", IF(AND(K$1 >= MATCH($D68, $G$2:$R$2, 0), K$1 <= (MATCH($D68, $G$2:$R$2, 0) + $D67 - 1)), (($D64/12)*$D66),""),""), "") | L65: =IF($D61="YES", if($D65="YES", IF(AND(L$1 >= MATCH($D68, $G$2:$R$2, 0), L$1 <= (MATCH($D68, $G$2:$R$2, 0) + $D67 - 1)), (($D64/12)*$D66),""),""), "") | M65: =IF($D61="YES", if($D65="YES", IF(AND(M$1 >= MATCH($D68, $G$2:$R$2, 0), M$1 <= (MATCH($D68, $G$2:$R$2, 0) + $D67 - 1)), (($D64/12)*$D66),""),""), "") | N65: =IF($D61="YES", if($D65="YES", IF(AND(N$1 >= MATCH($D68, $G$2:$R$2, 0), N$1 <= (MATCH($D68, $G$2:$R$2, 0) + $D67 - 1)), (($D64/12)*$D66),""),""), "") | ... R65: =IF($D61="YES", if($D65="YES", IF(AND(R$1 >= MATCH($D68, $G$2:$R$2, 0), R$1 <= (MATCH($D68, $G$2:$R$2, 0) + $D67 - 1)), (($D64/12)*$D66),""),""), "") | T65: =SUM(G65:R65) -> 0
C66: % of Factorial Support?
C67: How many months?
C68: First month of funding
C70: Dedicated Staff Member #8 | D70: NO
C71: Start date
C72: Role name | F72: =D72 | G72: =G73+G74 -> 0 | H72: =H73+H74 -> 0 | I72: =I73+I74 -> 0 | J72: =J73+J74 -> 0 | K72: =K73+K74 -> 0 | L72: =L73+L74 -> 0 | M72: =M73+M74 -> 0 | N72: =N73+N74 -> 0 | ... R72: =R73+R74 -> 0 | T72: =SUM(G72:R72) -> 0
C73: Final Annual Cost | F73: Salary | G73: =IF($D70="YES", IF($D71>0,IF(AND(G$1 >= MATCH($D71, $G$2:$R$2, 0)), -($D73/12), ""),""), "") | H73: =IF($D70="YES", IF($D71>0,IF(AND(H$1 >= MATCH($D71, $G$2:$R$2, 0)), -($D73/12), ""),""), "") | I73: =IF($D70="YES", IF($D71>0,IF(AND(I$1 >= MATCH($D71, $G$2:$R$2, 0)), -($D73/12), ""),""), "") | J73: =IF($D70="YES", IF($D71>0,IF(AND(J$1 >= MATCH($D71, $G$2:$R$2, 0)), -($D73/12), ""),""), "") | K73: =IF($D70="YES", IF($D71>0,IF(AND(K$1 >= MATCH($D71, $G$2:$R$2, 0)), -($D73/12), ""),""), "") | L73: =IF($D70="YES", IF($D71>0,IF(AND(L$1 >= MATCH($D71, $G$2:$R$2, 0)), -($D73/12), ""),""), "") | M73: =IF($D70="YES", IF($D71>0,IF(AND(M$1 >= MATCH($D71, $G$2:$R$2, 0)), -($D73/12), ""),""), "") | N73: =IF($D70="YES", IF($D71>0,IF(AND(N$1 >= MATCH($D71, $G$2:$R$2, 0)), -($D73/12), ""),""), "") | ... R73: =IF($D70="YES", IF($D71>0,IF(AND(R$1 >= MATCH($D71, $G$2:$R$2, 0)), -($D73/12), ""),""), "") | T73: =SUM(G73:R73) -> 0
C74: Factorial funds? | F74: Factorial Support | G74: =IF($D70="YES", if($D74="YES", IF(AND(G$1 >= MATCH($D77, $G$2:$R$2, 0), G$1 <= (MATCH($D77, $G$2:$R$2, 0) + $D76 - 1)), (($D73/12)*$D75),""),""), "") | H74: =IF($D70="YES", if($D74="YES", IF(AND(H$1 >= MATCH($D77, $G$2:$R$2, 0), H$1 <= (MATCH($D77, $G$2:$R$2, 0) + $D76 - 1)), (($D73/12)*$D75),""),""), "") | I74: =IF($D70="YES", if($D74="YES", IF(AND(I$1 >= MATCH($D77, $G$2:$R$2, 0), I$1 <= (MATCH($D77, $G$2:$R$2, 0) + $D76 - 1)), (($D73/12)*$D75),""),""), "") | J74: =IF($D70="YES", if($D74="YES", IF(AND(J$1 >= MATCH($D77, $G$2:$R$2, 0), J$1 <= (MATCH($D77, $G$2:$R$2, 0) + $D76 - 1)), (($D73/12)*$D75),""),""), "") | K74: =IF($D70="YES", if($D74="YES", IF(AND(K$1 >= MATCH($D77, $G$2:$R$2, 0), K$1 <= (MATCH($D77, $G$2:$R$2, 0) + $D76 - 1)), (($D73/12)*$D75),""),""), "") | L74: =IF($D70="YES", if($D74="YES", IF(AND(L$1 >= MATCH($D77, $G$2:$R$2, 0), L$1 <= (MATCH($D77, $G$2:$R$2, 0) + $D76 - 1)), (($D73/12)*$D75),""),""), "") | M74: =IF($D70="YES", if($D74="YES", IF(AND(M$1 >= MATCH($D77, $G$2:$R$2, 0), M$1 <= (MATCH($D77, $G$2:$R$2, 0) + $D76 - 1)), (($D73/12)*$D75),""),""), "") | N74: =IF($D70="YES", if($D74="YES", IF(AND(N$1 >= MATCH($D77, $G$2:$R$2, 0), N$1 <= (MATCH($D77, $G$2:$R$2, 0) + $D76 - 1)), (($D73/12)*$D75),""),""), "") | ... R74: =IF($D70="YES", if($D74="YES", IF(AND(R$1 >= MATCH($D77, $G$2:$R$2, 0), R$1 <= (MATCH($D77, $G$2:$R$2, 0) + $D76 - 1)), (($D73/12)*$D75),""),""), "") | T74: =SUM(G74:R74) -> 0
C75: % of Factorial Support?
C76: How many months?
C77: First month of funding
C79: Dedicated Staff Member #9 | D79: NO
C80: Start date
C81: Role name | F81: =D81 | G81: =G82+G83 -> 0 | H81: =H82+H83 -> 0 | I81: =I82+I83 -> 0 | J81: =J82+J83 -> 0 | K81: =K82+K83 -> 0 | L81: =L82+L83 -> 0 | M81: =M82+M83 -> 0 | N81: =N82+N83 -> 0 | ... R81: =R82+R83 -> 0 | T81: =SUM(G81:R81) -> 0
C82: Final Annual Cost | F82: Salary | G82: =IF($D79="YES", IF($D80>0,IF(AND(G$1 >= MATCH($D80, $G$2:$R$2, 0)), -($D82/12), ""),""), "") | H82: =IF($D79="YES", IF($D80>0,IF(AND(H$1 >= MATCH($D80, $G$2:$R$2, 0)), -($D82/12), ""),""), "") | I82: =IF($D79="YES", IF($D80>0,IF(AND(I$1 >= MATCH($D80, $G$2:$R$2, 0)), -($D82/12), ""),""), "") | J82: =IF($D79="YES", IF($D80>0,IF(AND(J$1 >= MATCH($D80, $G$2:$R$2, 0)), -($D82/12), ""),""), "") | K82: =IF($D79="YES", IF($D80>0,IF(AND(K$1 >= MATCH($D80, $G$2:$R$2, 0)), -($D82/12), ""),""), "") | L82: =IF($D79="YES", IF($D80>0,IF(AND(L$1 >= MATCH($D80, $G$2:$R$2, 0)), -($D82/12), ""),""), "") | M82: =IF($D79="YES", IF($D80>0,IF(AND(M$1 >= MATCH($D80, $G$2:$R$2, 0)), -($D82/12), ""),""), "") | N82: =IF($D79="YES", IF($D80>0,IF(AND(N$1 >= MATCH($D80, $G$2:$R$2, 0)), -($D82/12), ""),""), "") | ... R82: =IF($D79="YES", IF($D80>0,IF(AND(R$1 >= MATCH($D80, $G$2:$R$2, 0)), -($D82/12), ""),""), "") | T82: =SUM(G82:R82) -> 0
C83: Factorial funds? | F83: Factorial Support | G83: =IF($D79="YES", if($D83="YES", IF(AND(G$1 >= MATCH($D86, $G$2:$R$2, 0), G$1 <= (MATCH($D86, $G$2:$R$2, 0) + $D85 - 1)), (($D82/12)*$D84),""),""), "") | H83: =IF($D79="YES", if($D83="YES", IF(AND(H$1 >= MATCH($D86, $G$2:$R$2, 0), H$1 <= (MATCH($D86, $G$2:$R$2, 0) + $D85 - 1)), (($D82/12)*$D84),""),""), "") | I83: =IF($D79="YES", if($D83="YES", IF(AND(I$1 >= MATCH($D86, $G$2:$R$2, 0), I$1 <= (MATCH($D86, $G$2:$R$2, 0) + $D85 - 1)), (($D82/12)*$D84),""),""), "") | J83: =IF($D79="YES", if($D83="YES", IF(AND(J$1 >= MATCH($D86, $G$2:$R$2, 0), J$1 <= (MATCH($D86, $G$2:$R$2, 0) + $D85 - 1)), (($D82/12)*$D84),""),""), "") | K83: =IF($D79="YES", if($D83="YES", IF(AND(K$1 >= MATCH($D86, $G$2:$R$2, 0), K$1 <= (MATCH($D86, $G$2:$R$2, 0) + $D85 - 1)), (($D82/12)*$D84),""),""), "") | L83: =IF($D79="YES", if($D83="YES", IF(AND(L$1 >= MATCH($D86, $G$2:$R$2, 0), L$1 <= (MATCH($D86, $G$2:$R$2, 0) + $D85 - 1)), (($D82/12)*$D84),""),""), "") | M83: =IF($D79="YES", if($D83="YES", IF(AND(M$1 >= MATCH($D86, $G$2:$R$2, 0), M$1 <= (MATCH($D86, $G$2:$R$2, 0) + $D85 - 1)), (($D82/12)*$D84),""),""), "") | N83: =IF($D79="YES", if($D83="YES", IF(AND(N$1 >= MATCH($D86, $G$2:$R$2, 0), N$1 <= (MATCH($D86, $G$2:$R$2, 0) + $D85 - 1)), (($D82/12)*$D84),""),""), "") | ... R83: =IF($D79="YES", if($D83="YES", IF(AND(R$1 >= MATCH($D86, $G$2:$R$2, 0), R$1 <= (MATCH($D86, $G$2:$R$2, 0) + $D85 - 1)), (($D82/12)*$D84),""),""), "") | T83: =SUM(G83:R83) -> 0
C84: % of Factorial Support?
C85: How many months?
C86: First month of funding
C88: Dedicated Staff Member #10 | D88: NO
C89: Start date
C90: Role name | F90: =D90 | G90: =G91+G92 -> 0 | H90: =H91+H92 -> 0 | I90: =I91+I92 -> 0 | J90: =J91+J92 -> 0 | K90: =K91+K92 -> 0 | L90: =L91+L92 -> 0 | M90: =M91+M92 -> 0 | N90: =N91+N92 -> 0 | ... R90: =R91+R92 -> 0 | T90: =SUM(G90:R90) -> 0
C91: Final Annual Cost | F91: Salary | G91: =IF($D88="YES", IF($D89>0,IF(AND(G$1 >= MATCH($D89, $G$2:$R$2, 0)), -($D91/12), ""),""), "") | H91: =IF($D88="YES", IF($D89>0,IF(AND(H$1 >= MATCH($D89, $G$2:$R$2, 0)), -($D91/12), ""),""), "") | I91: =IF($D88="YES", IF($D89>0,IF(AND(I$1 >= MATCH($D89, $G$2:$R$2, 0)), -($D91/12), ""),""), "") | J91: =IF($D88="YES", IF($D89>0,IF(AND(J$1 >= MATCH($D89, $G$2:$R$2, 0)), -($D91/12), ""),""), "") | K91: =IF($D88="YES", IF($D89>0,IF(AND(K$1 >= MATCH($D89, $G$2:$R$2, 0)), -($D91/12), ""),""), "") | L91: =IF($D88="YES", IF($D89>0,IF(AND(L$1 >= MATCH($D89, $G$2:$R$2, 0)), -($D91/12), ""),""), "") | M91: =IF($D88="YES", IF($D89>0,IF(AND(M$1 >= MATCH($D89, $G$2:$R$2, 0)), -($D91/12), ""),""), "") | N91: =IF($D88="YES", IF($D89>0,IF(AND(N$1 >= MATCH($D89, $G$2:$R$2, 0)), -($D91/12), ""),""), "") | ... R91: =IF($D88="YES", IF($D89>0,IF(AND(R$1 >= MATCH($D89, $G$2:$R$2, 0)), -($D91/12), ""),""), "") | T91: =SUM(G91:R91) -> 0
C92: Factorial funds? | F92: Factorial Support | G92: =IF($D88="YES", if($D92="YES", IF(AND(G$1 >= MATCH($D95, $G$2:$R$2, 0), G$1 <= (MATCH($D95, $G$2:$R$2, 0) + $D94 - 1)), (($D91/12)*$D93),""),""), "") | H92: =IF($D88="YES", if($D92="YES", IF(AND(H$1 >= MATCH($D95, $G$2:$R$2, 0), H$1 <= (MATCH($D95, $G$2:$R$2, 0) + $D94 - 1)), (($D91/12)*$D93),""),""), "") | I92: =IF($D88="YES", if($D92="YES", IF(AND(I$1 >= MATCH($D95, $G$2:$R$2, 0), I$1 <= (MATCH($D95, $G$2:$R$2, 0) + $D94 - 1)), (($D91/12)*$D93),""),""), "") | J92: =IF($D88="YES", if($D92="YES", IF(AND(J$1 >= MATCH($D95, $G$2:$R$2, 0), J$1 <= (MATCH($D95, $G$2:$R$2, 0) + $D94 - 1)), (($D91/12)*$D93),""),""), "") | K92: =IF($D88="YES", if($D92="YES", IF(AND(K$1 >= MATCH($D95, $G$2:$R$2, 0), K$1 <= (MATCH($D95, $G$2:$R$2, 0) + $D94 - 1)), (($D91/12)*$D93),""),""), "") | L92: =IF($D88="YES", if($D92="YES", IF(AND(L$1 >= MATCH($D95, $G$2:$R$2, 0), L$1 <= (MATCH($D95, $G$2:$R$2, 0) + $D94 - 1)), (($D91/12)*$D93),""),""), "") | M92: =IF($D88="YES", if($D92="YES", IF(AND(M$1 >= MATCH($D95, $G$2:$R$2, 0), M$1 <= (MATCH($D95, $G$2:$R$2, 0) + $D94 - 1)), (($D91/12)*$D93),""),""), "") | N92: =IF($D88="YES", if($D92="YES", IF(AND(N$1 >= MATCH($D95, $G$2:$R$2, 0), N$1 <= (MATCH($D95, $G$2:$R$2, 0) + $D94 - 1)), (($D91/12)*$D93),""),""), "") | ... R92: =IF($D88="YES", if($D92="YES", IF(AND(R$1 >= MATCH($D95, $G$2:$R$2, 0), R$1 <= (MATCH($D95, $G$2:$R$2, 0) + $D94 - 1)), (($D91/12)*$D93),""),""), "") | T92: =SUM(G92:R92) -> 0
C93: % of Factorial Support?
C94: How many months?
C95: First month of funding
C97: Dedicated Staff Member #11 | D97: NO
C98: Start date
C99: Role name | F99: =D99 | G99: =G100+G101 -> 0 | H99: =H100+H101 -> 0 | I99: =I100+I101 -> 0 | J99: =J100+J101 -> 0 | K99: =K100+K101 -> 0 | L99: =L100+L101 -> 0 | M99: =M100+M101 -> 0 | N99: =N100+N101 -> 0 | ... R99: =R100+R101 -> 0 | T99: =SUM(G99:R99) -> 0
C100: Final Annual Cost | F100: Salary | G100: =IF($D97="YES", IF($D98>0,IF(AND(G$1 >= MATCH($D98, $G$2:$R$2, 0)), -($D100/12), ""),""), "") | H100: =IF($D97="YES", IF($D98>0,IF(AND(H$1 >= MATCH($D98, $G$2:$R$2, 0)), -($D100/12), ""),""), "") | I100: =IF($D97="YES", IF($D98>0,IF(AND(I$1 >= MATCH($D98, $G$2:$R$2, 0)), -($D100/12), ""),""), "") | J100: =IF($D97="YES", IF($D98>0,IF(AND(J$1 >= MATCH($D98, $G$2:$R$2, 0)), -($D100/12), ""),""), "") | K100: =IF($D97="YES", IF($D98>0,IF(AND(K$1 >= MATCH($D98, $G$2:$R$2, 0)), -($D100/12), ""),""), "") | L100: =IF($D97="YES", IF($D98>0,IF(AND(L$1 >= MATCH($D98, $G$2:$R$2, 0)), -($D100/12), ""),""), "") | M100: =IF($D97="YES", IF($D98>0,IF(AND(M$1 >= MATCH($D98, $G$2:$R$2, 0)), -($D100/12), ""),""), "") | N100: =IF($D97="YES", IF($D98>0,IF(AND(N$1 >= MATCH($D98, $G$2:$R$2, 0)), -($D100/12), ""),""), "") | ... R100: =IF($D97="YES", IF($D98>0,IF(AND(R$1 >= MATCH($D98, $G$2:$R$2, 0)), -($D100/12), ""),""), "") | T100: =SUM(G100:R100) -> 0
C101: Factorial funds? | F101: Factorial Support | G101: =IF($D97="YES", if($D101="YES", IF(AND(G$1 >= MATCH($D104, $G$2:$R$2, 0), G$1 <= (MATCH($D104, $G$2:$R$2, 0) + $D103 - 1)), (($D100/12)*$D102),""),""), "") | H101: =IF($D97="YES", if($D101="YES", IF(AND(H$1 >= MATCH($D104, $G$2:$R$2, 0), H$1 <= (MATCH($D104, $G$2:$R$2, 0) + $D103 - 1)), (($D100/12)*$D102),""),""), "") | I101: =IF($D97="YES", if($D101="YES", IF(AND(I$1 >= MATCH($D104, $G$2:$R$2, 0), I$1 <= (MATCH($D104, $G$2:$R$2, 0) + $D103 - 1)), (($D100/12)*$D102),""),""), "") | J101: =IF($D97="YES", if($D101="YES", IF(AND(J$1 >= MATCH($D104, $G$2:$R$2, 0), J$1 <= (MATCH($D104, $G$2:$R$2, 0) + $D103 - 1)), (($D100/12)*$D102),""),""), "") | K101: =IF($D97="YES", if($D101="YES", IF(AND(K$1 >= MATCH($D104, $G$2:$R$2, 0), K$1 <= (MATCH($D104, $G$2:$R$2, 0) + $D103 - 1)), (($D100/12)*$D102),""),""), "") | L101: =IF($D97="YES", if($D101="YES", IF(AND(L$1 >= MATCH($D104, $G$2:$R$2, 0), L$1 <= (MATCH($D104, $G$2:$R$2, 0) + $D103 - 1)), (($D100/12)*$D102),""),""), "") | M101: =IF($D97="YES", if($D101="YES", IF(AND(M$1 >= MATCH($D104, $G$2:$R$2, 0), M$1 <= (MATCH($D104, $G$2:$R$2, 0) + $D103 - 1)), (($D100/12)*$D102),""),""), "") | N101: =IF($D97="YES", if($D101="YES", IF(AND(N$1 >= MATCH($D104, $G$2:$R$2, 0), N$1 <= (MATCH($D104, $G$2:$R$2, 0) + $D103 - 1)), (($D100/12)*$D102),""),""), "") | ... R101: =IF($D97="YES", if($D101="YES", IF(AND(R$1 >= MATCH($D104, $G$2:$R$2, 0), R$1 <= (MATCH($D104, $G$2:$R$2, 0) + $D103 - 1)), (($D100/12)*$D102),""),""), "") | T101: =SUM(G101:R101) -> 0
C102: % of Factorial Support?
C103: How many months?
C104: First month of funding
C106: Dedicated Staff Member #12 | D106: NO
C107: Start date
C108: Role name | F108: =D108 | G108: =G109+G110 -> 0 | H108: =H109+H110 -> 0 | I108: =I109+I110 -> 0 | J108: =J109+J110 -> 0 | K108: =K109+K110 -> 0 | L108: =L109+L110 -> 0 | M108: =M109+M110 -> 0 | N108: =N109+N110 -> 0 | ... R108: =R109+R110 -> 0 | T108: =SUM(G108:R108) -> 0
C109: Final Annual Cost | F109: Salary | G109: =IF($D106="YES", IF($D107>0,IF(AND(G$1 >= MATCH($D107, $G$2:$R$2, 0)), -($D109/12), ""),""), "") | H109: =IF($D106="YES", IF($D107>0,IF(AND(H$1 >= MATCH($D107, $G$2:$R$2, 0)), -($D109/12), ""),""), "") | I109: =IF($D106="YES", IF($D107>0,IF(AND(I$1 >= MATCH($D107, $G$2:$R$2, 0)), -($D109/12), ""),""), "") | J109: =IF($D106="YES", IF($D107>0,IF(AND(J$1 >= MATCH($D107, $G$2:$R$2, 0)), -($D109/12), ""),""), "") | K109: =IF($D106="YES", IF($D107>0,IF(AND(K$1 >= MATCH($D107, $G$2:$R$2, 0)), -($D109/12), ""),""), "") | L109: =IF($D106="YES", IF($D107>0,IF(AND(L$1 >= MATCH($D107, $G$2:$R$2, 0)), -($D109/12), ""),""), "") | M109: =IF($D106="YES", IF($D107>0,IF(AND(M$1 >= MATCH($D107, $G$2:$R$2, 0)), -($D109/12), ""),""), "") | N109: =IF($D106="YES", IF($D107>0,IF(AND(N$1 >= MATCH($D107, $G$2:$R$2, 0)), -($D109/12), ""),""), "") | ... R109: =IF($D106="YES", IF($D107>0,IF(AND(R$1 >= MATCH($D107, $G$2:$R$2, 0)), -($D109/12), ""),""), "") | T109: =SUM(G109:R109) -> 0
C110: Factorial funds? | F110: Factorial Support | G110: =IF($D106="YES", if($D110="YES", IF(AND(G$1 >= MATCH($D113, $G$2:$R$2, 0), G$1 <= (MATCH($D113, $G$2:$R$2, 0) + $D112 - 1)), (($D109/12)*$D111),""),""), "") | H110: =IF($D106="YES", if($D110="YES", IF(AND(H$1 >= MATCH($D113, $G$2:$R$2, 0), H$1 <= (MATCH($D113, $G$2:$R$2, 0) + $D112 - 1)), (($D109/12)*$D111),""),""), "") | I110: =IF($D106="YES", if($D110="YES", IF(AND(I$1 >= MATCH($D113, $G$2:$R$2, 0), I$1 <= (MATCH($D113, $G$2:$R$2, 0) + $D112 - 1)), (($D109/12)*$D111),""),""), "") | J110: =IF($D106="YES", if($D110="YES", IF(AND(J$1 >= MATCH($D113, $G$2:$R$2, 0), J$1 <= (MATCH($D113, $G$2:$R$2, 0) + $D112 - 1)), (($D109/12)*$D111),""),""), "") | K110: =IF($D106="YES", if($D110="YES", IF(AND(K$1 >= MATCH($D113, $G$2:$R$2, 0), K$1 <= (MATCH($D113, $G$2:$R$2, 0) + $D112 - 1)), (($D109/12)*$D111),""),""), "") | L110: =IF($D106="YES", if($D110="YES", IF(AND(L$1 >= MATCH($D113, $G$2:$R$2, 0), L$1 <= (MATCH($D113, $G$2:$R$2, 0) + $D112 - 1)), (($D109/12)*$D111),""),""), "") | M110: =IF($D106="YES", if($D110="YES", IF(AND(M$1 >= MATCH($D113, $G$2:$R$2, 0), M$1 <= (MATCH($D113, $G$2:$R$2, 0) + $D112 - 1)), (($D109/12)*$D111),""),""), "") | N110: =IF($D106="YES", if($D110="YES", IF(AND(N$1 >= MATCH($D113, $G$2:$R$2, 0), N$1 <= (MATCH($D113, $G$2:$R$2, 0) + $D112 - 1)), (($D109/12)*$D111),""),""), "") | ... R110: =IF($D106="YES", if($D110="YES", IF(AND(R$1 >= MATCH($D113, $G$2:$R$2, 0), R$1 <= (MATCH($D113, $G$2:$R$2, 0) + $D112 - 1)), (($D109/12)*$D111),""),""), "") | T110: =SUM(G110:R110) -> 0
C111: % of Factorial Support?
C112: How many months?
...

Sheet B&I
O1: Actual | Q1: Plan
B2: Incentive Name | C2: KPI | D2: Period | E2: Incentive Type | F2: Amount | G2: Planned Pay Date | H2: Goal | I2: Actual | J2: Achieved? | K2: Amount to pay | L2: Month | O2: MRR | P2: DEMO | Q2: MRR | R2: DEMO
B3: Sales Fund Q1 | C3: MRR | D3: Q1 | E3: Lump sum | F3: =(35000)/4 -> 8750 | G3: March | H3: 6300 | I3: =IFERROR(IF(C3="","",IF(C3="MRR",VLOOKUP(D3,$N$1:$P$21,2,false),if(C3="DEMOs",(VLOOKUP(D3,$N$1:$P$21,3,FALSE)),""))),"") -> 0 | J3: =IF(I3="","",(IF(I3>=H3,"YES","NO"))) -> NO | K3: =if(E3="Lump sum",if(J3="YES",F3,""),if(E3="Accelerator",if(J3="YES",(I3*F3)-I3,""),"")) | N3: Yearly | O3: =SUM(O4:O5) -> 0 | P3: =SUM(P4:P5) -> 0 | Q3: =SUM(Q4:Q5) -> 35000 | R3: =SUM(R4:R5) -> 133
B4: Sales Fund Q2 | C4: MRR | D4: Q2 | E4: Lump sum | F4: =(35000)/4 -> 8750 | G4: June | H4: 8050 | I4: =IFERROR(IF(C4="","", IF(C4="MRR",VLOOKUP(D4,$N$1:$P$21,2,false),if(C4="DEMOs",(VLOOKUP(D4,$N$1:$P$21,3,FALSE)),""))),"") -> 0 | J4: =IF(I4="","",(IF(I4>=H4,"YES","NO"))) -> NO | K4: =if(E4="Lump sum",if(J4="YES",F4,""),if(E4="Accelerator",if(J4="YES",(I4*F4)-I4,""),"")) | N4: H1 | O4: =SUM(O6:O7) -> 0 | P4: =SUM(P6:P7) -> 0 | Q4: =SUM(Q6:Q7) -> 15050 | R4: =SUM(R6:R7) -> 53
B5: Sales Fund Q3 | C5: MRR | D5: Q3 | E5: Lump sum | F5: =(35000)/4 -> 8750 | G5: September | H5: 7700 | I5: =IFERROR(IF(C5="","",IF(C5="MRR",VLOOKUP(D5,$N$1:$P$21,2,false),if(C5="DEMOs",(VLOOKUP(D5,$N$1:$P$21,3,FALSE)),""))),"") -> 0 | J5: =IF(I5="","",(IF(I5>=H5,"YES","NO"))) -> NO | K5: =if(E5="Lump sum",if(J5="YES",F5,""),if(E5="Accelerator",if(J5="YES",(I5*F5)-I5,""),"")) | N5: H2 | O5: =SUM(O8:O9) -> 0 | P5: =SUM(P8:P9) -> 0 | Q5: =SUM(Q8:Q9) -> 19950 | R5: =SUM(R8:R9) -> 80
B6: Sales Fund Q4 | C6: MRR | D6: Q4 | E6: Lump sum | F6: =(35000)/4 -> 8750 | G6: December | H6: 12950 | I6: =IFERROR(IF(C6="","",IF(C6="MRR",VLOOKUP(D6,$N$1:$P$21,2,false),if(C6="DEMOs",(VLOOKUP(D6,$N$1:$P$21,3,FALSE)),""))),"") -> 0 | J6: =IF(I6="","",(IF(I6>=H6,"YES","NO"))) -> NO | K6: =if(E6="Lump sum",if(J6="YES",F6,""),if(E6="Accelerator",if(J6="YES",(I6*F6)-I6,""),"")) | N6: Q1 | O6: =SUM(O10:O12) -> 0 | P6: =SUM(P10:P12) -> 0 | Q6: =SUM(Q10:Q12) -> 6300 | R6: =SUM(R10:R12) -> 21
B7: Generation Fund (50% of DG costs) Q1 | C7: DEMOs | D7: Q1 | E7: Lump sum | F7: =SUMIF('Demand Generation Plan'!C:C,"=Q1",'Demand Generation Plan'!F:F)*0.5 -> 8450 | G7: March | H7: =if(E7="Lump sum","",if(E7="Accelerator",IF(C7="MRR",VLOOKUP(D7,$N$1:$R$21,4,false),if(C7="DEMOs",VLOOKUP(D7,$N$1:$R$21,5,FALSE),"")),"")) | I7: =IFERROR(IF(C7="","",IF(C7="MRR",VLOOKUP(D7,$N$1:$P$21,2,false),if(C7="DEMOs",(VLOOKUP(D7,$N$1:$P$21,3,FALSE)),""))),"") -> 0 | J7: =IF(I7="","",(IF(I7>=H7,"YES","NO"))) -> NO | K7: =if(E7="Lump sum",if(J7="YES",F7,""),if(E7="Accelerator",if(J7="YES",(I7*F7)-I7,""),"")) | N7: Q2 | O7: =SUM(O13:O15) -> 0 | P7: =SUM(P13:P15) -> 0 | Q7: =SUM(Q13:Q15) -> 8750 | R7: =SUM(R13:R15) -> 32
B8: Generation Fund (50% of DG costs) Q2 | C8: DEMOs | D8: Q2 | E8: Lump sum | F8: =SUMIF('Demand Generation Plan'!C:C,"=Q2",'Demand Generation Plan'!F:F)*0.5 -> 4800 | G8: June | H8: =if(E8="Lump sum","",if(E8="Accelerator",IF(C8="MRR",VLOOKUP(D8,$N$1:$R$21,4,false),if(C8="DEMOs",VLOOKUP(D8,$N$1:$R$21,5,FALSE),"")),"")) | I8: =IFERROR(IF(C8="","",IF(C8="MRR",VLOOKUP(D8,$N$1:$P$21,2,false),if(C8="DEMOs",(VLOOKUP(D8,$N$1:$P$21,3,FALSE)),""))),"") -> 0 | J8: =IF(I8="","",(IF(I8>=H8,"YES","NO"))) -> NO | K8: =if(E8="Lump sum",if(J8="YES",F8,""),if(E8="Accelerator",if(J8="YES",(I8*F8)-I8,""),"")) | N8: Q3 | O8: =SUM(O16:O18) -> 0 | P8: =SUM(P16:P18) -> 0 | Q8: =SUM(Q16:Q18) -> 9100 | R8: =SUM(R16:R18) -> 43
B9: Generation Fund (50% of DG costs) Q3 | C9: DEMOs | D9: Q3 | E9: Lump sum | F9: =SUMIF('Demand Generation Plan'!C:C,"=Q3",'Demand Generation Plan'!F:F)*0.5 -> 5300 | G9: September | H9: =if(E9="Lump sum","",if(E9="Accelerator",IF(C9="MRR",VLOOKUP(D9,$N$1:$R$21,4,false),if(C9="DEMOs",VLOOKUP(D9,$N$1:$R$21,5,FALSE),"")),"")) | I9: =IFERROR(IF(C9="","",IF(C9="MRR",VLOOKUP(D9,$N$1:$P$21,2,false),if(C9="DEMOs",(VLOOKUP(D9,$N$1:$P$21,3,FALSE)),""))),"") -> 0 | J9: =IF(I9="","",(IF(I9>=H9,"YES","NO"))) -> NO | K9: =if(E9="Lump sum",if(J9="YES",F9,""),if(E9="Accelerator",if(J9="YES",(I9*F9)-I9,""),"")) | N9: Q4 | O9: =SUM(O19:O21) -> 0 | P9: =SUM(P19:P21) -> 0 | Q9: =SUM(Q19:Q21) -> 10850 | R9: =SUM(R19:R21) -> 37
B10: Generation Fund (50% of DG costs) Q4 | C10: DEMOs | D10: Q4 | E10: Lump sum | F10: =SUMIF('Demand Generation Plan'!C:C,"=Q4",'Demand Generation Plan'!F:F)*0.5 -> 5800 | G10: December | H10: =if(E10="Lump sum","",if(E10="Accelerator",IF(C10="MRR",VLOOKUP(D10,$N$1:$R$21,4,false),if(C10="DEMOs",VLOOKUP(D10,$N$1:$R$21,5,FALSE),"")),"")) | I10: =IFERROR(IF(C10="","",IF(C10="MRR",VLOOKUP(D10,$N$1:$P$21,2,false),if(C10="DEMOs",(VLOOKUP(D10,$N$1:$P$21,3,FALSE)),""))),"") -> 0 | J10: =IF(I10="","",(IF(I10>=H10,"YES","NO"))) -> NO | K10: =if(E10="Lump sum",if(J10="YES",F10,""),if(E10="Accelerator",if(J10="YES",(I10*F10)-I10,""),"")) | N10: January | O10: ='Actual v Plan'!E12 -> 0 | P10: ='Actual v Plan'!E5 -> 0 | Q10: ='Actual v Plan'!D12 -> 1750 | R10: ='Actual v Plan'!D5 -> 5
H11: =if(E11="Lump sum","",if(E11="Accelerator",IF(C11="MRR",VLOOKUP(D11,$N$1:$R$21,4,false),if(C11="DEMOs",VLOOKUP(D11,$N$1:$R$21,5,FALSE),"")),"")) | I11: =IFERROR(IF(C11="","",IF(C11="MRR",VLOOKUP(D11,$N$1:$P$21,2,false),if(C11="DEMOs",(VLOOKUP(D11,$N$1:$P$21,3,FALSE)),""))),"") | J11: =IF(I11="","",(IF(I11>=H11,"YES","NO"))) | K11: =if(E11="Lump sum",if(J11="YES",F11,""),if(E11="Accelerator",if(J11="YES",(I11*F11)-I11,""),"")) | N11: February | O11: ='Actual v Plan'!J12 -> 0 | P11: ='Actual v Plan'!J5 -> 0 | Q11: ='Actual v Plan'!I12 -> 2100 | R11: ='Actual v Plan'!I5 -> 5
H12: =if(E12="Lump sum","",if(E12="Accelerator",IF(C12="MRR",VLOOKUP(D12,$N$1:$R$21,4,false),if(C12="DEMOs",VLOOKUP(D12,$N$1:$R$21,5,FALSE),"")),"")) | I12: =IFERROR(IF(C12="","",IF(C12="MRR",VLOOKUP(D12,$N$1:$P$21,2,false),if(C12="DEMOs",(VLOOKUP(D12,$N$1:$P$21,3,FALSE)),""))),"") | J12: =IF(I12="","",(IF(I12>=H12,"YES","NO"))) | K12: =if(E12="Lump sum",if(J12="YES",F12,""),if(E12="Accelerator",if(J12="YES",(I12*F12)-I12,""),"")) | N12: March | O12: ='Actual v Plan'!O12 -> 0 | P12: ='Actual v Plan'!O5 -> 0 | Q12: ='Actual v Plan'!N12 -> 2450 | R12: ='Actual v Plan'!N5 -> 11
H13: =if(E13="Lump sum","",if(E13="Accelerator",IF(C13="MRR",VLOOKUP(D13,$N$1:$R$21,4,false),if(C13="DEMOs",VLOOKUP(D13,$N$1:$R$21,5,FALSE),"")),"")) | I13: =IFERROR(IF(C13="","",IF(C13="MRR",VLOOKUP(D13,$N$1:$P$21,2,false),if(C13="DEMOs",(VLOOKUP(D13,$N$1:$P$21,3,FALSE)),""))),"") | J13: =IF(I13="","",(IF(I13>=H13,"YES","NO"))) | K13: =if(E13="Lump sum",if(J13="YES",F13,""),if(E13="Accelerator",if(J13="YES",(I13*F13)-I13,""),"")) | N13: April | O13: =SUM('Actual v Plan'!T12) -> 0 | P13: =SUM('Actual v Plan'!T5) -> 0 | Q13: =SUM('Actual v Plan'!S12) -> 2100 | R13: =SUM('Actual v Plan'!S5) -> 5
H14: =if(E14="Lump sum","",if(E14="Accelerator",IF(C14="MRR",VLOOKUP(D14,$N$1:$R$21,4,false),if(C14="DEMOs",VLOOKUP(D14,$N$1:$R$21,5,FALSE),"")),"")) | I14: =IFERROR(IF(C14="","",IF(C14="MRR",VLOOKUP(D14,$N$1:$P$21,2,false),if(C14="DEMOs",(VLOOKUP(D14,$N$1:$P$21,3,FALSE)),""))),"") | J14: =IF(I14="","",(IF(I14>=H14,"YES","NO"))) | K14: =if(E14="Lump sum",if(J14="YES",F14,""),if(E14="Accelerator",if(J14="YES",(I14*F14)-I14,""),"")) | N14: May | O14: =SUM('Actual v Plan'!Y12) -> 0 | P14: =SUM('Actual v Plan'!Y5) -> 0 | Q14: =SUM('Actual v Plan'!X12) -> 2450 | R14: =SUM('Actual v Plan'!X5) -> 11
H15: =if(E15="Lump sum","",if(E15="Accelerator",IF(C15="MRR",VLOOKUP(D15,$N$1:$R$21,4,false),if(C15="DEMOs",VLOOKUP(D15,$N$1:$R$21,5,FALSE),"")),"")) | I15: =IFERROR(IF(C15="","",IF(C15="MRR",VLOOKUP(D15,$N$1:$P$21,2,false),if(C15="DEMOs",(VLOOKUP(D15,$N$1:$P$21,3,FALSE)),""))),"") | J15: =IF(I15="","",(IF(I15>=H15,"YES","NO"))) | K15: =if(E15="Lump sum",if(J15="YES",F15,""),if(E15="Accelerator",if(J15="YES",(I15*F15)-I15,""),"")) | N15: June | O15: =SUM('Actual v Plan'!AD12) -> 0 | P15: =SUM('Actual v Plan'!AD5) -> 0 | Q15: =SUM('Actual v Plan'!AC12) -> 4200 | R15: =SUM('Actual v Plan'!AC5) -> 16
H16: =if(E16="Lump sum","",if(E16="Accelerator",IF(C16="MRR",VLOOKUP(D16,$N$1:$R$21,4,false),if(C16="DEMOs",VLOOKUP(D16,$N$1:$R$21,5,FALSE),"")),"")) | I16: =IFERROR(IF(C16="","",IF(C16="MRR",VLOOKUP(D16,$N$1:$P$21,2,false),if(C16="DEMOs",(VLOOKUP(D16,$N$1:$P$21,3,FALSE)),""))),"") | J16: =IF(I16="","",(IF(I16>=H16,"YES","NO"))) | K16: =if(E16="Lump sum",if(J16="YES",F16,""),if(E16="Accelerator",if(J16="YES",(I16*F16)-I16,""),"")) | N16: July | O16: =SUM('Actual v Plan'!AI12) -> 0 | P16: =SUM('Actual v Plan'!AI5) -> 0 | Q16: =SUM('Actual v Plan'!AH12) -> 2450 | R16: =SUM('Actual v Plan'!AH5) -> 11
H17: =if(E17="Lump sum","",if(E17="Accelerator",IF(C17="MRR",VLOOKUP(D17,$N$1:$R$21,4,false),if(C17="DEMOs",VLOOKUP(D17,$N$1:$R$21,5,FALSE),"")),"")) | I17: =IFERROR(IF(C17="","",IF(C17="MRR",VLOOKUP(D17,$N$1:$P$21,2,false),if(C17="DEMOs",(VLOOKUP(D17,$N$1:$P$21,3,FALSE)),""))),"") | J17: =IF(I17="","",(IF(I17>=H17,"YES","NO"))) | K17: =if(E17="Lump sum",if(J17="YES",F17,""),if(E17="Accelerator",if(J17="YES",(I17*F17)-I17,""),"")) | N17: August | O17: =SUM('Actual v Plan'!AN12) -> 0 | P17: =SUM('Actual v Plan'!AN5) -> 0 | Q17: =SUM('Actual v Plan'!AM12) -> 2800 | R17: =SUM('Actual v Plan'!AM5) -> 16
H18: =if(E18="Lump sum","",if(E18="Accelerator",IF(C18="MRR",VLOOKUP(D18,$N$1:$R$21,4,false),if(C18="DEMOs",VLOOKUP(D18,$N$1:$R$21,5,FALSE),"")),"")) | I18: =IFERROR(IF(C18="","",IF(C18="MRR",VLOOKUP(D18,$N$1:$P$21,2,false),if(C18="DEMOs",(VLOOKUP(D18,$N$1:$P$21,3,FALSE)),""))),"") | J18: =IF(I18="","",(IF(I18>=H18,"YES","NO"))) | K18: =if(E18="Lump sum",if(J18="YES",F18,""),if(E18="Accelerator",if(J18="YES",(I18*F18)-I18,""),"")) | N18: September | O18: =SUM('Actual v Plan'!AS12) -> 0 | P18: =SUM('Actual v Plan'!AS5) -> 0 | Q18: =SUM('Actual v Plan'!AR12) -> 3850 | R18: =SUM('Actual v Plan'!AR5) -> 16
H19: =if(E19="Lump sum","",if(E19="Accelerator",IF(C19="MRR",VLOOKUP(D19,$N$1:$R$21,4,false),if(C19="DEMOs",VLOOKUP(D19,$N$1:$R$21,5,FALSE),"")),"")) | I19: =IFERROR(IF(C19="","",IF(C19="MRR",VLOOKUP(D19,$N$1:$P$21,2,false),if(C19="DEMOs",(VLOOKUP(D19,$N$1:$P$21,3,FALSE)),""))),"") | J19: =IF(I19="","",(IF(I19>=H19,"YES","NO"))) | K19: =if(E19="Lump sum",if(J19="YES",F19,""),if(E19="Accelerator",if(J19="YES",(I19*F19)-I19,""),"")) | N19: October | O19: =SUM('Actual v Plan'!AX12) -> 0 | P19: =SUM('Actual v Plan'!AX5) -> 0 | Q19: =SUM('Actual v Plan'!AW12) -> 4200 | R19: =SUM('Actual v Plan'!AW5) -> 16
H20: =if(E20="Lump sum","",if(E20="Accelerator",IF(C20="MRR",VLOOKUP(D20,$N$1:$R$21,4,false),if(C20="DEMOs",VLOOKUP(D20,$N$1:$R$21,5,FALSE),"")),"")) | I20: =IFERROR(IF(C20="","",IF(C20="MRR",VLOOKUP(D20,$N$1:$P$21,2,false),if(C20="DEMOs",(VLOOKUP(D20,$N$1:$P$21,3,FALSE)),""))),"") | J20: =IF(I20="","",(IF(I20>=H20,"YES","NO"))) | K20: =if(E20="Lump sum",if(J20="YES",F20,""),if(E20="Accelerator",if(J20="YES",(I20*F20)-I20,""),"")) | N20: November | O20: =SUM('Actual v Plan'!BC12) -> 0 | P20: =SUM('Actual v Plan'!BC5) -> 0 | Q20: =SUM('Actual v Plan'!BB12) -> 4550 | R20: =SUM('Actual v Plan'!BB5) -> 16
H21: =if(E21="Lump sum","",if(E21="Accelerator",IF(C21="MRR",VLOOKUP(D21,$N$1:$R$21,4,false),if(C21="DEMOs",VLOOKUP(D21,$N$1:$R$21,5,FALSE),"")),"")) | I21: =IFERROR(IF(C21="","",IF(C21="MRR",VLOOKUP(D21,$N$1:$P$21,2,false),if(C21="DEMOs",(VLOOKUP(D21,$N$1:$P$21,3,FALSE)),""))),"") | J21: =IF(I21="","",(IF(I21>=H21,"YES","NO"))) | K21: =if(E21="Lump sum",if(J21="YES",F21,""),if(E21="Accelerator",if(J21="YES",(I21*F21)-I21,""),"")) | N21: December | O21: =SUM('Actual v Plan'!BH12) -> 0 | P21: =SUM('Actual v Plan'!BH5) -> 0 | Q21: =SUM('Actual v Plan'!BG12) -> 2100 | R21: =SUM('Actual v Plan'!BG5) -> 5
H22: =if(E22="Lump sum","",if(E22="Accelerator",IF(C22="MRR",VLOOKUP(D22,$N$1:$R$21,4,false),if(C22="DEMOs",VLOOKUP(D22,$N$1:$R$21,5,FALSE),"")),"")) | I22: =IFERROR(IF(C22="","",IF(C22="MRR",VLOOKUP(D22,$N$1:$P$21,2,false),if(C22="DEMOs",(VLOOKUP(D22,$N$1:$P$21,3,FALSE)),""))),"") | J22: =IF(I22="","",(IF(I22>=H22,"YES","NO"))) | K22: =if(E22="Lump sum",if(J22="YES",F22,""),if(E22="Accelerator",if(J22="YES",(I22*F22)-I22,""),""))
H23: =if(E23="Lump sum","",if(E23="Accelerator",IF(C23="MRR",VLOOKUP(D23,$N$1:$R$21,4,false),if(C23="DEMOs",VLOOKUP(D23,$N$1:$R$21,5,FALSE),"")),"")) | I23: =IFERROR(IF(C23="","",IF(C23="MRR",VLOOKUP(D23,$N$1:$P$21,2,false),if(C23="DEMOs",(VLOOKUP(D23,$N$1:$P$21,3,FALSE)),""))),"") | J23: =IF(I23="","",(IF(I23>=H23,"YES","NO"))) | K23: =if(E23="Lump sum",if(J23="YES",F23,""),if(E23="Accelerator",if(J23="YES",(I23*F23)-I23,""),""))
H24: =if(E24="Lump sum","",if(E24="Accelerator",IF(C24="MRR",VLOOKUP(D24,$N$1:$R$21,4,false),if(C24="DEMOs",VLOOKUP(D24,$N$1:$R$21,5,FALSE),"")),"")) | I24: =IFERROR(IF(C24="","",IF(C24="MRR",VLOOKUP(D24,$N$1:$P$21,2,false),if(C24="DEMOs",(VLOOKUP(D24,$N$1:$P$21,3,FALSE)),""))),"") | J24: =IF(I24="","",(IF(I24>=H24,"YES","NO"))) | K24: =if(E24="Lump sum",if(J24="YES",F24,""),if(E24="Accelerator",if(J24="YES",(I24*F24)-I24,""),""))
H25: =if(E25="Lump sum","",if(E25="Accelerator",IF(C25="MRR",VLOOKUP(D25,$N$1:$R$21,4,false),if(C25="DEMOs",VLOOKUP(D25,$N$1:$R$21,5,FALSE),"")),"")) | I25: =IFERROR(IF(C25="","",IF(C25="MRR",VLOOKUP(D25,$N$1:$P$21,2,false),if(C25="DEMOs",(VLOOKUP(D25,$N$1:$P$21,3,FALSE)),""))),"") | J25: =IF(I25="","",(IF(I25>=H25,"YES","NO"))) | K25: =if(E25="Lump sum",if(J25="YES",F25,""),if(E25="Accelerator",if(J25="YES",(I25*F25)-I25,""),""))
H26: =if(E26="Lump sum","",if(E26="Accelerator",IF(C26="MRR",VLOOKUP(D26,$N$1:$R$21,4,false),if(C26="DEMOs",VLOOKUP(D26,$N$1:$R$21,5,FALSE),"")),"")) | I26: =IFERROR(IF(C26="","",IF(C26="MRR",VLOOKUP(D26,$N$1:$P$21,2,false),if(C26="DEMOs",(VLOOKUP(D26,$N$1:$P$21,3,FALSE)),""))),"") | J26: =IF(I26="","",(IF(I26>=H26,"YES","NO"))) | K26: =if(E26="Lump sum",if(J26="YES",F26,""),if(E26="Accelerator",if(J26="YES",(I26*F26)-I26,""),""))
H27: =if(E27="Lump sum","",if(E27="Accelerator",IF(C27="MRR",VLOOKUP(D27,$N$1:$R$21,4,false),if(C27="DEMOs",VLOOKUP(D27,$N$1:$R$21,5,FALSE),"")),"")) | I27: =IFERROR(IF(C27="","",IF(C27="MRR",VLOOKUP(D27,$N$1:$P$21,2,false),if(C27="DEMOs",(VLOOKUP(D27,$N$1:$P$21,3,FALSE)),""))),"") | J27: =IF(I27="","",(IF(I27>=H27,"YES","NO"))) | K27: =if(E27="Lump sum",if(J27="YES",F27,""),if(E27="Accelerator",if(J27="YES",(I27*F27)-I27,""),""))
H28: =if(E28="Lump sum","",if(E28="Accelerator",IF(C28="MRR",VLOOKUP(D28,$N$1:$R$21,4,false),if(C28="DEMOs",VLOOKUP(D28,$N$1:$R$21,5,FALSE),"")),"")) | I28: =IFERROR(IF(C28="","",IF(C28="MRR",VLOOKUP(D28,$N$1:$P$21,2,false),if(C28="DEMOs",(VLOOKUP(D28,$N$1:$P$21,3,FALSE)),""))),"") | J28: =IF(I28="","",(IF(I28>=H28,"YES","NO"))) | K28: =if(E28="Lump sum",if(J28="YES",F28,""),if(E28="Accelerator",if(J28="YES",(I28*F28)-I28,""),""))
H29: =if(E29="Lump sum","",if(E29="Accelerator",IF(C29="MRR",VLOOKUP(D29,$N$1:$R$21,4,false),if(C29="DEMOs",VLOOKUP(D29,$N$1:$R$21,5,FALSE),"")),"")) | I29: =IFERROR(IF(C29="","",IF(C29="MRR",VLOOKUP(D29,$N$1:$P$21,2,false),if(C29="DEMOs",(VLOOKUP(D29,$N$1:$P$21,3,FALSE)),""))),"") | J29: =IF(I29="","",(IF(I29>=H29,"YES","NO"))) | K29: =if(E29="Lump sum",if(J29="YES",F29,""),if(E29="Accelerator",if(J29="YES",(I29*F29)-I29,""),""))
H30: =if(E30="Lump sum","",if(E30="Accelerator",IF(C30="MRR",VLOOKUP(D30,$N$1:$R$21,4,false),if(C30="DEMOs",VLOOKUP(D30,$N$1:$R$21,5,FALSE),"")),"")) | I30: =IFERROR(IF(C30="","",IF(C30="MRR",VLOOKUP(D30,$N$1:$P$21,2,false),if(C30="DEMOs",(VLOOKUP(D30,$N$1:$P$21,3,FALSE)),""))),"") | J30: =IF(I30="","",(IF(I30>=H30,"YES","NO"))) | K30: =if(E30="Lump sum",if(J30="YES",F30,""),if(E30="Accelerator",if(J30="YES",(I30*F30)-I30,""),""))
H31: =if(E31="Lump sum","",if(E31="Accelerator",IF(C31="MRR",VLOOKUP(D31,$N$1:$R$21,4,false),if(C31="DEMOs",VLOOKUP(D31,$N$1:$R$21,5,FALSE),"")),"")) | I31: =IFERROR(IF(C31="","",IF(C31="MRR",VLOOKUP(D31,$N$1:$P$21,2,false),if(C31="DEMOs",(VLOOKUP(D31,$N$1:$P$21,3,FALSE)),""))),"") | J31: =IF(I31="","",(IF(I31>=H31,"YES","NO"))) | K31: =if(E31="Lump sum",if(J31="YES",F31,""),if(E31="Accelerator",if(J31="YES",(I31*F31)-I31,""),""))
H32: =if(E32="Lump sum","",if(E32="Accelerator",IF(C32="MRR",VLOOKUP(D32,$N$1:$R$21,4,false),if(C32="DEMOs",VLOOKUP(D32,$N$1:$R$21,5,FALSE),"")),"")) | I32: =IFERROR(IF(C32="","",IF(C32="MRR",VLOOKUP(D32,$N$1:$P$21,2,false),if(C32="DEMOs",(VLOOKUP(D32,$N$1:$P$21,3,FALSE)),""))),"") | J32: =IF(I32="","",(IF(I32>=H32,"YES","NO"))) | K32: =if(E32="Lump sum",if(J32="YES",F32,""),if(E32="Accelerator",if(J32="YES",(I32*F32)-I32,""),""))
H33: =if(E33="Lump sum","",if(E33="Accelerator",IF(C33="MRR",VLOOKUP(D33,$N$1:$R$21,4,false),if(C33="DEMOs",VLOOKUP(D33,$N$1:$R$21,5,FALSE),"")),"")) | I33: =IFERROR(IF(C33="","",IF(C33="MRR",VLOOKUP(D33,$N$1:$P$21,2,false),if(C33="DEMOs",(VLOOKUP(D33,$N$1:$P$21,3,FALSE)),""))),"") | J33: =IF(I33="","",(IF(I33>=H33,"YES","NO"))) | K33: =if(E33="Lump sum",if(J33="YES",F33,""),if(E33="Accelerator",if(J33="YES",(I33*F33)-I33,""),""))
... H291: =if(E291="Lump sum","",if(E291="Accelerator",IF(C291="MRR",VLOOKUP(D291,$N$1:$R$21,4,false),if(C291="DEMOs",VLOOKUP(D291,$N$1:$R$21,5,FALSE),"")),"")) | I291: =IFERROR(IF(C291="","",IF(C291="MRR",VLOOKUP(D291,$N$1:$P$21,2,false),if(C291="DEMOs",(VLOOKUP(D291,$N$1:$P$21,3,FALSE)),""))),"") | J291: =IF(I291="","",(IF(I291>=H291,"YES","NO"))) | K291: =if(E291="Lump sum",if(J291="YES",F291,""),if(E291="Accelerator",if(J291="YES",(I291*F291)-I291,""),""))
K292: =if(J292="YES",F292,"") | L292: =if(G292="","", date(year(G292),month(G292),1))

Sheet Actual Dashboard
D1: 46023 | E1: 46024 | F1: 46025 | G1: 46026 | H1: 46027 | I1: 46028 | J1: 46029 | K1: 46030 | L1: 46031 | M1: 46032 | N1: 46033 | O1: 46034
C2: Actual Dashboard | D2: Q1 | G2: Q2 | J2: Q3 | M2: Q4 | Q2: Q1 | R2: Q2 | S2: Q3 | T2: Q4 | U2: Total
D3: January | E3: February | F3: March | G3: April | H3: May | I3: June | J3: July | K3: August | L3: September | M3: October | N3: November | O3: December
C4: Demos # | D4: ='Actual v Plan'!E5 -> 0 | E4: ='Actual v Plan'!J5 -> 0 | F4: ='Actual v Plan'!O5 -> 0 | G4: ='Actual v Plan'!T5 -> 0 | H4: ='Actual v Plan'!Y5 -> 0 | I4: ='Actual v Plan'!AD5 -> 0 | J4: ='Actual v Plan'!AI5 -> 0 | K4: ='Actual v Plan'!AN5 -> 0 | L4: ='Actual v Plan'!AS5 -> 0 | M4: ='Actual v Plan'!AX5 -> 0 | N4: ='Actual v Plan'!BC5 -> 0 | O4: ='Actual v Plan'!BH5 -> 0 | Q4: =SUM(D4:F4) -> 0 | R4: =SUM(G4:I4) -> 0 | S4: =SUM(J4:L4) -> 0 | T4: =SUM(M3:O4) -> 0 | U4: =SUM(D4:O4) -> 0
C5: Plan v Actual Demos | D5: =IF(D4>0,-(#REF!-D4),"") | E5: =IF(E4>0,-#REF!-E4,"") | F5: =IF(F4>0,-#REF!-F4,"") | G5: =IF(G4>0,-#REF!-G4,"") | H5: =IF(H4>0,-#REF!-H4,"") | I5: =IF(I4>0,-#REF!-I4,"") | J5: =IF(J4>0,-#REF!-J4,"") | K5: =IF(K4>0,-#REF!-K4,"") | L5: =IF(L4>0,-#REF!-L4,"") | ... O5: =IF(O4>0,-#REF!-O4,"") | Q5: =SUM(D5:F5) -> 0 | R5: =SUM(G5:I5) -> 0 | S5: =SUM(J5:L5) -> 0 | T5: =SUM(M4:O5) -> 0 | U5: =U4*12 -> 0
E6: =D6 | F6: =E6 | G6: =F6 | H6: =G6 | I6: =H6 | J6: =I6 | K6: =J6 | L6: =K6 | ... O6: =N6
C7: Won MRR | D7: ='Actual v Plan'!E12 -> 0 | E7: ='Actual v Plan'!J12 -> 0 | F7: ='Actual v Plan'!O12 -> 0 | G7: ='Actual v Plan'!T12 -> 0 | H7: ='Actual v Plan'!Y12 -> 0 | I7: ='Actual v Plan'!AD12 -> 0 | J7: ='Actual v Plan'!AI12 -> 0 | K7: ='Actual v Plan'!AN12 -> 0 | L7: ='Actual v Plan'!AS12 -> 0 | M7: ='Actual v Plan'!AX12 -> 0 | N7: ='Actual v Plan'!BC12 -> 0 | O7: ='Actual v Plan'!BH12 -> 0 | Q7: =SUM(D7:F7) -> 0 | R7: =SUM(G7:I7) -> 0 | S7: =SUM(J7:L7) -> 0 | T7: =SUM(M6:O7) -> 0 | U7: =SUM(D7:O7) -> 0
C8: Plan v Actual MRR | D8: =IF(D7>0,-('Plan Summary'!D6-D7),if(TODAY()>D1,-('Plan Summary'!D6-D7),"")) | E8: =IF(E7>0,-('Plan Summary'!E6-E7),if(TODAY()>E1,-('Plan Summary'!E6-E7),"")) | F8: =IF(F7>0,-('Plan Summary'!F6-F7),if(TODAY()>F1,-('Plan Summary'!F6-F7),"")) | G8: =IF(G7>0,-('Plan Summary'!G6-G7),if(TODAY()>G1,-('Plan Summary'!G6-G7),"")) | H8: =IF(H7>0,-('Plan Summary'!H6-H7),if(TODAY()>H1,-('Plan Summary'!H6-H7),"")) | I8: =IF(I7>0,-('Plan Summary'!I6-I7),if(TODAY()>I1,-('Plan Summary'!I6-I7),"")) | J8: =IF(J7>0,-('Plan Summary'!J6-J7),if(TODAY()>J1,-('Plan Summary'!J6-J7),"")) | K8: =IF(K7>0,-('Plan Summary'!K6-K7),if(TODAY()>K1,-('Plan Summary'!K6-K7),"")) | ... O8: =IF(O7>0,-('Plan Summary'!O6-O7),if(TODAY()>O1,-('Plan Summary'!O6-O7),""))
C9: Won ARR | D9: =D7*12 -> 0 | E9: =E7*12 -> 0 | F9: =F7*12 -> 0 | G9: =G7*12 -> 0 | H9: =H7*12 -> 0 | I9: =I7*12 -> 0 | J9: =J7*12 -> 0 | K9: =K7*12 -> 0 | ... O9: =O7*12 -> 0 | Q9: =SUM(D9:F9) -> 0 | R9: =SUM(G9:I9) -> 0 | S9: =SUM(J9:L9) -> 0 | T9: =SUM(M7:O9) -> 0 | U9: =U7*12 -> 0
C11: Total Commissions | D11: =SUM(D17:D20) -> 0 | E11: =SUM(E17:E20) -> 0 | F11: =SUM(F17:F20) -> 0 | G11: =SUM(G17:G20) -> 0 | H11: =SUM(H17:H20) -> 0 | I11: =SUM(I17:I20) -> 0 | J11: =SUM(J17:J20) -> 0 | K11: =SUM(K17:K20) -> 0 | ... O11: =SUM(O17:O20) -> 0 | Q11: =SUM(D11:F11) -> 0 | R11: =SUM(G11:I11) -> 0 | S11: =SUM(J11:L11) -> 0 | T11: =SUM(M10:O11) -> 0 | U11: =SUM(D11:O11) -> 0
C13: Total Invested | D13: =(D22+D23)+D24 -> 0 | E13: =(E22+E23)+E24 -> 0 | F13: =(F22+F23)+F24 -> 0 | G13: =(G22+G23)+G24 -> 0 | H13: =(H22+H23)+H24 -> 0 | I13: =(I22+I23)+I24 -> 0 | J13: =(J22+J23)+J24 -> 0 | K13: =(K22+K23)+K24 -> 0 | ... O13: =(O22+O23)+O24 -> 0 | Q13: =SUM(D13:F13) -> 0 | R13: =SUM(G13:I13) -> 0 | S13: =SUM(J13:L13) -> 0 | T13: =SUM(M12:O13) -> 0 | U13: =SUM(D13:O13) -> 0
C15: Total Balance (P v L) | D15: =D11+D13 -> 0 | E15: =E11+E13 -> 0 | F15: =F11+F13 -> 0 | G15: =G11+G13 -> 0 | H15: =H11+H13 -> 0 | I15: =I11+I13 -> 0 | J15: =J11+J13 -> 0 | K15: =K11+K13 -> 0 | ... O15: =O11+O13 -> 0 | Q15: =SUM(D15:F15) -> 0 | R15: =SUM(G15:I15) -> 0 | S15: =SUM(J15:L15) -> 0 | T15: =SUM(M14:O15) -> 0 | U15: =SUM(D15:O15) -> 0
C17: Commissions - Sales | D17: ='Actual v Plan'!E18 -> 0 | E17: ='Actual v Plan'!J18 | F17: ='Actual v Plan'!O18 | G17: ='Actual v Plan'!T18 | H17: ='Actual v Plan'!Y18 | I17: ='Actual v Plan'!AD18 | J17: ='Actual v Plan'!AI18 | K17: ='Actual v Plan'!AN18 | L17: ='Actual v Plan'!AS18 | M17: ='Actual v Plan'!AX18 | N17: ='Actual v Plan'!BC18 | O17: ='Actual v Plan'!BH18 | Q17: =SUM(D17:F17) -> 0 | R17: =SUM(G17:I17) -> 0 | S17: =SUM(J17:L17) -> 0 | T17: =SUM(M9:O17) -> 0 | U17: =SUM(D17:O17) -> 0
C18: Commissions - Integrations | D18: ='Actual v Plan'!E19 | E18: ='Actual v Plan'!J19 | F18: ='Actual v Plan'!O19 | G18: ='Actual v Plan'!T19 | H18: ='Actual v Plan'!Y19 | I18: ='Actual v Plan'!AD19 | J18: ='Actual v Plan'!AI19 | K18: ='Actual v Plan'!AN19 | L18: ='Actual v Plan'!AS19 | M18: ='Actual v Plan'!AX19 | N18: ='Actual v Plan'!BC19 | O18: ='Actual v Plan'!BH19 | Q18: =SUM(D18:F18) -> 0 | R18: =SUM(G18:I18) -> 0 | S18: =SUM(J18:L18) -> 0 | T18: =SUM(M17:O18) -> 0 | U18: =SUM(D18:O18) -> 0
C19: Onboardings | D19: ='Actual v Plan'!E20 | E19: ='Actual v Plan'!J20 | F19: ='Actual v Plan'!O20 | G19: ='Actual v Plan'!T20 | H19: ='Actual v Plan'!Y20 | I19: ='Actual v Plan'!AD20 | J19: ='Actual v Plan'!AI20 | K19: ='Actual v Plan'!AN20 | L19: ='Actual v Plan'!AS20 | M19: ='Actual v Plan'!AX20 | N19: ='Actual v Plan'!BC20 | O19: ='Actual v Plan'!BH20
C20: Bonus & Incentives | D20: ='Actual v Plan'!E21 -> 0 | E20: ='Actual v Plan'!J21 -> 0 | F20: ='Actual v Plan'!O21 -> 0 | G20: ='Actual v Plan'!T21 -> 0 | H20: ='Actual v Plan'!Y21 -> 0 | I20: ='Actual v Plan'!AD21 -> 0 | J20: ='Actual v Plan'!AI21 -> 0 | K20: ='Actual v Plan'!AN21 -> 0 | L20: ='Actual v Plan'!AS21 -> 0 | M20: ='Actual v Plan'!AX21 -> 0 | N20: ='Actual v Plan'!BC21 -> 0 | O20: ='Actual v Plan'!BH21 -> 0 | Q20: =SUM(D20:F20) -> 0 | R20: =SUM(G20:I20) -> 0 | S20: =SUM(J20:L20) -> 0 | T20: =SUM(M18:O20) -> 0
C21: Funded Heads | D21: =D22-D23 -> 0 | E21: =E22-E23 -> 0 | F21: =F22-F23 -> 0 | G21: =G22-G23 -> 0 | H21: =H22-H23 -> 0 | I21: =I22-I23 -> 0 | J21: =J22-J23 -> 0 | K21: =K22-K23 -> 0 | ... O21: =O22-O23 -> 0 | Q21: =SUM(D21:F21) -> 0 | R21: =SUM(G21:I21) -> 0 | S21: =SUM(J21:L21) -> 0 | T21: =SUM(M10:O21) -> 0 | U21: =SUM(D21:O21) -> 0
C22: Monthly Salary | D22: ='Actual v Plan'!E30 | E22: ='Actual v Plan'!J30 | F22: ='Actual v Plan'!O30 | G22: ='Actual v Plan'!T30 | H22: ='Actual v Plan'!Y30 | I22: ='Actual v Plan'!AD30 | J22: ='Actual v Plan'!AI30 | K22: ='Actual v Plan'!AN30 | L22: ='Actual v Plan'!AS30 | M22: ='Actual v Plan'!AX30 | N22: ='Actual v Plan'!BC30 | O22: ='Actual v Plan'!BH30 | Q22: =SUM(D22:F22) -> 0 | R22: =SUM(G22:I22) -> 0 | S22: =SUM(J22:L22) -> 0 | T22: =SUM(M21:O22) -> 0 | U22: =SUM(D22:O22) -> 0
C23: Factorial Support | D23: ='Actual v Plan'!E31 | E23: ='Actual v Plan'!J31 | F23: ='Actual v Plan'!O31 | G23: ='Actual v Plan'!T31 | H23: ='Actual v Plan'!Y31 | I23: ='Actual v Plan'!AD31 | J23: ='Actual v Plan'!AI31 | K23: ='Actual v Plan'!AN31 | L23: ='Actual v Plan'!AS31 | M23: ='Actual v Plan'!AX31 | N23: ='Actual v Plan'!BC31 | O23: ='Actual v Plan'!BH31 | Q23: =SUM(D23:F23) -> 0 | R23: =SUM(G23:I23) -> 0 | S23: =SUM(J23:L23) -> 0 | T23: =SUM(M22:O23) -> 0 | U23: =SUM(D23:O23) -> 0
C24: Budget | D24: =-sumif('Demand Generation Plan'!$D$4:$D24,D3,'Demand Generation Plan'!$R$4:$R24) -> 0 | E24: =-sumif('Demand Generation Plan'!$D$4:$D24,E3,'Demand Generation Plan'!$R$4:$R24) -> 0 | F24: =-sumif('Demand Generation Plan'!$D$4:$D24,F3,'Demand Generation Plan'!$R$4:$R24) -> 0 | G24: =-sumif('Demand Generation Plan'!$D$4:$D24,G3,'Demand Generation Plan'!$R$4:$R24) -> 0 | H24: =-sumif('Demand Generation Plan'!$D$4:$D24,H3,'Demand Generation Plan'!$R$4:$R24) -> 0 | I24: =-sumif('Demand Generation Plan'!$D$4:$D24,I3,'Demand Generation Plan'!$R$4:$R24) -> 0 | J24: =-sumif('Demand Generation Plan'!$D$4:$D24,J3,'Demand Generation Plan'!$R$4:$R24) -> 0 | K24: =-sumif('Demand Generation Plan'!$D$4:$D24,K3,'Demand Generation Plan'!$R$4:$R24) -> 0 | ... O24: =-sumif('Demand Generation Plan'!$D$4:$D24,O3,'Demand Generation Plan'!$R$4:$R24) -> 0 | Q24: =SUM(D24:F24) -> 0 | R24: =SUM(G24:I24) -> 0 | S24: =SUM(J24:L24) -> 0 | T24: =SUM(M24:O24) -> 0 | U24: =SUM(D24:O24) -> 0

Sheet Actual v Plan
E1: 46023 | F1: 46054 | J1: 46054 | K1: 46082 | O1: 46082 | P1: 46113 | T1: 46113 | U1: 46143 | Y1: 46143 | Z1: 46174 | AD1: 46174 | AE1: 46204 | AI1: 46204 | AJ1: 46235 | AN1: 46235 | AO1: 46266 | AS1: 46266 | AT1: 46296 | AX1: 46296 | AY1: 46327 | BC1: 46327 | BD1: 46357 | BH1: 46357 | BI1: 46388
D2: Q1 | S2: Q2 | AH2: Q3 | AW2: Q4 | BL2: TOTAL | BQ2: Q1 | BV2: Q2 | CA2: Q3 | CF2: Q4
D3: January | I3: February | N3: March | S3: April | X3: May | AC3: June | AH3: July | AM3: August | AR3: September | AW3: October | BB3: November | BG3: December
D4: Plan | E4: Actual | F4: Actual vs Plan | I4: Plan | J4: Actual | K4: Actual vs Plan | N4: Plan | O4: Actual | P4: Actual vs Plan | S4: Plan | T4: Actual | U4: Actual vs Plan | X4: Plan | Y4: Actual | Z4: Actual vs Plan | AC4: Plan | AD4: Actual | AE4: Actual vs Plan | AH4: Plan | AI4: Actual | AJ4: Actual vs Plan | AM4: Plan | AN4: Actual | AO4: Actual vs Plan | AR4: Plan | AS4: Actual | AT4: Actual vs Plan | AW4: Plan | AX4: Actual | AY4: Actual vs Plan | BB4: Plan | BC4: Actual | BD4: Actual vs Plan | BG4: Plan | BH4: Actual | BI4: Actual vs Plan | BL4: Plan | BM4: Actual | BN4: Actual vs Plan | BQ4: Plan | BR4: Actual | BS4: Actual vs Plan | BV4: Plan | BW4: Actual | BX4: Actual vs Plan | CA4: Plan | CB4: Actual | CC4: Actual vs Plan | CF4: Plan | CG4: Actual | CH4: Actual vs Plan
C5: Demos # | D5: ='Business Plan'!E4 -> 5 | E5: =SUMIFS('DATA-IMP'!$Y$3:$Y43, 'DATA-IMP'!$E$3:$E43, ">" & E$1, 'DATA-IMP'!$E$3:$E43, "<" & F$1) -> 0 | F5: =E5-D5 -> -5 | G5: =iferror(E5/D5,"") -> 0 | I5: ='Business Plan'!F4 -> 5 | J5: =SUMIFS('DATA-IMP'!$Y$3:$Y43, 'DATA-IMP'!$E$3:$E43, ">" & J$1, 'DATA-IMP'!$E$3:$E43, "<" & K$1) -> 0 | K5: =J5-I$5 -> -5 | L5: =iferror(J5/I5,"") -> 0 | N5: ='Business Plan'!G4 -> 11 | O5: =SUMIFS('DATA-IMP'!$Y$3:$Y43, 'DATA-IMP'!$E$3:$E43, ">" & O$1, 'DATA-IMP'!$E$3:$E43, "<" & P$1) -> 0 | P5: =O5-N$5 -> -11 | Q5: =iferror(O5/N5,"") -> 0 | S5: ='Business Plan'!H4 -> 5 | T5: =SUMIFS('DATA-IMP'!$Y$3:$Y43, 'DATA-IMP'!$E$3:$E43, ">" & T$1, 'DATA-IMP'!$E$3:$E43, "<" & U$1) -> 0 | U5: =T5-S$5 -> -5 | V5: =iferror(T5/S5,"") -> 0 | X5: ='Business Plan'!I4 -> 11 | Y5: =SUMIFS('DATA-IMP'!$Y$3:$Y43, 'DATA-IMP'!$E$3:$E43, ">" & Y$1, 'DATA-IMP'!$E$3:$E43, "<" & Z$1) -> 0 | Z5: =Y5-X$5 -> -11 | AA5: =iferror(Y5/X5,"") -> 0 | AC5: ='Business Plan'!J4 -> 16 | AD5: =SUMIFS('DATA-IMP'!$Y$3:$Y43, 'DATA-IMP'!$E$3:$E43, ">" & AD$1, 'DATA-IMP'!$E$3:$E43, "<" & AE$1) -> 0 | AE5: =AD5-AC$5 -> -16 | AF5: =iferror(AD5/AC5,"") -> 0 | AH5: ='Business Plan'!K4 -> 11 | AI5: =SUMIFS('DATA-IMP'!$Y$3:$Y43, 'DATA-IMP'!$E$3:$E43, ">" & AI$1, 'DATA-IMP'!$E$3:$E43, "<" & AJ$1) -> 0 | AJ5: =AI5-AH$5 -> -11 | AK5: =iferror(AI5/AH5,"") -> 0 | AM5: ='Business Plan'!L4 -> 16 | AN5: =SUMIFS('DATA-IMP'!$Y$3:$Y43, 'DATA-IMP'!$E$3:$E43, ">" & AN$1, 'DATA-IMP'!$E$3:$E43, "<" & AO$1) -> 0 | AO5: =AN5-AM$5 -> -16 | AP5: =iferror(AN5/AM5,"") -> 0 | AR5: ='Business Plan'!M4 -> 16 | AS5: =SUMIFS('DATA-IMP'!$Y$3:$Y43, 'DATA-IMP'!$E$3:$E43, ">" & AS$1, 'DATA-IMP'!$E$3:$E43, "<" & AT$1) -> 0 | AT5: =AS5-AR$5 -> -16 | AU5: =iferror(AS5/AR5,"") -> 0 | AW5: ='Business Plan'!N4 -> 16 | AX5: =SUMIFS('DATA-IMP'!$Y$3:$Y43, 'DATA-IMP'!$E$3:$E43, ">" & AX$1, 'DATA-IMP'!$E$3:$E43, "<" & AY$1) -> 0 | AY5: =AX5-AW$5 -> -16 | AZ5: =iferror(AX5/AW5,"") -> 0 | BB5: ='Business Plan'!O4 -> 16 | BC5: =SUMIFS('DATA-IMP'!$Y$3:$Y43, 'DATA-IMP'!$E$3:$E43, ">" & BC$1, 'DATA-IMP'!$E$3:$E43, "<" & BD$1) -> 0 | BD5: =BC5-BB$5 -> -16 | BE5: =iferror(BC5/BB5,"") -> 0 | BG5: ='Business Plan'!P4 -> 5 | BH5: =SUMIFS('DATA-IMP'!$Y$3:$Y43, 'DATA-IMP'!$E$3:$E43, ">" & BH$1, 'DATA-IMP'!$E$3:$E43, "<" & BI$1) -> 0 | BI5: =BH5-BG$5 -> -5 | BJ5: =iferror(BH5/BG5,"") -> 0 | BL5: =SUM(BG5,BB5,AW5,AR5,AM5,AH5,AC5,X5,S5,N5,I5,D5,) -> 133 | BM5: =SUM(BH5,BC5,AX5,AS5,AN5,AI5,AD5,Y5,T5,O5,J5,E5,) -> 0 | BN5: =BM5-BL$5 -> -133 | BO5: =iferror(BM5/BL5,"") -> 0 | BQ5: =D5+I5+N5 -> 21 | BR5: =E5+J5+O5 -> 0 | BS5: =BR5-BQ$5 -> -21 | BT5: =iferror(BR5/BQ5,"") -> 0 | BV5: =S5+X5+AC5 -> 32 | BW5: =T5+Y5+AD5 -> 0 | BX5: =BW5-BV$5 -> -32 | BY5: =iferror(BW5/BV5,"") -> 0 | CA5: =AH5+AM5+AR5 -> 43 | CB5: =AI5+AN5+AS5 -> 0 | CC5: =CB5-CA$5 -> -43 | CD5: =iferror(CB5/CA5,"") -> 0 | CF5: =BG5+BB5+AW5 -> 37 | CG5: =BH5+BC5+AX5 -> 0 | CH5: =CG5-CF$5 -> -37 | CI5: =iferror(CG5/CF5,"") -> 0
C6: % Demo to Customer | D6: ='Business Plan'!E5 -> 0.18 | E6: =iferror(E9/E5,"") | I6: ='Business Plan'!F5 -> 0.18 | J6: =iferror(J9/J5,"") | N6: ='Business Plan'!G5 -> 0.18 | O6: =iferror(O9/O5,"") | S6: ='Business Plan'!H5 -> 0.18 | T6: =iferror(T9/T5,"") | X6: ='Business Plan'!I5 -> 0.18 | Y6: =iferror(Y9/Y5,"") | AC6: ='Business Plan'!J5 -> 0.18 | AD6: =iferror(AD9/AD5,"") | AH6: ='Business Plan'!K5 -> 0.18 | AI6: =iferror(AI9/AI5,"") | AM6: ='Business Plan'!L5 -> 0.18 | AN6: =iferror(AN9/AN5,"") | AR6: ='Business Plan'!M5 -> 0.18 | AS6: =iferror(AS9/AS5,"") | AW6: ='Business Plan'!N5 -> 0.18 | AX6: =iferror(AX9/AX5,"") | BB6: ='Business Plan'!O5 -> 0.18 | BC6: =iferror(BC9/BC5,"") | BG6: ='Business Plan'!P5 -> 0.18 | BH6: =iferror(BH9/BH5,"") | BL6: ='Business Plan'!D5 | BM6: =iferror(BM9/BM5,"") | BQ6: =D6+I6+N6 -> 0.54 | BR6: =E6+J6+O6 -> 0 | BV6: =S6+X6+AC6 -> 0.54 | BW6: =T6+Y6+AD6 -> 0 | CA6: =AH6+AM6+AR6 -> 0.54 | CB6: =AI6+AN6+AS6 -> 0 | CF6: =BG6+BB6+AW6 -> 0.54 | CG6: =BH6+BC6+AX6 -> 0
C7: Demos # (agg) | D7: =D5 -> 5 | E7: =E5 -> 0 | I7: =D7+I5 -> 10 | J7: =E7+J5 -> 0 | N7: =I7+N5 -> 21 | O7: =J7+O5 -> 0 | S7: =N7+S5 -> 26 | T7: =O7+T5 -> 0 | X7: =S7+X5 -> 37 | Y7: =T7+Y5 -> 0 | AC7: =X7+AC5 -> 53 | AD7: =Y7+AD5 -> 0 | AH7: =AC7+AH5 -> 64 | AI7: =AD7+AI5 -> 0 | AM7: =AH7+AM5 -> 80 | AN7: =AI7+AN5 -> 0 | AR7: =AM7+AR5 -> 96 | AS7: =AN7+AS5 -> 0 | AW7: =AR7+AW5 -> 112 | AX7: =AS7+AX5 -> 0 | BB7: =AW7+BB5 -> 128 | BC7: =AX7+BC5 -> 0 | BG7: =BB7+BG5 -> 133 | BH7: =BC7+BH5 -> 0 | BQ7: =D7+I7+N7 -> 36 | BR7: =E7+J7+O7 -> 0 | BV7: =S7+X7+AC7 -> 116 | BW7: =T7+Y7+AD7 -> 0 | CA7: =AH7+AM7+AR7 -> 240 | CB7: =AI7+AN7+AS7 -> 0 | CF7: =BG7+BB7+AW7 -> 373 | CG7: =BH7+BC7+AX7 -> 0
C9: Won Customers # | D9: ='Business Plan'!E9 -> 1 | E9: =SUMIFS('DATA-IMP'!$Z$3:$Z43, 'DATA-IMP'!$D$3:$D43, ">=" & E$1, 'DATA-IMP'!$D$3:$D43, "<" & F$1) -> 0 | F9: =E9-D9 -> -1 | G9: =iferror(E9/D9,"") -> 0 | I9: ='Business Plan'!F9 -> 1 | J9: =SUMIFS('DATA-IMP'!$Z$3:$Z43, 'DATA-IMP'!$D$3:$D43, ">=" & J$1, 'DATA-IMP'!$D$3:$D43, "<" & K$1) -> 0 | K9: =J9-I$9 -> -1 | L9: =iferror(J9/I9,"") -> 0 | N9: ='Business Plan'!G9 -> 2 | O9: =SUMIFS('DATA-IMP'!$Z$3:$Z43, 'DATA-IMP'!$D$3:$D43, ">=" & O$1, 'DATA-IMP'!$D$3:$D43, "<" & P$1) -> 0 | P9: =O9-N$9 -> -2 | Q9: =iferror(O9/N9,"") -> 0 | S9: ='Business Plan'!H9 -> 1 | T9: =SUMIFS('DATA-IMP'!$Z$3:$Z43, 'DATA-IMP'!$D$3:$D43, ">=" & T$1, 'DATA-IMP'!$D$3:$D43, "<" & U$1) -> 0 | U9: =T9-S$9 -> -1 | V9: =iferror(T9/S9,"") -> 0 | X9: ='Business Plan'!I9 -> 2 | Y9: =SUMIFS('DATA-IMP'!$Z$3:$Z43, 'DATA-IMP'!$D$3:$D43, ">=" & Y$1, 'DATA-IMP'!$D$3:$D43, "<" & Z$1) -> 0 | Z9: =Y9-X$9 -> -2 | AA9: =iferror(Y9/X9,"") -> 0 | AC9: ='Business Plan'!J9 -> 3 | AD9: =SUMIFS('DATA-IMP'!$Z$3:$Z43, 'DATA-IMP'!$D$3:$D43, ">=" & AD$1, 'DATA-IMP'!$D$3:$D43, "<" & AE$1) -> 0 | AE9: =AD9-AC$9 -> -3 | AF9: =iferror(AD9/AC9,"") -> 0 | AH9: ='Business Plan'!K9 -> 2 | AI9: =SUMIFS('DATA-IMP'!$Z$3:$Z43, 'DATA-IMP'!$D$3:$D43, ">=" & AI$1, 'DATA-IMP'!$D$3:$D43, "<" & AJ$1) -> 0 | AJ9: =AI9-AH$9 -> -2 | AK9: =iferror(AI9/AH9,"") -> 0 | AM9: ='Business Plan'!L9 -> 3 | AN9: =SUMIFS('DATA-IMP'!$Z$3:$Z43, 'DATA-IMP'!$D$3:$D43, ">=" & AN$1, 'DATA-IMP'!$D$3:$D43, "<" & AO$1) -> 0 | AO9: =AN9-AM$9 -> -3 | AP9: =iferror(AN9/AM9,"") -> 0 | AR9: ='Business Plan'!M9 -> 3 | AS9: =SUMIFS('DATA-IMP'!$Z$3:$Z43, 'DATA-IMP'!$D$3:$D43, ">=" & AS$1, 'DATA-IMP'!$D$3:$D43, "<" & AT$1) -> 0 | AT9: =AS9-AR$9 -> -3 | AU9: =iferror(AS9/AR9,"") -> 0 | AW9: ='Business Plan'!N9 -> 3 | AX9: =SUMIFS('DATA-IMP'!$Z$3:$Z43, 'DATA-IMP'!$D$3:$D43, ">=" & AX$1, 'DATA-IMP'!$D$3:$D43, "<" & AY$1) -> 0 | AY9: =AX9-AW$9 -> -3 | AZ9: =iferror(AX9/AW9,"") -> 0 | BB9: ='Business Plan'!O9 -> 3 | BC9: =SUMIFS('DATA-IMP'!$Z$3:$Z43, 'DATA-IMP'!$D$3:$D43, ">=" & BC$1, 'DATA-IMP'!$D$3:$D43, "<" & BD$1) -> 0 | BD9: =BC9-BB$9 -> -3 | BE9: =iferror(BC9/BB9,"") -> 0 | BG9: ='Business Plan'!P9 -> 1 | BH9: =SUMIFS('DATA-IMP'!$Z$3:$Z43, 'DATA-IMP'!$D$3:$D43, ">=" & BH$1, 'DATA-IMP'!$D$3:$D43, "<" & BI$1) -> 0 | BI9: =BH9-BG$9 -> -1 | BJ9: =iferror(BH9/BG9,"") -> 0 | BL9: =SUM(BG9,BB9,AW9,AR9,AM9,AH9,AC9,X9,S9,N9,I9,D9,) -> 25 | BM9: =SUM(BH9,BC9,AX9,AS9,AN9,AI9,AD9,Y9,T9,O9,J9,E9,) -> 0 | BN9: =BM9-BL$9 -> -25 | BO9: =iferror(BM9/BL9,"") -> 0 | BQ9: =D9+I9+N9 -> 4 | BR9: =E9+J9+O9 -> 0 | BS9: =BR9-BQ$9 -> -4 | BT9: =iferror(BR9/BQ9,"") -> 0 | BV9: =S9+X9+AC9 -> 6 | BW9: =T9+Y9+AD9 -> 0 | BX9: =BW9-BV$9 -> -6 | BY9: =iferror(BW9/BV9,"") -> 0 | CA9: =AH9+AM9+AR9 -> 8 | CB9: =AI9+AN9+AS9 -> 0 | CC9: =CB9-CA$9 -> -8 | CD9: =iferror(CB9/CA9,"") -> 0 | CF9: =BG9+BB9+AW9 -> 7 | CG9: =BH9+BC9+AX9 -> 0 | CH9: =CG9-CF$9 -> -7 | CI9: =iferror(CG9/CF9,"") -> 0
C10: Won Customers # (agg) | D10: =D9 -> 1 | E10: =E9 -> 0 | I10: =I9+D10 -> 2 | J10: =J9+E10 -> 0 | N10: =N9+I10 -> 4 | O10: =O9+J10 -> 0 | S10: =S9+N10 -> 5 | T10: =T9+O10 -> 0 | X10: =X9+S10 -> 7 | Y10: =Y9+T10 -> 0 | AC10: =AC9+X10 -> 10 | AD10: =AD9+Y10 -> 0 | AH10: =AH9+AC10 -> 12 | AI10: =AI9+AD10 -> 0 | AM10: =AM9+AH10 -> 15 | AN10: =AN9+AI10 -> 0 | AR10: =AR9+AM10 -> 18 | AS10: =AS9+AN10 -> 0 | AW10: =AW9+AR10 -> 21 | AX10: =AX9+AS10 -> 0 | BB10: =BB9+AW10 -> 24 | BC10: =BC9+AX10 -> 0 | BG10: =BG9+BB10 -> 25 | BH10: =BH9+BC10 -> 0 | BQ10: =D10+I10+N10 -> 7 | BR10: =E10+J10+O10 -> 0 | BV10: =S10+X10+AC10 -> 22 | BW10: =T10+Y10+AD10 -> 0 | CA10: =AH10+AM10+AR10 -> 45 | CB10: =AI10+AN10+AS10 -> 0 | CF10: =BG10+BB10+AW10 -> 70 | CG10: =BH10+BC10+AX10 -> 0
CF11: =BG11+BB11+AW11 -> 0 | CG11: =BH11+BC11+AX11 -> 0
C12: Won MRR | D12: ='Business Plan'!E12 -> 1750 | E12: =SUMIFS('DATA-IMP'!$U$3:$U43, 'DATA-IMP'!$D$3:$D43, ">=" & E$1, 'DATA-IMP'!$D$3:$D43, "<" & F$1,'DATA-IMP'!$F$3:$F43,"Closed Won") -> 0 | F12: =E12-D12 -> -1750 | G12: =iferror(E12/D12,"") -> 0 | I12: ='Business Plan'!F12 -> 2100 | J12: =SUMIFS('DATA-IMP'!$U$3:$U43, 'DATA-IMP'!$D$3:$D43, ">=" & J$1, 'DATA-IMP'!$D$3:$D43, "<" & K$1,'DATA-IMP'!$F$3:$F43,"Closed Won") -> 0 | K12: =J12-I$12 -> -2100 | L12: =iferror(J12/I12,"") -> 0 | N12: ='Business Plan'!G12 -> 2450 | O12: =SUMIFS('DATA-IMP'!$U$3:$U43, 'DATA-IMP'!$D$3:$D43, ">=" & O$1, 'DATA-IMP'!$D$3:$D43, "<" & P$1,'DATA-IMP'!$F$3:$F43,"Closed Won") -> 0 | P12: =O12-N$12 -> -2450 | Q12: =iferror(O12/N12,"") -> 0 | S12: ='Business Plan'!H12 -> 2100 | T12: =SUMIFS('DATA-IMP'!$U$3:$U43, 'DATA-IMP'!$D$3:$D43, ">=" & T$1, 'DATA-IMP'!$D$3:$D43, "<" & U$1,'DATA-IMP'!$F$3:$F43,"Closed Won") -> 0 | U12: =T12-S$12 -> -2100 | V12: =iferror(T12/S12,"") -> 0 | X12: ='Business Plan'!I12 -> 2450 | Y12: =SUMIFS('DATA-IMP'!$U$3:$U43, 'DATA-IMP'!$D$3:$D43, ">=" & Y$1, 'DATA-IMP'!$D$3:$D43, "<" & Z$1,'DATA-IMP'!$F$3:$F43,"Closed Won") -> 0 | Z12: =Y12-X$12 -> -2450 | AA12: =iferror(Y12/X12,"") -> 0 | AC12: ='Business Plan'!J12 -> 4200 | AD12: =SUMIFS('DATA-IMP'!$U$3:$U43, 'DATA-IMP'!$D$3:$D43, ">=" & AD$1, 'DATA-IMP'!$D$3:$D43, "<" & AE$1,'DATA-IMP'!$F$3:$F43,"Closed Won") -> 0 | AE12: =AD12-AC$12 -> -4200 | AF12: =iferror(AD12/AC12,"") -> 0 | AH12: ='Business Plan'!K12 -> 2450 | AI12: =SUMIFS('DATA-IMP'!$U$3:$U43, 'DATA-IMP'!$D$3:$D43, ">=" & AI$1, 'DATA-IMP'!$D$3:$D43, "<" & AJ$1,'DATA-IMP'!$F$3:$F43,"Closed Won") -> 0 | AJ12: =AI12-AH$12 -> -2450 | AK12: =iferror(AI12/AH12,"") -> 0 | AM12: ='Business Plan'!L12 -> 2800 | AN12: =SUMIFS('DATA-IMP'!$U$3:$U43, 'DATA-IMP'!$D$3:$D43, ">=" & AN$1, 'DATA-IMP'!$D$3:$D43, "<" & AO$1,'DATA-IMP'!$F$3:$F43,"Closed Won") -> 0 | AO12: =AN12-AM$12 -> -2800 | AP12: =iferror(AN12/AM12,"") -> 0 | AR12: ='Business Plan'!M12 -> 3850 | AS12: =SUMIFS('DATA-IMP'!$U$3:$U43, 'DATA-IMP'!$D$3:$D43, ">=" & AS$1, 'DATA-IMP'!$D$3:$D43, "<" & AT$1,'DATA-IMP'!$F$3:$F43,"Closed Won") -> 0 | AT12: =AS12-AR$12 -> -3850 | AU12: =iferror(AS12/AR12,"") -> 0 | AW12: ='Business Plan'!N12 -> 4200 | AX12: =SUMIFS('DATA-IMP'!$U$3:$U43, 'DATA-IMP'!$D$3:$D43, ">=" & AX$1, 'DATA-IMP'!$D$3:$D43, "<" & AY$1,'DATA-IMP'!$F$3:$F43,"Closed Won") -> 0 | AY12: =AX12-AW$12 -> -4200 | AZ12: =iferror(AX12/AW12,"") -> 0 | BB12: ='Business Plan'!O12 -> 4550 | BC12: =SUMIFS('DATA-IMP'!$U$3:$U43, 'DATA-IMP'!$D$3:$D43, ">=" & BC$1, 'DATA-IMP'!$D$3:$D43, "<" & BD$1,'DATA-IMP'!$F$3:$F43,"Closed Won") -> 0 | BD12: =BC12-BB$12 -> -4550 | BE12: =iferror(BC12/BB12,"") -> 0 | BG12: ='Business Plan'!P12 -> 2100 | BH12: =SUMIFS('DATA-IMP'!$U$3:$U43, 'DATA-IMP'!$D$3:$D43, ">=" & BH$1, 'DATA-IMP'!$D$3:$D43, "<" & BI$1,'DATA-IMP'!$F$3:$F43,"Closed Won") -> 0 | BI12: =BH12-BG$12 -> -2100 | BJ12: =iferror(BH12/BG12,"") -> 0 | BL12: =SUM(BG12,BB12,AW12,AR12,AM12,AH12,AC12,X12,S12,N12,I12,D12,) -> 35000 | BM12: =SUM(BH12,BC12,AX12,AS12,AN12,AI12,AD12,Y12,T12,O12,J12,E12,) -> 0 | BN12: =BM12-BL$12 -> -35000 | BO12: =iferror(BM12/BL12,"") -> 0 | BQ12: =D12+I12+N12 -> 6300 | BR12: =E12+J12+O12 -> 0 | BS12: =BR12-BQ$12 -> -6300 | BT12: =iferror(BR12/BQ12,"") -> 0 | BV12: =S12+X12+AC12 -> 8750 | BW12: =T12+Y12+AD12 -> 0 | BX12: =BW12-BV$12 -> -8750 | BY12: =iferror(BW12/BV12,"") -> 0 | CA12: =AH12+AM12+AR12 -> 9100 | CB12: =AI12+AN12+AS12 -> 0 | CC12: =CB12-CA$12 -> -9100 | CD12: =iferror(CB12/CA12,"") -> 0 | CF12: =BG12+BB12+AW12 -> 10850 | CG12: =BH12+BC12+AX12 -> 0 | CH12: =CG12-CF$12 -> -10850 | CI12: =iferror(CG12/CF12,"") -> 0
C13: ARPU | D13: ='Business Plan'!E14 -> 1200 | E13: =iferror(E12/E9,"") | F13: =E13-D13 -> -1200 | G13: =iferror(E13/D13,"") -> 0 | I13: ='Business Plan'!F14 -> 1200 | J13: =iferror(J12/J9,"") | K13: =J13-I13 -> -1200 | L13: =iferror(J13/I13,"") -> 0 | N13: ='Business Plan'!G14 -> 1200 | O13: =iferror(O12/O9,"") | P13: =O13-N13 -> -1200 | Q13: =iferror(O13/N13,"") -> 0 | S13: ='Business Plan'!H14 -> 1200 | T13: =iferror(T12/T9,"") | U13: =T13-S13 -> -1200 | V13: =iferror(T13/S13,"") -> 0 | X13: ='Business Plan'!I14 -> 1200 | Y13: =iferror(Y12/Y9,"") | Z13: =Y13-X13 -> -1200 | AA13: =iferror(Y13/X13,"") -> 0 | AC13: ='Business Plan'!J14 -> 1200 | AD13: =iferror(AD12/AD9,"") | AE13: =AD13-AC13 -> -1200 | AF13: =iferror(AD13/AC13,"") -> 0 | AH13: ='Business Plan'!K14 -> 1200 | AI13: =iferror(AI12/AI9,"") | AJ13: =AI13-AH13 -> -1200 | AK13: =iferror(AI13/AH13,"") -> 0 | AM13: ='Business Plan'!L14 -> 1200 | AN13: =iferror(AN12/AN9,"") | AO13: =AN13-AM13 -> -1200 | AP13: =iferror(AN13/AM13,"") -> 0 | AR13: ='Business Plan'!M14 -> 1200 | AS13: =iferror(AS12/AS9,"") | AT13: =AS13-AR13 -> -1200 | AU13: =iferror(AS13/AR13,"") -> 0 | AW13: ='Business Plan'!N14 -> 1200 | AX13: =iferror(AX12/AX9,"") | AY13: =AX13-AW13 -> -1200 | AZ13: =iferror(AX13/AW13,"") -> 0 | BB13: ='Business Plan'!O14 -> 1200 | BC13: =iferror(BC12/BC9,"") | BD13: =BC13-BB13 -> -1200 | BE13: =iferror(BC13/BB13,"") -> 0 | BG13: ='Business Plan'!P14 -> 1200 | BH13: =iferror(BH12/BH9,"") | BI13: =BH13-BG13 -> -1200 | BJ13: =iferror(BH13/BG13,"") -> 0 | BL13: =SUM(BG13,BB13,AW13,AR13,AM13,AH13,AC13,X13,S13,N13,I13,D13,) -> 14400 | BM13: =SUM(BH13,BC13,AX13,AS13,AN13,AI13,AD13,Y13,T13,O13,J13,E13,) -> 0 | BN13: =BM13-BL13 -> -14400 | BO13: =iferror(BM13/BL13,"") -> 0 | BQ13: =D13+I13+N13 -> 3600 | BR13: =E13+J13+O13 -> 0 | BS13: =BR13-BQ13 -> -3600 | BT13: =iferror(BR13/BQ13,"") -> 0 | BV13: =S13+X13+AC13 -> 3600 | BW13: =T13+Y13+AD13 -> 0 | BX13: =BW13-BV13 -> -3600 | BY13: =iferror(BW13/BV13,"") -> 0 | CA13: =AH13+AM13+AR13 -> 3600 | CB13: =AI13+AN13+AS13 -> 0 | CC13: =CB13-CA13 -> -3600 | CD13: =iferror(CB13/CA13,"") -> 0 | CF13: =BG13+BB13+AW13 -> 3600 | CG13: =BH13+BC13+AX13 -> 0 | CH13: =CG13-CF13 -> -3600 | CI13: =iferror(CG13/CF13,"") -> 0
C14: Won ARR | D14: ='Business Plan'!E15 -> 21000 | E14: =IFERROR(E12*12,"") -> 0 | F14: =E14-D14 -> -21000 | G14: =iferror(E14/D14,"") -> 0 | I14: ='Business Plan'!F15 -> 25200 | J14: =IFERROR(J12*12,"") -> 0 | K14: =J14-I14 -> -25200 | L14: =iferror(J14/I14,"") -> 0 | N14: ='Business Plan'!G15 -> 29400 | O14: =IFERROR(O12*12,"") -> 0 | P14: =O14-N14 -> -29400 | Q14: =iferror(O14/N14,"") -> 0 | S14: ='Business Plan'!H15 -> 25200 | T14: =IFERROR(T12*12,"") -> 0 | U14: =T14-S14 -> -25200 | V14: =iferror(T14/S14,"") -> 0 | X14: ='Business Plan'!I15 -> 29400 | Y14: =IFERROR(Y12*12,"") -> 0 | Z14: =Y14-X14 -> -29400 | AA14: =iferror(Y14/X14,"") -> 0 | AC14: ='Business Plan'!J15 -> 50400 | AD14: =IFERROR(AD12*12,"") -> 0 | AE14: =AD14-AC14 -> -50400 | AF14: =iferror(AD14/AC14,"") -> 0 | AH14: ='Business Plan'!K15 -> 29400 | AI14: =IFERROR(AI12*12,"") -> 0 | AJ14: =AI14-AH14 -> -29400 | AK14: =iferror(AI14/AH14,"") -> 0 | AM14: ='Business Plan'!L15 -> 33600 | AN14: =IFERROR(AN12*12,"") -> 0 | AO14: =AN14-AM14 -> -33600 | AP14: =iferror(AN14/AM14,"") -> 0 | AR14: ='Business Plan'!M15 -> 46200 | AS14: =IFERROR(AS12*12,"") -> 0 | AT14: =AS14-AR14 -> -46200 | AU14: =iferror(AS14/AR14,"") -> 0 | AW14: ='Business Plan'!N15 -> 50400 | AX14: =IFERROR(AX12*12,"") -> 0 | AY14: =AX14-AW14 -> -50400 | AZ14: =iferror(AX14/AW14,"") -> 0 | BB14: ='Business Plan'!O15 -> 54600 | BC14: =IFERROR(BC12*12,"") -> 0 | BD14: =BC14-BB14 -> -54600 | BE14: =iferror(BC14/BB14,"") -> 0 | BG14: ='Business Plan'!P15 -> 25200 | BH14: =IFERROR(BH12*12,"") -> 0 | BI14: =BH14-BG14 -> -25200 | BJ14: =iferror(BH14/BG14,"") -> 0 | BL14: =SUM(BG14,BB14,AW14,AR14,AM14,AH14,AC14,X14,S14,N14,I14,D14,) -> 420000 | BM14: =SUM(BH14,BC14,AX14,AS14,AN14,AI14,AD14,Y14,T14,O14,J14,E14,) -> 0 | BN14: =BM14-BL14 -> -420000 | BO14: =iferror(BM14/BL14,"") -> 0 | BQ14: =D14+I14+N14 -> 75600 | BR14: =E14+J14+O14 -> 0 | BS14: =BR14-BQ14 -> -75600 | BT14: =iferror(BR14/BQ14,"") -> 0 | BV14: =S14+X14+AC14 -> 105000 | BW14: =T14+Y14+AD14 -> 0 | BX14: =BW14-BV14 -> -105000 | BY14: =iferror(BW14/BV14,"") -> 0 | CA14: =AH14+AM14+AR14 -> 109200 | CB14: =AI14+AN14+AS14 -> 0 | CC14: =CB14-CA14 -> -109200 | CD14: =iferror(CB14/CA14,"") -> 0 | CF14: =BG14+BB14+AW14 -> 130200 | CG14: =BH14+BC14+AX14 -> 0 | CH14: =CG14-CF14 -> -130200 | CI14: =iferror(CG14/CF14,"") -> 0
C15: Won ARR (agg) | D15: ='Business Plan'!E16 -> 21000 | E15: =E14 -> 0 | F15: =E15-D15 -> -21000 | G15: =iferror(E15/D15,"") -> 0 | I15: ='Business Plan'!F16 -> 46200 | J15: =sum(E15,J14) -> 0 | K15: =J15-I$15 -> -46200 | L15: =iferror(J15/I15,"") -> 0 | N15: ='Business Plan'!G16 -> 75600 | O15: =sum(J15,O14) -> 0 | P15: =O15-N$15 -> -75600 | Q15: =iferror(O15/N15,"") -> 0 | S15: ='Business Plan'!H16 -> 100800 | T15: =sum(O15,T14) -> 0 | U15: =T15-S$15 -> -100800 | V15: =iferror(T15/S15,"") -> 0 | X15: ='Business Plan'!I16 -> 130200 | Y15: =sum(T15,Y14) -> 0 | Z15: =Y15-X$15 -> -130200 | AA15: =iferror(Y15/X15,"") -> 0 | AC15: ='Business Plan'!J16 -> 180600 | AD15: =sum(Y15,AD14) -> 0 | AE15: =AD15-AC$15 -> -180600 | AF15: =iferror(AD15/AC15,"") -> 0 | AH15: ='Business Plan'!K16 -> 210000 | AI15: =sum(AD15,AI14) -> 0 | AJ15: =AI15-AH$15 -> -210000 | AK15: =iferror(AI15/AH15,"") -> 0 | AM15: ='Business Plan'!L16 -> 243600 | AN15: =sum(AI15,AN14) -> 0 | AO15: =AN15-AM$15 -> -243600 | AP15: =iferror(AN15/AM15,"") -> 0 | AR15: ='Business Plan'!M16 -> 289800 | AS15: =sum(AN15,AS14) -> 0 | AT15: =AS15-AR$15 -> -289800 | AU15: =iferror(AS15/AR15,"") -> 0 | AW15: ='Business Plan'!N16 -> 340200 | AX15: =sum(AS15,AX14) -> 0 | AY15: =AX15-AW$15 -> -340200 | AZ15: =iferror(AX15/AW15,"") -> 0 | BB15: ='Business Plan'!O16 -> 394800 | BC15: =sum(AX15,BC14) -> 0 | BD15: =BC15-BB$15 -> -394800 | BE15: =iferror(BC15/BB15,"") -> 0 | BG15: ='Business Plan'!P16 -> 420000 | BH15: =sum(BC15,BH14) -> 0 | BI15: =BH15-BG$15 -> -420000 | BJ15: =iferror(BH15/BG15,"") -> 0 | BL15: =SUM(BG15,BB15,AW15,AR15,AM15,AH15,AC15,X15,S15,N15,I15,D15,) -> 2452800 | BM15: =SUM(BH15,BC15,AX15,AS15,AN15,AI15,AD15,Y15,T15,O15,J15,E15,) -> 0 | BN15: =BM15-BL$15 -> -2452800 | BO15: =iferror(BM15/BL15,"") -> 0 | BQ15: =D15+I15+N15 -> 142800 | BR15: =E15+J15+O15 -> 0 | BS15: =BR15-BQ$15 -> -142800 | BT15: =iferror(BR15/BQ15,"") -> 0 | BV15: =S15+X15+AC15 -> 411600 | BW15: =T15+Y15+AD15 -> 0 | BX15: =BW15-BV$15 -> -411600 | BY15: =iferror(BW15/BV15,"") -> 0 | CA15: =AH15+AM15+AR15 -> 743400 | CB15: =AI15+AN15+AS15 -> 0 | CC15: =CB15-CA$15 -> -743400 | CD15: =iferror(CB15/CA15,"") -> 0 | CF15: =BG15+BB15+AW15 -> 1155000 | CG15: =BH15+BC15+AX15 -> 0 | CH15: =CG15-CF$15 -> -1155000 | CI15: =iferror(CG15/CF15,"") -> 0
C17: Commissions Total | D17: ='Business Plan'!E18 -> 8100 | E17: =SUM(E18:E21) -> 0 | F17: =E17-D17 -> -8100 | G17: =iferror(E17/D17,"") -> 0 | I17: ='Business Plan'!F18 -> 9570 | J17: =SUM(J18:J21) -> 0 | K17: =J17-I$17 -> -9570 | L17: =iferror(J17/I17,"") -> 0 | N17: ='Business Plan'!G18 -> 28990 | O17: =SUM(O18:O21) -> 0 | P17: =O17-N$17 -> -28990 | Q17: =iferror(O17/N17,"") -> 0 | S17: ='Business Plan'!H18 -> 10320 | T17: =SUM(T18:T21) -> 0 | U17: =T17-S$17 -> -10320 | V17: =iferror(T17/S17,"") -> 0 | X17: ='Business Plan'!I18 -> 13290 | Y17: =SUM(Y18:Y21) -> 0 | Z17: =Y17-X$17 -> -13290 | AA17: =iferror(Y17/X17,"") -> 0 | AC17: ='Business Plan'!J18 -> 35690 | AD17: =SUM(AD18:AD21) -> 0 | AE17: =AD17-AC$17 -> -35690 | AF17: =iferror(AD17/AC17,"") -> 0 | AH17: ='Business Plan'!K18 -> 16290 | AI17: =SUM(AI18:AI21) -> 0 | AJ17: =AI17-AH$17 -> -16290 | AK17: =iferror(AI17/AH17,"") -> 0 | AM17: ='Business Plan'!L18 -> 20760 | AN17: =SUM(AN18:AN21) -> 0 | AO17: =AN17-AM$17 -> -20760 | AP17: =iferror(AN17/AM17,"") -> 0 | AR17: ='Business Plan'!M18 -> 39220 | AS17: =SUM(AS18:AS21) -> 0 | AT17: =AS17-AR$17 -> -39220 | AU17: =iferror(AS17/AR17,"") -> 0 | AW17: ='Business Plan'!N18 -> 26640 | AX17: =SUM(AX18:AX21) -> 0 | AY17: =AX17-AW$17 -> -26640 | AZ17: =iferror(AX17/AW17,"") -> 0 | BB17: ='Business Plan'!O18 -> 28110 | BC17: =SUM(BC18:BC21) -> 0 | BD17: =BC17-BB$17 -> -28110 | BE17: =iferror(BC17/BB17,"") -> 0 | BG17: ='Business Plan'!P18 -> 26370 | BH17: =SUM(BH18:BH21) -> 0 | BI17: =BH17-BG$17 -> -26370 | BJ17: =iferror(BH17/BG17,"") -> 0 | BL17: =SUM(BG17,BB17,AW17,AR17,AM17,AH17,AC17,X17,S17,N17,I17,D17,) -> 263350 | BM17: =SUM(BH17,BC17,AX17,AS17,AN17,AI17,AD17,Y17,T17,O17,J17,E17,) -> 0 | BN17: =BM17-BL$17 -> -263350 | BO17: =iferror(BM17/BL17,"") -> 0 | BQ17: =D17+I17+N17 -> 46660 | BR17: =E17+J17+O17 -> 0 | BS17: =BR17-BQ$17 -> -46660 | BT17: =iferror(BR17/BQ17,"") -> 0 | BV17: =S17+X17+AC17 -> 59300 | BW17: =T17+Y17+AD17 -> 0 | BX17: =BW17-BV$17 -> -59300 | BY17: =iferror(BW17/BV17,"") -> 0 | CA17: =AH17+AM17+AR17 -> 76270 | CB17: =AI17+AN17+AS17 -> 0 | CC17: =CB17-CA$17 -> -76270 | CD17: =iferror(CB17/CA17,"") -> 0 | CF17: =BG17+BB17+AW17 -> 81120 | CG17: =BH17+BC17+AX17 -> 0 | CH17: =CG17-CF$17 -> -81120 | CI17: =iferror(CG17/CF17,"") -> 0
C18: Commissions - Sales | D18: ='Business Plan'!E19 -> 7350 | E18: =E14*'Partnership Info'!$D$11 -> 0 | F18: =E18-D18 -> -7350 | G18: =iferror(E18/D18,"") -> 0 | I18: ='Business Plan'!F19 -> 8820 | K18: =J18-I$18 -> -8820 | L18: =iferror(J18/I18,"") -> 0 | N18: ='Business Plan'!G19 -> 10290 | P18: =O18-N$18 -> -10290 | Q18: =iferror(O18/N18,"") -> 0 | S18: ='Business Plan'!H19 -> 8820 | U18: =T18-S$18 -> -8820 | V18: =iferror(T18/S18,"") -> 0 | X18: ='Business Plan'!I19 -> 10290 | Z18: =Y18-X$18 -> -10290 | AA18: =iferror(Y18/X18,"") -> 0 | AC18: ='Business Plan'!J19 -> 17640 | AE18: =AD18-AC$18 -> -17640 | AF18: =iferror(AD18/AC18,"") -> 0 | AH18: ='Business Plan'!K19 -> 10290 | AJ18: =AI18-AH$18 -> -10290 | AK18: =iferror(AI18/AH18,"") -> 0 | AM18: ='Business Plan'!L19 -> 11760 | AO18: =AN18-AM$18 -> -11760 | AP18: =iferror(AN18/AM18,"") -> 0 | AR18: ='Business Plan'!M19 -> 16170 | AT18: =AS18-AR$18 -> -16170 | AU18: =iferror(AS18/AR18,"") -> 0 | AW18: ='Business Plan'!N19 -> 17640 | AY18: =AX18-AW$18 -> -17640 | AZ18: =iferror(AX18/AW18,"") -> 0 | BB18: ='Business Plan'!O19 -> 19110 | BD18: =BC18-BB$18 -> -19110 | BE18: =iferror(BC18/BB18,"") -> 0 | BG18: ='Business Plan'!P19 -> 8820 | BI18: =BH18-BG$18 -> -8820 | BJ18: =iferror(BH18/BG18,"") -> 0 | BL18: =SUM(BG18,BB18,AW18,AR18,AM18,AH18,AC18,X18,S18,N18,I18,D18,) -> 147000 | BM18: =SUM(BH18,BC18,AX18,AS18,AN18,AI18,AD18,Y18,T18,O18,J18,E18,) -> 0 | BN18: =BM18-BL$18 -> -147000 | BO18: =iferror(BM18/BL18,"") -> 0 | BQ18: =D18+I18+N18 -> 26460 | BR18: =E18+J18+O18 -> 0 | BS18: =BR18-BQ$18 -> -26460 | BT18: =iferror(BR18/BQ18,"") -> 0 | BV18: =S18+X18+AC18 -> 36750 | BW18: =T18+Y18+AD18 -> 0 | BX18: =BW18-BV$18 -> -36750 | BY18: =iferror(BW18/BV18,"") -> 0 | CA18: =AH18+AM18+AR18 -> 38220 | CB18: =AI18+AN18+AS18 -> 0 | CC18: =CB18-CA$18 -> -38220 | CD18: =iferror(CB18/CA18,"") -> 0 | CF18: =BG18+BB18+AW18 -> 45570 | CG18: =BH18+BC18+AX18 -> 0 | CH18: =CG18-CF$18 -> -45570 | CI18: =iferror(CG18/CF18,"") -> 0
C19: Own Integrations | D19: ='Business Plan'!E21 -> 0 | I19: ='Business Plan'!F21 -> 0 | N19: ='Business Plan'!G21 -> 0 | S19: ='Business Plan'!H21 -> 0 | X19: ='Business Plan'!I21 -> 0 | AC19: ='Business Plan'!J21 -> 0 | AH19: ='Business Plan'!K21 -> 0 | AM19: ='Business Plan'!L21 -> 0 | AR19: ='Business Plan'!M21 -> 0 | AW19: ='Business Plan'!N21 -> 0 | BB19: ='Business Plan'!O21 -> 0 | BG19: ='Business Plan'!P21 -> 0 | BL19: =SUM(BG19,BB19,AW19,AR19,AM19,AH19,AC19,X19,S19,N19,I19,D19,) -> 0 | BM19: =SUM(BH19,BC19,AX19,AS19,AN19,AI19,AD19,Y19,T19,O19,J19,E19,) -> 0 | BQ19: =D19+I19+N19 -> 0 | BR19: =E19+J19+O19 -> 0 | BV19: =S19+X19+AC19 -> 0 | BW19: =T19+Y19+AD19 -> 0 | CA19: =AH19+AM19+AR19 -> 0 | CB19: =AI19+AN19+AS19 -> 0 | CF19: =BG19+BB19+AW19 -> 0 | CG19: =BH19+BC19+AX19 -> 0
C20: Onboardings | D20: ='Business Plan'!E22 -> 750 | F20: =E20-D20 -> -750 | G20: =iferror(E20/D20,"") -> 0 | I20: ='Business Plan'!F22 -> 750 | K20: =J20-I$20 -> -750 | L20: =iferror(J20/I20,"") -> 0 | N20: ='Business Plan'!G22 -> 1500 | P20: =O20-N$20 -> -1500 | Q20: =iferror(O20/N20,"") -> 0 | S20: ='Business Plan'!H22 -> 1500 | U20: =T20-S$20 -> -1500 | V20: =iferror(T20/S20,"") -> 0 | X20: ='Business Plan'!I22 -> 3000 | Z20: =Y20-X$20 -> -3000 | AA20: =iferror(Y20/X20,"") -> 0 | AC20: ='Business Plan'!J22 -> 4500 | AE20: =AD20-AC$20 -> -4500 | AF20: =iferror(AD20/AC20,"") -> 0 | AH20: ='Business Plan'!K22 -> 6000 | AJ20: =AI20-AH$20 -> -6000 | AK20: =iferror(AI20/AH20,"") -> 0 | AM20: ='Business Plan'!L22 -> 9000 | AO20: =AN20-AM$20 -> -9000 | AP20: =iferror(AN20/AM20,"") -> 0 | AR20: ='Business Plan'!M22 -> 9000 | AT20: =AS20-AR$20 -> -9000 | AU20: =iferror(AS20/AR20,"") -> 0 | AW20: ='Business Plan'!N22 -> 9000 | AY20: =AX20-AW$20 -> -9000 | AZ20: =iferror(AX20/AW20,"") -> 0 | BB20: ='Business Plan'!O22 -> 9000 | BD20: =BC20-BB$20 -> -9000 | BE20: =iferror(BC20/BB20,"") -> 0 | BG20: ='Business Plan'!P22 -> 3000 | BI20: =BH20-BG$20 -> -3000 | BJ20: =iferror(BH20/BG20,"") -> 0 | BL20: =SUM(BG20,BB20,AW20,AR20,AM20,AH20,AC20,X20,S20,N20,I20,D20,) -> 57000 | BM20: =SUM(BH20,BC20,AX20,AS20,AN20,AI20,AD20,Y20,T20,O20,J20,E20,) -> 0 | BN20: =BM20-BL$20 -> -57000 | BO20: =iferror(BM20/BL20,"") -> 0 | BQ20: =D20+I20+N20 -> 3000 | BR20: =E20+J20+O20 -> 0 | BS20: =BR20-BQ$20 -> -3000 | BT20: =iferror(BR20/BQ20,"") -> 0 | BV20: =S20+X20+AC20 -> 9000 | BW20: =T20+Y20+AD20 -> 0 | BX20: =BW20-BV$20 -> -9000 | BY20: =iferror(BW20/BV20,"") -> 0 | CA20: =AH20+AM20+AR20 -> 24000 | CB20: =AI20+AN20+AS20 -> 0 | CC20: =CB20-CA$20 -> -24000 | CD20: =iferror(CB20/CA20,"") -> 0 | CF20: =BG20+BB20+AW20 -> 21000 | CG20: =BH20+BC20+AX20 -> 0 | CH20: =CG20-CF$20 -> -21000 | CI20: =iferror(CG20/CF20,"") -> 0
C21: Bonus & Incentives | D21: ='Business Plan'!E20 -> 0 | E21: =SUMIF('B&I'!$L$3:$L43,D3,'B&I'!$K$3:$K43) -> 0 | F21: =E21-D21 -> 0 | G21: =iferror(E21/D21,"") | I21: ='Business Plan'!F20 -> 0 | J21: =SUMIF('B&I'!$L$3:$L43,I3,'B&I'!$K$3:$K43) -> 0 | K21: =J21-I$21 -> 0 | L21: =iferror(J21/I21,"") | N21: ='Business Plan'!G20 -> 17200 | O21: =SUMIF('B&I'!$L$3:$L43,N3,'B&I'!$K$3:$K43) -> 0 | P21: =O21-N$21 -> -17200 | Q21: =iferror(O21/N21,"") -> 0 | S21: ='Business Plan'!H20 -> 0 | T21: =SUMIF('B&I'!$L$3:$L43,S3,'B&I'!$K$3:$K43) -> 0 | U21: =T21-S$21 -> 0 | V21: =iferror(T21/S21,"") | X21: ='Business Plan'!I20 -> 0 | Y21: =SUMIF('B&I'!$L$3:$L43,X3,'B&I'!$K$3:$K43) -> 0 | Z21: =Y21-X$21 -> 0 | AA21: =iferror(Y21/X21,"") | AC21: ='Business Plan'!J20 -> 13550 | AD21: =SUMIF('B&I'!$L$3:$L43,AC3,'B&I'!$K$3:$K43) -> 0 | AE21: =AD21-AC$21 -> -13550 | AF21: =iferror(AD21/AC21,"") -> 0 | AH21: ='Business Plan'!K20 -> 0 | AI21: =SUMIF('B&I'!$L$3:$L43,AH3,'B&I'!$K$3:$K43) -> 0 | AJ21: =AI21-AH$21 -> 0 | AK21: =iferror(AI21/AH21,"") | AM21: ='Business Plan'!L20 -> 0 | AN21: =SUMIF('B&I'!$L$3:$L43,AM3,'B&I'!$K$3:$K43) -> 0 | AO21: =AN21-AM$21 -> 0 | AP21: =iferror(AN21/AM21,"") | AR21: ='Business Plan'!M20 -> 14050 | AS21: =SUMIF('B&I'!$L$3:$L43,AR3,'B&I'!$K$3:$K43) -> 0 | AT21: =AS21-AR$21 -> -14050 | AU21: =iferror(AS21/AR21,"") -> 0 | AW21: ='Business Plan'!N20 -> 0 | AX21: =SUMIF('B&I'!$L$3:$L43,AW3,'B&I'!$K$3:$K43) -> 0 | AY21: =AX21-AW$21 -> 0 | AZ21: =iferror(AX21/AW21,"") | BB21: ='Business Plan'!O20 -> 0 | BC21: =SUMIF('B&I'!$L$3:$L43,BB3,'B&I'!$K$3:$K43) -> 0 | BD21: =BC21-BB$21 -> 0 | BE21: =iferror(BC21/BB21,"") | BG21: ='Business Plan'!P20 -> 14550 | BH21: =SUMIF('B&I'!$L$3:$L43,BG3,'B&I'!$K$3:$K43) -> 0 | BI21: =BH21-BG$21 -> -14550 | BJ21: =iferror(BH21/BG21,"") -> 0 | BL21: =SUM(BG21,BB21,AW21,AR21,AM21,AH21,AC21,X21,S21,N21,I21,D21,) -> 59350 | BM21: =SUM(BH21,BC21,AX21,AS21,AN21,AI21,AD21,Y21,T21,O21,J21,E21,) -> 0 | BN21: =BM21-BL$21 -> -59350 | BO21: =iferror(BM21/BL21,"") -> 0 | BQ21: =D21+I21+N21 -> 17200 | BR21: =E21+J21+O21 -> 0 | BS21: =BR21-BQ$21 -> -17200 | BT21: =iferror(BR21/BQ21,"") -> 0 | BV21: =S21+X21+AC21 -> 13550 | BW21: =T21+Y21+AD21 -> 0 | BX21: =BW21-BV$21 -> -13550 | BY21: =iferror(BW21/BV21,"") -> 0 | CA21: =AH21+AM21+AR21 -> 14050 | CB21: =AI21+AN21+AS21 -> 0 | CC21: =CB21-CA$21 -> -14050 | CD21: =iferror(CB21/CA21,"") -> 0 | CF21: =BG21+BB21+AW21 -> 14550 | CG21: =BH21+BC21+AX21 -> 0 | CH21: =CG21-CF$21 -> -14550 | CI21: =iferror(CG21/CF21,"") -> 0
C22: Commissions Total (agg) | D22: ='Business Plan'!E24 -> 8100 | E22: =SUM(E18:E21) -> 0 | F22: =E22-D22 -> -8100 | G22: =iferror(E22/D22,"") -> 0 | I22: ='Business Plan'!F24 -> 17670 | J22: =E22+SUM(J18:J21) -> 0 | K22: =J22-I$22 -> -17670 | L22: =iferror(J22/I22,"") -> 0 | N22: ='Business Plan'!G24 -> 46660 | O22: =J22+SUM(O18:O21) -> 0 | P22: =O22-N$22 -> -46660 | Q22: =iferror(O22/N22,"") -> 0 | S22: ='Business Plan'!H24 -> 56980 | T22: =O22+SUM(T18:T21) -> 0 | U22: =T22-S$22 -> -56980 | V22: =iferror(T22/S22,"") -> 0 | X22: ='Business Plan'!I24 -> 70270 | Y22: =T22+SUM(Y18:Y21) -> 0 | Z22: =Y22-X$22 -> -70270 | AA22: =iferror(Y22/X22,"") -> 0 | AC22: ='Business Plan'!J24 -> 105960 | AD22: =Y22+SUM(AD18:AD21) -> 0 | AE22: =AD22-AC$22 -> -105960 | AF22: =iferror(AD22/AC22,"") -> 0 | AH22: ='Business Plan'!K24 -> 122250 | AI22: =AD22+SUM(AI18:AI21) -> 0 | AJ22: =AI22-AH$22 -> -122250 | AK22: =iferror(AI22/AH22,"") -> 0 | AM22: ='Business Plan'!L24 -> 143010 | AN22: =AI22+SUM(AN18:AN21) -> 0 | AO22: =AN22-AM$22 -> -143010 | AP22: =iferror(AN22/AM22,"") -> 0 | AR22: ='Business Plan'!M24 -> 182230 | AS22: =AN22+SUM(AS18:AS21) -> 0 | AT22: =AS22-AR$22 -> -182230 | AU22: =iferror(AS22/AR22,"") -> 0 | AW22: ='Business Plan'!N24 -> 208870 | AX22: =AS22+SUM(AX18:AX21) -> 0 | AY22: =AX22-AW$22 -> -208870 | AZ22: =iferror(AX22/AW22,"") -> 0 | BB22: ='Business Plan'!O24 -> 236980 | BC22: =AX22+SUM(BC18:BC21) -> 0 | BD22: =BC22-BB$22 -> -236980 | BE22: =iferror(BC22/BB22,"") -> 0 | BG22: ='Business Plan'!P24 -> 263350 | BH22: =BC22+SUM(BH18:BH21) -> 0 | BI22: =BH22-BG$22 -> -263350 | BJ22: =iferror(BH22/BG22,"") -> 0 | BL22: =BG22 -> 263350 | BM22: =BH22 -> 0 | BN22: =BM22-BL$22 -> -263350 | BO22: =iferror(BM22/BL22,"") -> 0 | BQ22: =N22 -> 46660 | BR22: =O22 -> 0 | BS22: =BR22-BQ$22 -> -46660 | BT22: =iferror(BR22/BQ22,"") -> 0 | BV22: =AC22 -> 105960 | BW22: =AD22 -> 0 | BX22: =BW22-BV$22 -> -105960 | BY22: =iferror(BW22/BV22,"") -> 0 | CA22: =AR22 -> 182230 | CB22: =AS22 -> 0 | CC22: =CB22-CA$22 -> -182230 | CD22: =iferror(CB22/CA22,"") -> 0 | CF22: =BG22 -> 263350 | CG22: =BH22 -> 0 | CH22: =CG22-CF$22 -> -263350 | CI22: =iferror(CG22/CF22,"") -> 0
C24: Demand Generation Plan | G24: =iferror(E24/D24,"") | L24: =iferror(J24/I24,"") | Q24: =iferror(O24/N24,"") | V24: =iferror(T24/S24,"") | AA24: =iferror(Y24/X24,"") | AF24: =iferror(AD24/AC24,"") | AK24: =iferror(AI24/AH24,"") | AP24: =iferror(AN24/AM24,"") | AU24: =iferror(AS24/AR24,"") | AZ24: =iferror(AX24/AW24,"") | BE24: =iferror(BC24/BB24,"") | BJ24: =iferror(BH24/BG24,"") | BO24: =iferror(BM24/BL24,"") | BQ24: =D24+I24+N24 -> 0 | BR24: =E24+J24+O24 -> 0 | BT24: =iferror(BR24/BQ24,"") | BV24: =S24+X24+AC24 -> 0 | BW24: =T24+Y24+AD24 -> 0 | BY24: =iferror(BW24/BV24,"") | CA24: =AH24+AM24+AR24 -> 0 | CB24: =AI24+AN24+AS24 -> 0 | CD24: =iferror(CB24/CA24,"") | CF24: =BG24+BB24+AW24 -> 0 | CG24: =BH24+BC24+AX24 -> 0 | CI24: =iferror(CG24/CF24,"")
C25: Actions # | D25: ='Business Plan'!E33 -> 3 | E25: =COUNTIFS('Demand Generation Plan'!$P$4:$P43,">0",'Demand Generation Plan'!$D$4:$D43,D3) -> 0 | F25: =E25-D25 -> -3 | G25: =iferror(E25/D25,"") -> 0 | I25: ='Business Plan'!F33 -> 3 | J25: =COUNTIFS('Demand Generation Plan'!$P$4:$P43,">0",'Demand Generation Plan'!$D$4:$D43,I3) -> 0 | K25: =J25-I25 -> -3 | L25: =iferror(J25/I25,"") -> 0 | N25: ='Business Plan'!G33 -> 2 | O25: =COUNTIFS('Demand Generation Plan'!$P$4:$P43,">0",'Demand Generation Plan'!$D$4:$D43,N3) -> 0 | P25: =O25-N25 -> -2 | Q25: =iferror(O25/N25,"") -> 0 | S25: ='Business Plan'!H33 -> 3 | T25: =COUNTIFS('Demand Generation Plan'!$P$4:$P43,">0",'Demand Generation Plan'!$D$4:$D43,S3) -> 0 | U25: =T25-S25 -> -3 | V25: =iferror(T25/S25,"") -> 0 | X25: ='Business Plan'!I33 -> 3 | Y25: =COUNTIFS('Demand Generation Plan'!$P$4:$P43,">0",'Demand Generation Plan'!$D$4:$D43,X3) -> 0 | Z25: =Y25-X25 -> -3 | AA25: =iferror(Y25/X25,"") -> 0 | AC25: ='Business Plan'!J33 -> 2 | AD25: =COUNTIFS('Demand Generation Plan'!$P$4:$P43,">0",'Demand Generation Plan'!$D$4:$D43,AC3) -> 0 | AE25: =AD25-AC25 -> -2 | AF25: =iferror(AD25/AC25,"") -> 0 | AH25: ='Business Plan'!K33 -> 4 | AI25: =COUNTIFS('Demand Generation Plan'!$P$4:$P43,">0",'Demand Generation Plan'!$D$4:$D43,AH3) -> 0 | AJ25: =AI25-AH25 -> -4 | AK25: =iferror(AI25/AH25,"") -> 0 | AM25: ='Business Plan'!L33 -> 2 | AN25: =COUNTIFS('Demand Generation Plan'!$P$4:$P43,">0",'Demand Generation Plan'!$D$4:$D43,AM3) -> 0 | AO25: =AN25-AM25 -> -2 | AP25: =iferror(AN25/AM25,"") -> 0 | AR25: ='Business Plan'!M33 -> 2 | AS25: =COUNTIFS('Demand Generation Plan'!$P$4:$P43,">0",'Demand Generation Plan'!$D$4:$D43,AR3) -> 0 | AT25: =AS25-AR25 -> -2 | AU25: =iferror(AS25/AR25,"") -> 0 | AW25: ='Business Plan'!N33 -> 4 | AX25: =COUNTIFS('Demand Generation Plan'!$P$4:$P43,">0",'Demand Generation Plan'!$D$4:$D43,AW3) -> 0 | AY25: =AX25-AW25 -> -4 | AZ25: =iferror(AX25/AW25,"") -> 0 | BB25: ='Business Plan'!O33 -> 2 | BC25: =COUNTIFS('Demand Generation Plan'!$P$4:$P43,">0",'Demand Generation Plan'!$D$4:$D43,BB3) -> 0 | BD25: =BC25-BB25 -> -2 | BE25: =iferror(BC25/BB25,"") -> 0 | BG25: ='Business Plan'!P33 -> 2 | BH25: =COUNTIFS('Demand Generation Plan'!$P$4:$P43,">0",'Demand Generation Plan'!$D$4:$D43,BG3) -> 0 | BI25: =BH25-BG25 -> -2 | BJ25: =iferror(BH25/BG25,"") -> 0 | BL25: =SUM(BG25,BB25,AW25,AR25,AM25,AH25,AC25,X25,S25,N25,I25,D25,) -> 32 | BM25: =SUM(BH25,BC25,AX25,AS25,AN25,AI25,AD25,Y25,T25,O25,J25,E25,) -> 0 | BN25: =BM25-BL25 -> -32 | BO25: =iferror(BM25/BL25,"") -> 0 | BQ25: =D25+I25+N25 -> 8 | BR25: =E25+J25+O25 -> 0 | BS25: =BR25-BQ25 -> -8 | BT25: =iferror(BR25/BQ25,"") -> 0 | BV25: =S25+X25+AC25 -> 8 | BW25: =T25+Y25+AD25 -> 0 | BX25: =BW25-BV25 -> -8 | BY25: =iferror(BW25/BV25,"") -> 0 | CA25: =AH25+AM25+AR25 -> 8 | CB25: =AI25+AN25+AS25 -> 0 | CC25: =CB25-CA25 -> -8 | CD25: =iferror(CB25/CA25,"") -> 0 | CF25: =BG25+BB25+AW25 -> 8 | CG25: =BH25+BC25+AX25 -> 0 | CH25: =CG25-CF25 -> -8 | CI25: =iferror(CG25/CF25,"") -> 0
C26: Budget | D26: ='Business Plan'!E34 -> -1700 | E26: =-SUMIF('Demand Generation Plan'!$D$4:$D43,D3,'Demand Generation Plan'!$R$4:$R43) -> 0 | F26: =E26-D26 -> 1700 | G26: =iferror(E26/D26,"") -> 0 | I26: ='Business Plan'!F34 -> -11000 | J26: =SUMIF('Demand Generation Plan'!$D$4:$D43,I3,'Demand Generation Plan'!$R$4:$R43) -> 0 | K26: =J26-I26 -> 11000 | L26: =iferror(J26/I26,"") -> 0 | N26: ='Business Plan'!G34 -> -1200 | O26: =SUMIF('Demand Generation Plan'!$D$4:$D43,N3,'Demand Generation Plan'!$R$4:$R43) -> 0 | P26: =O26-N26 -> 1200 | Q26: =iferror(O26/N26,"") -> 0 | S26: ='Business Plan'!H34 -> -1700 | T26: =SUMIF('Demand Generation Plan'!$D$4:$D43,S3,'Demand Generation Plan'!$R$4:$R43) -> 0 | U26: =T26-S26 -> 1700 | V26: =iferror(T26/S26,"") -> 0 | X26: ='Business Plan'!I34 -> -8700 | Y26: =SUMIF('Demand Generation Plan'!$D$4:$D43,X3,'Demand Generation Plan'!$R$4:$R43) -> 0 | Z26: =Y26-X26 -> 8700 | AA26: =iferror(Y26/X26,"") -> 0 | AC26: ='Business Plan'!J34 -> -1200 | AD26: =SUMIF('Demand Generation Plan'!$D$4:$D43,AC3,'Demand Generation Plan'!$R$4:$R43) -> 0 | AE26: =AD26-AC26 -> 1200 | AF26: =iferror(AD26/AC26,"") -> 0 | AH26: ='Business Plan'!K34 -> -9200 | AI26: =SUMIF('Demand Generation Plan'!$D$4:$D43,AH3,'Demand Generation Plan'!$R$4:$R43) -> 0 | AJ26: =AI26-AH26 -> 9200 | AK26: =iferror(AI26/AH26,"") -> 0 | AM26: ='Business Plan'!L34 -> -1200 | AN26: =SUMIF('Demand Generation Plan'!$D$4:$D43,AM3,'Demand Generation Plan'!$R$4:$R43) -> 0 | AO26: =AN26-AM26 -> 1200 | AP26: =iferror(AN26/AM26,"") -> 0 | AR26: ='Business Plan'!M34 -> -1200 | AS26: =SUMIF('Demand Generation Plan'!$D$4:$D43,AR3,'Demand Generation Plan'!$R$4:$R43) -> 0 | AT26: =AS26-AR26 -> 1200 | AU26: =iferror(AS26/AR26,"") -> 0 | AW26: ='Business Plan'!N34 -> -9200 | AX26: =SUMIF('Demand Generation Plan'!$D$4:$D43,AW3,'Demand Generation Plan'!$R$4:$R43) -> 0 | AY26: =AX26-AW26 -> 9200 | AZ26: =iferror(AX26/AW26,"") -> 0 | BB26: ='Business Plan'!O34 -> -1200 | BC26: =SUMIF('Demand Generation Plan'!$D$4:$D43,BB3,'Demand Generation Plan'!$R$4:$R43) -> 0 | BD26: =BC26-BB26 -> 1200 | BE26: =iferror(BC26/BB26,"") -> 0 | BG26: ='Business Plan'!P34 -> -1200 | BH26: =SUMIF('Demand Generation Plan'!$D$4:$D43,BG3,'Demand Generation Plan'!$R$4:$R43) -> 0 | BI26: =BH26-BG26 -> 1200 | BJ26: =iferror(BH26/BG26,"") -> 0 | BL26: =SUM(BG26,BB26,AW26,AR26,AM26,AH26,AC26,X26,S26,N26,I26,D26,) -> -48700 | BM26: =SUM(BH26,BC26,AX26,AS26,AN26,AI26,AD26,Y26,T26,O26,J26,E26,) -> 0 | BN26: =BM26-BL26 -> 48700 | BO26: =iferror(BM26/BL26,"") -> 0 | BQ26: =D26+I26+N26 -> -13900 | BR26: =E26+J26+O26 -> 0 | BS26: =BR26-BQ26 -> 13900 | BT26: =iferror(BR26/BQ26,"") -> 0 | BV26: =S26+X26+AC26 -> -11600 | BW26: =T26+Y26+AD26 -> 0 | BX26: =BW26-BV26 -> 11600 | BY26: =iferror(BW26/BV26,"") -> 0 | CA26: =AH26+AM26+AR26 -> -11600 | CB26: =AI26+AN26+AS26 -> 0 | CC26: =CB26-CA26 -> 11600 | CD26: =iferror(CB26/CA26,"") -> 0 | CF26: =BG26+BB26+AW26 -> -11600 | CG26: =BH26+BC26+AX26 -> 0 | CH26: =CG26-CF26 -> 11600 | CI26: =iferror(CG26/CF26,"") -> 0
C27: Leads # | D27: - | E27: =SUMIF('Demand Generation Plan'!$D$4:$D43,D3,'Demand Generation Plan'!$P$4:$P43) -> 0 | I27: - | J27: =SUMIF('Demand Generation Plan'!$D$4:$D43,I3,'Demand Generation Plan'!$P$4:$P43) -> 0 | N27: - | O27: =SUMIF('Demand Generation Plan'!$D$4:$D43,N3,'Demand Generation Plan'!$P$4:$P43) -> 0 | S27: - | T27: =SUMIF('Demand Generation Plan'!$D$4:$D43,S3,'Demand Generation Plan'!$P$4:$P43) -> 0 | X27: - | Y27: =SUMIF('Demand Generation Plan'!$D$4:$D43,X3,'Demand Generation Plan'!$P$4:$P43) -> 0 | AC27: - | AD27: =SUMIF('Demand Generation Plan'!$D$4:$D43,AC3,'Demand Generation Plan'!$P$4:$P43) -> 0 | AH27: - | AI27: =SUMIF('Demand Generation Plan'!$D$4:$D43,AH3,'Demand Generation Plan'!$P$4:$P43) -> 0 | AM27: - | AN27: =SUMIF('Demand Generation Plan'!$D$4:$D43,AM3,'Demand Generation Plan'!$P$4:$P43) -> 0 | AR27: - | AS27: =SUMIF('Demand Generation Plan'!$D$4:$D43,AR3,'Demand Generation Plan'!$P$4:$P43) -> 0 | AW27: - | AX27: =SUMIF('Demand Generation Plan'!$D$4:$D43,AW3,'Demand Generation Plan'!$P$4:$P43) -> 0 | BB27: - | BC27: =SUMIF('Demand Generation Plan'!$D$4:$D43,BB3,'Demand Generation Plan'!$P$4:$P43) -> 0 | BG27: - | BH27: =SUMIF('Demand Generation Plan'!$D$4:$D43,BG3,'Demand Generation Plan'!$P$4:$P43) -> 0 | BL27: =SUM(BG27,BB27,AW27,AR27,AM27,AH27,AC27,X27,S27,N27,I27,D27,) -> 0 | BM27: =SUM(BH27,BC27,AX27,AS27,AN27,AI27,AD27,Y27,T27,O27,J27,E27,) -> 0 | BN27: =BM27-BL27 -> 0 | BR27: =E27+J27+O27 -> 0 | BW27: =T27+Y27+AD27 -> 0 | CB27: =AI27+AN27+AS27 -> 0 | CG27: =BH27+BC27+AX27 -> 0
C29: Headcount | D29: =D30+D31 -> -14216.667 | E29: =E30+E31 -> 0 | G29: =iferror(E29/D29,"") -> 0 | I29: =I30+I31 -> -14216.667 | J29: =J30+J31 -> 0 | L29: =iferror(J29/I29,"") -> 0 | N29: =N30+N31 -> -14216.667 | O29: =O30+O31 -> 0 | Q29: =iferror(O29/N29,"") -> 0 | S29: =S30+S31 -> -14216.667 | T29: =T30+T31 -> 0 | V29: =iferror(T29/S29,"") -> 0 | X29: =X30+X31 -> -14216.667 | Y29: =Y30+Y31 -> 0 | AA29: =iferror(Y29/X29,"") -> 0 | AC29: =AC30+AC31 -> -14216.667 | AD29: =AD30+AD31 -> 0 | AF29: =iferror(AD29/AC29,"") -> 0 | AH29: =AH30+AH31 -> -14216.667 | AI29: =AI30+AI31 -> 0 | AK29: =iferror(AI29/AH29,"") -> 0 | AM29: =AM30+AM31 -> -14216.667 | AN29: =AN30+AN31 -> 0 | AP29: =iferror(AN29/AM29,"") -> 0 | AR29: =AR30+AR31 -> -14216.667 | AS29: =AS30+AS31 -> 0 | AU29: =iferror(AS29/AR29,"") -> 0 | AW29: =AW30+AW31 -> -14216.667 | AX29: =AX30+AX31 -> 0 | AZ29: =iferror(AX29/AW29,"") -> 0 | BB29: =BB30+BB31 -> -14216.667 | BC29: =BC30+BC31 -> 0 | BE29: =iferror(BC29/BB29,"") -> 0 | BG29: =BG30+BG31 -> -14216.667 | BH29: =BH30+BH31 -> 0 | BJ29: =iferror(BH29/BG29,"") -> 0 | BL29: =BL30+BL31 -> -170600 | BM29: =BM30+BM31 -> 0 | BO29: =iferror(BM29/BL29,"") -> 0 | BQ29: =D29+I29+N29 -> -42650 | BR29: =E29+J29+O29 -> 0 | BT29: =iferror(BR29/BQ29,"") -> 0 | BV29: =S29+X29+AC29 -> -42650 | BW29: =T29+Y29+AD29 -> 0 | BY29: =iferror(BW29/BV29,"") -> 0 | CA29: =AH29+AM29+AR29 -> -42650 | CB29: =AI29+AN29+AS29 -> 0 | CD29: =iferror(CB29/CA29,"") -> 0 | CF29: =BG29+BB29+AW29 -> -42650 | CG29: =BH29+BC29+AX29 -> 0 | CI29: =iferror(CG29/CF29,"") -> 0
C30: Salary | D30: ='Business Plan'!E37 -> -14216.667 | F30: =E30-D30 -> 14216.667 | G30: =iferror(E30/D30,"") -> 0 | I30: ='Business Plan'!F37 -> -14216.667 | K30: =J30-I30 -> 14216.667 | L30: =iferror(J30/I30,"") -> 0 | N30: ='Business Plan'!G37 -> -14216.667 | P30: =O30-N30 -> 14216.667 | Q30: =iferror(O30/N30,"") -> 0 | S30: ='Business Plan'!H37 -> -14216.667 | U30: =T30-S30 -> 14216.667 | V30: =iferror(T30/S30,"") -> 0 | X30: ='Business Plan'!I37 -> -14216.667 | Z30: =Y30-X30 -> 14216.667 | AA30: =iferror(Y30/X30,"") -> 0 | AC30: ='Business Plan'!J37 -> -14216.667 | AE30: =AD30-AC30 -> 14216.667 | AF30: =iferror(AD30/AC30,"") -> 0 | AH30: ='Business Plan'!K37 -> -14216.667 | AJ30: =AI30-AH30 -> 14216.667 | AK30: =iferror(AI30/AH30,"") -> 0 | AM30: ='Business Plan'!L37 -> -14216.667 | AO30: =AN30-AM30 -> 14216.667 | AP30: =iferror(AN30/AM30,"") -> 0 | AR30: ='Business Plan'!M37 -> -14216.667 | AT30: =AS30-AR30 -> 14216.667 | AU30: =iferror(AS30/AR30,"") -> 0 | AW30: ='Business Plan'!N37 -> -14216.667 | AY30: =AX30-AW30 -> 14216.667 | AZ30: =iferror(AX30/AW30,"") -> 0 | BB30: ='Business Plan'!O37 -> -14216.667 | BD30: =BC30-BB30 -> 14216.667 | BE30: =iferror(BC30/BB30,"") -> 0 | BG30: ='Business Plan'!P37 -> -14216.667 | BI30: =BH30-BG30 -> 14216.667 | BJ30: =iferror(BH30/BG30,"") -> 0 | BL30: =SUM(BG30,BB30,AW30,AR30,AM30,AH30,AC30,X30,S30,N30,I30,D30) -> -170600 | BM30: =SUM(BH30,BC30,AX30,AS30,AN30,AI30,AD30,Y30,T30,O30,J30,E30,) -> 0 | BN30: =BM30-BL30 -> 170600 | BO30: =iferror(BM30/BL30,"") -> 0 | BQ30: =D30+I30+N30 -> -42650 | BR30: =E30+J30+O30 -> 0 | BS30: =BR30-BQ30 -> 42650 | BT30: =iferror(BR30/BQ30,"") -> 0 | BV30: =S30+X30+AC30 -> -42650 | BW30: =T30+Y30+AD30 -> 0 | BX30: =BW30-BV30 -> 42650 | BY30: =iferror(BW30/BV30,"") -> 0 | CA30: =AH30+AM30+AR30 -> -42650 | CB30: =AI30+AN30+AS30 -> 0 | CC30: =CB30-CA30 -> 42650 | CD30: =iferror(CB30/CA30,"") -> 0 | CF30: =BG30+BB30+AW30 -> -42650 | CG30: =BH30+BC30+AX30 -> 0 | CH30: =CG30-CF30 -> 42650 | CI30: =iferror(CG30/CF30,"") -> 0
C31: Factorial Support | D31: ='Business Plan'!E38 -> 0 | I31: ='Business Plan'!F38 -> 0 | N31: ='Business Plan'!G38 -> 0 | S31: ='Business Plan'!H38 -> 0 | X31: ='Business Plan'!I38 -> 0 | AC31: ='Business Plan'!J38 -> 0 | AH31: ='Business Plan'!K38 -> 0 | AM31: ='Business Plan'!L38 -> 0 | AR31: ='Business Plan'!M38 -> 0 | AW31: ='Business Plan'!N38 -> 0 | BB31: ='Business Plan'!O38 -> 0 | BG31: ='Business Plan'!P38 -> 0 | BL31: =SUM(BG31,BB31,AW31,AR31,AM31,AH31,AC31,X31,S31,N31,I31,D31) -> 0 | BM31: =SUM(BH31,BC31,AX31,AS31,AN31,AI31,AD31,Y31,T31,O31,J31,E31,) -> 0 | BQ31: =D31+I31+N31 -> 0 | BR31: =E31+J31+O31 -> 0 | BV31: =S31+X31+AC31 -> 0 | BW31: =T31+Y31+AD31 -> 0 | CA31: =AH31+AM31+AR31 -> 0 | CB31: =AI31+AN31+AS31 -> 0 | CF31: =BG31+BB31+AW31 -> 0 | CG31: =BH31+BC31+AX31 -> 0
C32: Funded Heads (agg) | D32: =D29 -> -14216.667 | E32: =E29 -> 0 | I32: =I29+D32 -> -28433.333 | J32: =J29+E32 -> 0 | N32: =N29+I32 -> -42650 | O32: =O29+J32 -> 0 | S32: =S29+N32 -> -56866.667 | T32: =T29+O32 -> 0 | X32: =X29+S32 -> -71083.333 | Y32: =Y29+T32 -> 0 | AC32: =AC29+X32 -> -85300 | AD32: =AD29+Y32 -> 0 | AH32: =AH29+AC32 -> -99516.667 | AI32: =AI29+AD32 -> 0 | AM32: =AM29+AH32 -> -113733.33 | AN32: =AN29+AI32 -> 0 | AR32: =AR29+AM32 -> -127950 | AS32: =AS29+AN32 -> 0 | AW32: =AW29+AR32 -> -142166.67 | AX32: =AX29+AS32 -> 0 | BB32: =BB29+AW32 -> -156383.33 | BC32: =BC29+AX32 -> 0 | BG32: =BG29+BB32 -> -170600 | BH32: =BH29+BC32 -> 0 | BQ32: =D32+I32+N32 -> -85300 | BR32: =E32+J32+O32 -> 0 | BV32: =S32+X32+AC32 -> -213250 | BW32: =T32+Y32+AD32 -> 0 | CA32: =AH32+AM32+AR32 -> -341200 | CB32: =AI32+AN32+AS32 -> 0 | CF32: =BG32+BB32+AW32 -> -469150 | CG32: =BH32+BC32+AX32 -> 0
E34: 1 | F34: 2 | G34: 3 | H34: 4 | I34: 5 | J34: 6 | K34: 7 | L34: 8 | M34: 9 | N34: 10 | O34: 11 | P34: 12
E35: January | F35: February | G35: March | H35: April | I35: May | J35: June | K35: July | L35: August | M35: September | N35: October | O35: November | P35: December
E36: =SUMPRODUCT((IFERROR(MATCH('Demand Generation Plan'!$D$4:$D999, $E$35:$P$35, 0),"") = MOD(E$34 - 'Demand Generation Plan'!$M$1 - 1, 12) + 1) * ('Demand Generation Plan'!$D$4:$D999 <> ""), 'Demand Generation Plan'!$M$4:$M999) + SUMPRODUCT((IFERROR(MATCH('Demand Generation Plan'!$D$4:$D999, $E$35:$P$35, 0),"") = MOD(E$34 - 'Demand Generation Plan'!$N$1 - 1, 12) + 1) * ('Demand Generation Plan'!$D$4:$D999 <> ""), 'Demand Generation Plan'!$N$4:$N999) + SUMPRODUCT((IFERROR(MATCH('Demand Generation Plan'!$D$4:$D999, $E$35:$P$35, 0),"") = MOD(E$34 - 'Demand Generation Plan'!$O$1 - 1, 12) + 1) * ('Demand Generation Plan'!$D$4:$D999 <> ""), 'Demand Generation Plan'!$O$4:$O999) -> 0 | F36: =SUMPRODUCT((IFERROR(MATCH('Demand Generation Plan'!$D$4:$D999, $E$35:$P$35, 0),"") = MOD(F$34 - 'Demand Generation Plan'!$M$1 - 1, 12) + 1) * ('Demand Generation Plan'!$D$4:$D999 <> ""), 'Demand Generation Plan'!$M$4:$M999) + SUMPRODUCT((IFERROR(MATCH('Demand Generation Plan'!$D$4:$D999, $E$35:$P$35, 0),"") = MOD(F$34 - 'Demand Generation Plan'!$N$1 - 1, 12) + 1) * ('Demand Generation Plan'!$D$4:$D999 <> ""), 'Demand Generation Plan'!$N$4:$N999) + SUMPRODUCT((IFERROR(MATCH('Demand Generation Plan'!$D$4:$D999, $E$35:$P$35, 0),"") = MOD(F$34 - 'Demand Generation Plan'!$O$1 - 1, 12) + 1) * ('Demand Generation Plan'!$D$4:$D999 <> ""), 'Demand Generation Plan'!$O$4:$O999) -> 0 | G36: =SUMPRODUCT((IFERROR(MATCH('Demand Generation Plan'!$D$4:$D999, $E$35:$P$35, 0),"") = MOD(G$34 - 'Demand Generation Plan'!$M$1 - 1, 12) + 1) * ('Demand Generation Plan'!$D$4:$D999 <> ""), 'Demand Generation Plan'!$M$4:$M999) + SUMPRODUCT((IFERROR(MATCH('Demand Generation Plan'!$D$4:$D999, $E$35:$P$35, 0),"") = MOD(G$34 - 'Demand Generation Plan'!$N$1 - 1, 12) + 1) * ('Demand Generation Plan'!$D$4:$D999 <> ""), 'Demand Generation Plan'!$N$4:$N999) + SUMPRODUCT((IFERROR(MATCH('Demand Generation Plan'!$D$4:$D999, $E$35:$P$35, 0),"") = MOD(G$34 - 'Demand Generation Plan'!$O$1 - 1, 12) + 1) * ('Demand Generation Plan'!$D$4:$D999 <> ""), 'Demand Generation Plan'!$O$4:$O999) -> 0 | H36: =SUMPRODUCT((IFERROR(MATCH('Demand Generation Plan'!$D$4:$D999, $E$35:$P$35, 0),"") = MOD(H$34 - 'Demand Generation Plan'!$M$1 - 1, 12) + 1) * ('Demand Generation Plan'!$D$4:$D999 <> ""), 'Demand Generation Plan'!$M$4:$M999) + SUMPRODUCT((IFERROR(MATCH('Demand Generation Plan'!$D$4:$D999, $E$35:$P$35, 0),"") = MOD(H$34 - 'Demand Generation Plan'!$N$1 - 1, 12) + 1) * ('Demand Generation Plan'!$D$4:$D999 <> ""), 'Demand Generation Plan'!$N$4:$N999) + SUMPRODUCT((IFERROR(MATCH('Demand Generation Plan'!$D$4:$D999, $E$35:$P$35, 0),"") = MOD(H$34 - 'Demand Generation Plan'!$O$1 - 1, 12) + 1) * ('Demand Generation Plan'!$D$4:$D999 <> ""), 'Demand Generation Plan'!$O$4:$O999) -> 0 | I36: =SUMPRODUCT((IFERROR(MATCH('Demand Generation Plan'!$D$4:$D999, $E$35:$P$35, 0),"") = MOD(I$34 - 'Demand Generation Plan'!$M$1 - 1, 12) + 1) * ('Demand Generation Plan'!$D$4:$D999 <> ""), 'Demand Generation Plan'!$M$4:$M999) + SUMPRODUCT((IFERROR(MATCH('Demand Generation Plan'!$D$4:$D999, $E$35:$P$35, 0),"") = MOD(I$34 - 'Demand Generation Plan'!$N$1 - 1, 12) + 1) * ('Demand Generation Plan'!$D$4:$D999 <> ""), 'Demand Generation Plan'!$N$4:$N999) + SUMPRODUCT((IFERROR(MATCH('Demand Generation Plan'!$D$4:$D999, $E$35:$P$35, 0),"") = MOD(I$34 - 'Demand Generation Plan'!$O$1 - 1, 12) + 1) * ('Demand Generation Plan'!$D$4:$D999 <> ""), 'Demand Generation Plan'!$O$4:$O999) -> 0 | J36: =SUMPRODUCT((IFERROR(MATCH('Demand Generation Plan'!$D$4:$D999, $E$35:$P$35, 0),"") = MOD(J$34 - 'Demand Generation Plan'!$M$1 - 1, 12) + 1) * ('Demand Generation Plan'!$D$4:$D999 <> ""), 'Demand Generation Plan'!$M$4:$M999) + SUMPRODUCT((IFERROR(MATCH('Demand Generation Plan'!$D$4:$D999, $E$35:$P$35, 0),"") = MOD(J$34 - 'Demand Generation Plan'!$N$1 - 1, 12) + 1) * ('Demand Generation Plan'!$D$4:$D999 <> ""), 'Demand Generation Plan'!$N$4:$N999) + SUMPRODUCT((IFERROR(MATCH('Demand Generation Plan'!$D$4:$D999, $E$35:$P$35, 0),"") = MOD(J$34 - 'Demand Generation Plan'!$O$1 - 1, 12) + 1) * ('Demand Generation Plan'!$D$4:$D999 <> ""), 'Demand Generation Plan'!$O$4:$O999) -> 0 | K36: =SUMPRODUCT((IFERROR(MATCH('Demand Generation Plan'!$D$4:$D999, $E$35:$P$35, 0),"") = MOD(K$34 - 'Demand Generation Plan'!$M$1 - 1, 12) + 1) * ('Demand Generation Plan'!$D$4:$D999 <> ""), 'Demand Generation Plan'!$M$4:$M999) + SUMPRODUCT((IFERROR(MATCH('Demand Generation Plan'!$D$4:$D999, $E$35:$P$35, 0),"") = MOD(K$34 - 'Demand Generation Plan'!$N$1 - 1, 12) + 1) * ('Demand Generation Plan'!$D$4:$D999 <> ""), 'Demand Generation Plan'!$N$4:$N999) + SUMPRODUCT((IFERROR(MATCH('Demand Generation Plan'!$D$4:$D999, $E$35:$P$35, 0),"") = MOD(K$34 - 'Demand Generation Plan'!$O$1 - 1, 12) + 1) * ('Demand Generation Plan'!$D$4:$D999 <> ""), 'Demand Generation Plan'!$O$4:$O999) -> 0 | L36: =SUMPRODUCT((IFERROR(MATCH('Demand Generation Plan'!$D$4:$D999, $E$35:$P$35, 0),"") = MOD(L$34 - 'Demand Generation Plan'!$M$1 - 1, 12) + 1) * ('Demand Generation Plan'!$D$4:$D999 <> ""), 'Demand Generation Plan'!$M$4:$M999) + SUMPRODUCT((IFERROR(MATCH('Demand Generation Plan'!$D$4:$D999, $E$35:$P$35, 0),"") = MOD(L$34 - 'Demand Generation Plan'!$N$1 - 1, 12) + 1) * ('Demand Generation Plan'!$D$4:$D999 <> ""), 'Demand Generation Plan'!$N$4:$N999) + SUMPRODUCT((IFERROR(MATCH('Demand Generation Plan'!$D$4:$D999, $E$35:$P$35, 0),"") = MOD(L$34 - 'Demand Generation Plan'!$O$1 - 1, 12) + 1) * ('Demand Generation Plan'!$D$4:$D999 <> ""), 'Demand Generation Plan'!$O$4:$O999) -> 0 | ... P36: =SUMPRODUCT((IFERROR(MATCH('Demand Generation Plan'!$D$4:$D999, $E$35:$P$35, 0),"") = MOD(P$34 - 'Demand Generation Plan'!$M$1 - 1, 12) + 1) * ('Demand Generation Plan'!$D$4:$D999 <> ""), 'Demand Generation Plan'!$M$4:$M999) + SUMPRODUCT((IFERROR(MATCH('Demand Generation Plan'!$D$4:$D999, $E$35:$P$35, 0),"") = MOD(P$34 - 'Demand Generation Plan'!$N$1 - 1, 12) + 1) * ('Demand Generation Plan'!$D$4:$D999 <> ""), 'Demand Generation Plan'!$N$4:$N999) + SUMPRODUCT((IFERROR(MATCH('Demand Generation Plan'!$D$4:$D999, $E$35:$P$35, 0),"") = MOD(P$34 - 'Demand Generation Plan'!$O$1 - 1, 12) + 1) * ('Demand Generation Plan'!$D$4:$D999 <> ""), 'Demand Generation Plan'!$O$4:$O999) -> 0

Sheet Project Planner
B2: Project Name | D2: Project | G2: Q1 | T2: Q2 | AG2: Q3 | AT2: Q4
B4: Task Name | C4: Task Owner | D4: Deliverable | E4: Status | F4: Deadline | G4: January | L4: February | P4: March | T4: April | Y4: May | AC4: June | AG4: July | AL4: August | AP4: September | AT4: October | AY4: November | BC4: December
G5: W1 | H5: W2 | I5: W3 | J5: W4 | K5: W5 | L5: W6 | M5: W7 | N5: W8 | O5: W9 | P5: W10 | Q5: W11 | R5: W12 | S5: W13 | T5: W14 | U5: W15 | V5: W16 | W5: W17 | X5: W18 | Y5: W19 | Z5: W20 | AA5: W21 | AB5: W22 | AC5: W23 | AD5: W24 | AE5: W25 | AF5: W26 | AG5: W27 | AH5: W28 | AI5: W29 | AJ5: W30 | AK5: W31 | AL5: W32 | AM5: W33 | AN5: W34 | AO5: W35 | AP5: W36 | AQ5: W37 | AR5: W38 | AS5: W39 | AT5: W40 | AU5: W41 | AV5: W42 | AW5: W43 | AX5: W44 | AY5: W45 | AZ5: W46 | BA5: W47 | BB5: W48 | BC5: W49 | BD5: W50 | BE5: W51 | BF5: W52
B6: Project 1
B7: Task 1 | C7: Partner + Factorial | D7: Deliverable 1 | E7: Done | F7: 45664
B8: Task 2 | C8: Partner | D8: Deliverable 2 | E8: Done | F8: 45675
B9: Task 3 | C9: Partner | D9: Deliverable 3 | E9: Done | F9: 45681
B10: Task 4 | C10: Partner + Factorial | D10: Deliverable 4 | E10: In progress | F10: 45688

Sheet DATA-EXP
A1: Country Code | B1: Name | C1: PDM | D1: PAM | E1: Marketing Manager | F1: Month | G1: Type | H1: {=TRANSPOSE('Actual v Plan'!C5:E32)} -> Demos # | I1: % Demo to Customer | J1: Demos # (agg) | L1: Won Customers # | M1: Won Customers # (agg) | O1: Won MRR | P1: ARPU | Q1: Won ARR | R1: Won ARR (agg) | T1: Commissions Total | U1: Commissions - Sales | V1: Own Integrations | W1: Onboardings | X1: Bonus & Incentives | Y1: Commissions Total (agg) | AA1: Demand Generation Plan | AB1: Actions # | AC1: Budget | AD1: Leads # | AF1: Headcount | AG1: Salary | AH1: Factorial Support | AI1: Funded Heads (agg)
A2: ='Partnership Info'!$D$10 -> ROW | B2: ='Partnership Info'!$D$2 -> Partner | C2: ='Partnership Info'!$D$5 -> Leon Ribeiro | D2: ='Partnership Info'!$D$6 -> Edgar Balby | E2: ='Partnership Info'!$D$7 -> Agata Lech | F2: January | G2: Plan | H2: 5 | I2: 0.18 | J2: 5 | L2: 1 | M2: 1 | O2: 1750 | P2: 1200 | Q2: 21000 | R2: 21000 | T2: 8100 | U2: 7350 | V2: 0 | W2: 750 | X2: 0 | Y2: 8100 | AB2: 3 | AC2: -1700 | AD2: - | AF2: -14216.667 | AG2: -14216.667 | AH2: 0 | AI2: -14216.667
A3: ='Partnership Info'!$D$10 -> ROW | B3: ='Partnership Info'!$D$2 -> Partner | C3: ='Partnership Info'!$D$5 -> Leon Ribeiro | D3: ='Partnership Info'!$D$6 -> Edgar Balby | E3: ='Partnership Info'!$D$7 -> Agata Lech | F3: January | G3: Actual | H3: 0 | J3: 0 | L3: 0 | M3: 0 | O3: 0 | Q3: 0 | R3: 0 | T3: 0 | U3: 0 | X3: 0 | Y3: 0 | AB3: 0 | AC3: 0 | AD3: 0 | AF3: 0 | AI3: 0
A4: ='Partnership Info'!$D$10 -> ROW | B4: ='Partnership Info'!$D$2 -> Partner | C4: ='Partnership Info'!$D$5 -> Leon Ribeiro | D4: ='Partnership Info'!$D$6 -> Edgar Balby | E4: ='Partnership Info'!$D$7 -> Agata Lech | F4: February | G4: Plan | H4: {=TRANSPOSE('Actual v Plan'!I5:J32)} -> 5 | I4: 0.18 | J4: 10 | L4: 1 | M4: 2 | O4: 2100 | P4: 1200 | Q4: 25200 | R4: 46200 | T4: 9570 | U4: 8820 | V4: 0 | W4: 750 | X4: 0 | Y4: 17670 | AB4: 3 | AC4: -11000 | AD4: - | AF4: -14216.667 | AG4: -14216.667 | AH4: 0 | AI4: -28433.333
A5: ='Partnership Info'!$D$10 -> ROW | B5: ='Partnership Info'!$D$2 -> Partner | C5: ='Partnership Info'!$D$5 -> Leon Ribeiro | D5: ='Partnership Info'!$D$6 -> Edgar Balby | E5: ='Partnership Info'!$D$7 -> Agata Lech | F5: February | G5: Actual | H5: 0 | J5: 0 | L5: 0 | M5: 0 | O5: 0 | Q5: 0 | R5: 0 | T5: 0 | X5: 0 | Y5: 0 | AB5: 0 | AC5: 0 | AD5: 0 | AF5: 0 | AI5: 0
A6: ='Partnership Info'!$D$10 -> ROW | B6: ='Partnership Info'!$D$2 -> Partner | C6: ='Partnership Info'!$D$5 -> Leon Ribeiro | D6: ='Partnership Info'!$D$6 -> Edgar Balby | E6: ='Partnership Info'!$D$7 -> Agata Lech | F6: March | G6: Plan | H6: {=TRANSPOSE('Actual v Plan'!N5:O32)} -> 11 | I6: 0.18 | J6: 21 | L6: 2 | M6: 4 | O6: 2450 | P6: 1200 | Q6: 29400 | R6: 75600 | T6: 28990 | U6: 10290 | V6: 0 | W6: 1500 | X6: 17200 | Y6: 46660 | AB6: 2 | AC6: -1200 | AD6: - | AF6: -14216.667 | AG6: -14216.667 | AH6: 0 | AI6: -42650
A7: ='Partnership Info'!$D$10 -> ROW | B7: ='Partnership Info'!$D$2 -> Partner | C7: ='Partnership Info'!$D$5 -> Leon Ribeiro | D7: ='Partnership Info'!$D$6 -> Edgar Balby | E7: ='Partnership Info'!$D$7 -> Agata Lech | F7: March | G7: Actual | H7: 0 | J7: 0 | L7: 0 | M7: 0 | O7: 0 | Q7: 0 | R7: 0 | T7: 0 | X7: 0 | Y7: 0 | AB7: 0 | AC7: 0 | AD7: 0 | AF7: 0 | AI7: 0
A8: ='Partnership Info'!$D$10 -> ROW | B8: ='Partnership Info'!$D$2 -> Partner | C8: ='Partnership Info'!$D$5 -> Leon Ribeiro | D8: ='Partnership Info'!$D$6 -> Edgar Balby | E8: ='Partnership Info'!$D$7 -> Agata Lech | F8: April | G8: Plan | H8: {=TRANSPOSE('Actual v Plan'!S5:T32)} -> 5 | I8: 0.18 | J8: 26 | L8: 1 | M8: 5 | O8: 2100 | P8: 1200 | Q8: 25200 | R8: 100800 | T8: 10320 | U8: 8820 | V8: 0 | W8: 1500 | X8: 0 | Y8: 56980 | AB8: 3 | AC8: -1700 | AD8: - | AF8: -14216.667 | AG8: -14216.667 | AH8: 0 | AI8: -56866.667
A9: ='Partnership Info'!$D$10 -> ROW | B9: ='Partnership Info'!$D$2 -> Partner | C9: ='Partnership Info'!$D$5 -> Leon Ribeiro | D9: ='Partnership Info'!$D$6 -> Edgar Balby | E9: ='Partnership Info'!$D$7 -> Agata Lech | F9: April | G9: Actual | H9: 0 | J9: 0 | L9: 0 | M9: 0 | O9: 0 | Q9: 0 | R9: 0 | T9: 0 | X9: 0 | Y9: 0 | AB9: 0 | AC9: 0 | AD9: 0 | AF9: 0 | AI9: 0
A10: ='Partnership Info'!$D$10 -> ROW | B10: ='Partnership Info'!$D$2 -> Partner | C10: ='Partnership Info'!$D$5 -> Leon Ribeiro | D10: ='Partnership Info'!$D$6 -> Edgar Balby | E10: ='Partnership Info'!$D$7 -> Agata Lech | F10: May | G10: Plan | H10: {=TRANSPOSE('Actual v Plan'!X5:Y32)} -> 11 | I10: 0.18 | J10: 37 | L10: 2 | M10: 7 | O10: 2450 | P10: 1200 | Q10: 29400 | R10: 130200 | T10: 13290 | U10: 10290 | V10: 0 | W10: 3000 | X10: 0 | Y10: 70270 | AB10: 3 | AC10: -8700 | AD10: - | AF10: -14216.667 | AG10: -14216.667 | AH10: 0 | AI10: -71083.333
A11: ='Partnership Info'!$D$10 -> ROW | B11: ='Partnership Info'!$D$2 -> Partner | C11: ='Partnership Info'!$D$5 -> Leon Ribeiro | D11: ='Partnership Info'!$D$6 -> Edgar Balby | E11: ='Partnership Info'!$D$7 -> Agata Lech | F11: May | G11: Actual | H11: 0 | J11: 0 | L11: 0 | M11: 0 | O11: 0 | Q11: 0 | R11: 0 | T11: 0 | X11: 0 | Y11: 0 | AB11: 0 | AC11: 0 | AD11: 0 | AF11: 0 | AI11: 0
A12: ='Partnership Info'!$D$10 -> ROW | B12: ='Partnership Info'!$D$2 -> Partner | C12: ='Partnership Info'!$D$5 -> Leon Ribeiro | D12: ='Partnership Info'!$D$6 -> Edgar Balby | E12: ='Partnership Info'!$D$7 -> Agata Lech | F12: June | G12: Plan | H12: {=TRANSPOSE('Actual v Plan'!AC5:AD32)} -> 16 | I12: 0.18 | J12: 53 | L12: 3 | M12: 10 | O12: 4200 | P12: 1200 | Q12: 50400 | R12: 180600 | T12: 35690 | U12: 17640 | V12: 0 | W12: 4500 | X12: 13550 | Y12: 105960 | AB12: 2 | AC12: -1200 | AD12: - | AF12: -14216.667 | AG12: -14216.667 | AH12: 0 | AI12: -85300
A13: ='Partnership Info'!$D$10 -> ROW | B13: ='Partnership Info'!$D$2 -> Partner | C13: ='Partnership Info'!$D$5 -> Leon Ribeiro | D13: ='Partnership Info'!$D$6 -> Edgar Balby | E13: ='Partnership Info'!$D$7 -> Agata Lech | F13: June | G13: Actual | H13: 0 | J13: 0 | L13: 0 | M13: 0 | O13: 0 | Q13: 0 | R13: 0 | T13: 0 | X13: 0 | Y13: 0 | AB13: 0 | AC13: 0 | AD13: 0 | AF13: 0 | AI13: 0
A14: ='Partnership Info'!$D$10 -> ROW | B14: ='Partnership Info'!$D$2 -> Partner | C14: ='Partnership Info'!$D$5 -> Leon Ribeiro | D14: ='Partnership Info'!$D$6 -> Edgar Balby | E14: ='Partnership Info'!$D$7 -> Agata Lech | F14: July | G14: Plan | H14: {=TRANSPOSE('Actual v Plan'!AH5:AI32)} -> 11 | I14: 0.18 | J14: 64 | L14: 2 | M14: 12 | O14: 2450 | P14: 1200 | Q14: 29400 | R14: 210000 | T14: 16290 | U14: 10290 | V14: 0 | W14: 6000 | X14: 0 | Y14: 122250 | AB14: 4 | AC14: -9200 | AD14: - | AF14: -14216.667 | AG14: -14216.667 | AH14: 0 | AI14: -99516.667
A15: ='Partnership Info'!$D$10 -> ROW | B15: ='Partnership Info'!$D$2 -> Partner | C15: ='Partnership Info'!$D$5 -> Leon Ribeiro | D15: ='Partnership Info'!$D$6 -> Edgar Balby | E15: ='Partnership Info'!$D$7 -> Agata Lech | F15: July | G15: Actual | H15: 0 | J15: 0 | L15: 0 | M15: 0 | O15: 0 | Q15: 0 | R15: 0 | T15: 0 | X15: 0 | Y15: 0 | AB15: 0 | AC15: 0 | AD15: 0 | AF15: 0 | AI15: 0
A16: ='Partnership Info'!$D$10 -> ROW | B16: ='Partnership Info'!$D$2 -> Partner | C16: ='Partnership Info'!$D$5 -> Leon Ribeiro | D16: ='Partnership Info'!$D$6 -> Edgar Balby | E16: ='Partnership Info'!$D$7 -> Agata Lech | F16: August | G16: Plan | H16: {=TRANSPOSE('Actual v Plan'!AM5:AN32)} -> 16 | I16: 0.18 | J16: 80 | L16: 3 | M16: 15 | O16: 2800 | P16: 1200 | Q16: 33600 | R16: 243600 | T16: 20760 | U16: 11760 | V16: 0 | W16: 9000 | X16: 0 | Y16: 143010 | AB16: 2 | AC16: -1200 | AD16: - | AF16: -14216.667 | AG16: -14216.667 | AH16: 0 | AI16: -113733.33
A17: ='Partnership Info'!$D$10 -> ROW | B17: ='Partnership Info'!$D$2 -> Partner | C17: ='Partnership Info'!$D$5 -> Leon Ribeiro | D17: ='Partnership Info'!$D$6 -> Edgar Balby | E17: ='Partnership Info'!$D$7 -> Agata Lech | F17: August | G17: Actual | H17: 0 | J17: 0 | L17: 0 | M17: 0 | O17: 0 | Q17: 0 | R17: 0 | T17: 0 | X17: 0 | Y17: 0 | AB17: 0 | AC17: 0 | AD17: 0 | AF17: 0 | AI17: 0
A18: ='Partnership Info'!$D$10 -> ROW | B18: ='Partnership Info'!$D$2 -> Partner | C18: ='Partnership Info'!$D$5 -> Leon Ribeiro | D18: ='Partnership Info'!$D$6 -> Edgar Balby | E18: ='Partnership Info'!$D$7 -> Agata Lech | F18: September | G18: Plan | H18: {=TRANSPOSE('Actual v Plan'!AR5:AS32)} -> 16 | I18: 0.18 | J18: 96 | L18: 3 | M18: 18 | O18: 3850 | P18: 1200 | Q18: 46200 | R18: 289800 | T18: 39220 | U18: 16170 | V18: 0 | W18: 9000 | X18: 14050 | Y18: 182230 | AB18: 2 | AC18: -1200 | AD18: - | AF18: -14216.667 | AG18: -14216.667 | AH18: 0 | AI18: -127950
A19: ='Partnership Info'!$D$10 -> ROW | B19: ='Partnership Info'!$D$2 -> Partner | C19: ='Partnership Info'!$D$5 -> Leon Ribeiro | D19: ='Partnership Info'!$D$6 -> Edgar Balby | E19: ='Partnership Info'!$D$7 -> Agata Lech | F19: September | G19: Actual | H19: 0 | J19: 0 | L19: 0 | M19: 0 | O19: 0 | Q19: 0 | R19: 0 | T19: 0 | X19: 0 | Y19: 0 | AB19: 0 | AC19: 0 | AD19: 0 | AF19: 0 | AI19: 0
A20: ='Partnership Info'!$D$10 -> ROW | B20: ='Partnership Info'!$D$2 -> Partner | C20: ='Partnership Info'!$D$5 -> Leon Ribeiro | D20: ='Partnership Info'!$D$6 -> Edgar Balby | E20: ='Partnership Info'!$D$7 -> Agata Lech | F20: October | G20: Plan | H20: {=TRANSPOSE('Actual v Plan'!AW5:AX32)} -> 16 | I20: 0.18 | J20: 112 | L20: 3 | M20: 21 | O20: 4200 | P20: 1200 | Q20: 50400 | R20: 340200 | T20: 26640 | U20: 17640 | V20: 0 | W20: 9000 | X20: 0 | Y20: 208870 | AB20: 4 | AC20: -9200 | AD20: - | AF20: -14216.667 | AG20: -14216.667 | AH20: 0 | AI20: -142166.67
A21: ='Partnership Info'!$D$10 -> ROW | B21: ='Partnership Info'!$D$2 -> Partner | C21: ='Partnership Info'!$D$5 -> Leon Ribeiro | D21: ='Partnership Info'!$D$6 -> Edgar Balby | E21: ='Partnership Info'!$D$7 -> Agata Lech | F21: October | G21: Actual | H21: 0 | J21: 0 | L21: 0 | M21: 0 | O21: 0 | Q21: 0 | R21: 0 | T21: 0 | X21: 0 | Y21: 0 | AB21: 0 | AC21: 0 | AD21: 0 | AF21: 0 | AI21: 0
A22: ='Partnership Info'!$D$10 -> ROW | B22: ='Partnership Info'!$D$2 -> Partner | C22: ='Partnership Info'!$D$5 -> Leon Ribeiro | D22: ='Partnership Info'!$D$6 -> Edgar Balby | E22: ='Partnership Info'!$D$7 -> Agata Lech | F22: November | G22: Plan | H22: {=TRANSPOSE('Actual v Plan'!BB5:BC32)} -> 16 | I22: 0.18 | J22: 128 | L22: 3 | M22: 24 | O22: 4550 | P22: 1200 | Q22: 54600 | R22: 394800 | T22: 28110 | U22: 19110 | V22: 0 | W22: 9000 | X22: 0 | Y22: 236980 | AB22: 2 | AC22: -1200 | AD22: - | AF22: -14216.667 | AG22: -14216.667 | AH22: 0 | AI22: -156383.33
A23: ='Partnership Info'!$D$10 -> ROW | B23: ='Partnership Info'!$D$2 -> Partner | C23: ='Partnership Info'!$D$5 -> Leon Ribeiro | D23: ='Partnership Info'!$D$6 -> Edgar Balby | E23: ='Partnership Info'!$D$7 -> Agata Lech | F23: November | G23: Actual | H23: 0 | J23: 0 | L23: 0 | M23: 0 | O23: 0 | Q23: 0 | R23: 0 | T23: 0 | X23: 0 | Y23: 0 | AB23: 0 | AC23: 0 | AD23: 0 | AF23: 0 | AI23: 0
A24: ='Partnership Info'!$D$10 -> ROW | B24: ='Partnership Info'!$D$2 -> Partner | C24: ='Partnership Info'!$D$5 -> Leon Ribeiro | D24: ='Partnership Info'!$D$6 -> Edgar Balby | E24: ='Partnership Info'!$D$7 -> Agata Lech | F24: December | G24: Plan | H24: {=TRANSPOSE('Actual v Plan'!BG5:BH32)} -> 5 | I24: 0.18 | J24: 133 | L24: 1 | M24: 25 | O24: 2100 | P24: 1200 | Q24: 25200 | R24: 420000 | T24: 26370 | U24: 8820 | V24: 0 | W24: 3000 | X24: 14550 | Y24: 263350 | AB24: 2 | AC24: -1200 | AD24: - | AF24: -14216.667 | AG24: -14216.667 | AH24: 0 | AI24: -170600
A25: ='Partnership Info'!$D$10 -> ROW | B25: ='Partnership Info'!$D$2 -> Partner | C25: ='Partnership Info'!$D$5 -> Leon Ribeiro | D25: ='Partnership Info'!$D$6 -> Edgar Balby | E25: ='Partnership Info'!$D$7 -> Agata Lech | F25: December | G25: Actual | H25: 0 | J25: 0 | L25: 0 | M25: 0 | O25: 0 | Q25: 0 | R25: 0 | T25: 0 | X25: 0 | Y25: 0 | AB25: 0 | AC25: 0 | AD25: 0 | AF25: 0 | AI25: 0
V46: ='Business Plan'!X61 | W46: ='Business Plan'!Y61 | X46: ='Business Plan'!Z61
V47: ='Business Plan'!X62 | W47: ='Business Plan'!Y62 | X47: ='Business Plan'!Z62
V48: ='Business Plan'!X63 | W48: ='Business Plan'!Y63 | X48: ='Business Plan'!Z63
V49: ='Business Plan'!X64 | W49: ='Business Plan'!Y64 | X49: ='Business Plan'!Z64
V50: ='Business Plan'!X65 | W50: ='Business Plan'!Y65 | X50: ='Business Plan'!Z65
V51: ='Business Plan'!X66 | W51: ='Business Plan'!Y66 | X51: ='Business Plan'!Z66
V52: ='Business Plan'!X67 | W52: ='Business Plan'!Y67 | X52: ='Business Plan'!Z67
V53: ='Business Plan'!X68 | W53: ='Business Plan'!Y68 | X53: ='Business Plan'!Z68
V54: ='Business Plan'!X69 | W54: ='Business Plan'!Y69 | X54: ='Business Plan'!Z69
V55: ='Business Plan'!X70 | W55: ='Business Plan'!Y70 | X55: ='Business Plan'!Z70
V56: ='Business Plan'!X71 | W56: ='Business Plan'!Y71 | X56: ='Business Plan'!Z71
V57: ='Business Plan'!X72 | W57: ='Business Plan'!Y72 | X57: ='Business Plan'!Z72
... V100: ='Business Plan'!X115 | W100: ='Business Plan'!Y115 | X100: ='Business Plan'!Z115
A101: ='Business Plan'!C116 | B101: ='Business Plan'!E116 | F101: ='Business Plan'!F116 | H101: ='Business Plan'!G116 | I101: ='Business Plan'!H116 | J101: ='Business Plan'!I116 | K101: ='Business Plan'!J116 | L101: ='Business Plan'!K116 | M101: ='Business Plan'!L116 | N101: ='Business Plan'!M116 | O101: ='Business Plan'!N116 | ... R101: ='Business Plan'!Q116 | S101: ='Business Plan'!D116 | T101: ='Business Plan'!R116 | U101: ='Business Plan'!W116 | V101: ='Business Plan'!X116 | W101: ='Business Plan'!Y116 | X101: ='Business Plan'!Z116
A102: ='Business Plan'!C117 | B102: ='Business Plan'!E117 | F102: ='Business Plan'!F117 | H102: ='Business Plan'!G117 | I102: ='Business Plan'!H117 | J102: ='Business Plan'!I117 | K102: ='Business Plan'!J117 | L102: ='Business Plan'!K117 | M102: ='Business Plan'!L117 | N102: ='Business Plan'!M117 | O102: ='Business Plan'!N117 | ... R102: ='Business Plan'!Q117 | S102: ='Business Plan'!D117 | T102: ='Business Plan'!R117 | U102: ='Business Plan'!W117 | V102: ='Business Plan'!X117 | W102: ='Business Plan'!Y117 | X102: ='Business Plan'!Z117
A103: ='Business Plan'!C118 | B103: ='Business Plan'!E118 | F103: ='Business Plan'!F118 | H103: ='Business Plan'!G118 | I103: ='Business Plan'!H118 | J103: ='Business Plan'!I118 | K103: ='Business Plan'!J118 | L103: ='Business Plan'!K118 | M103: ='Business Plan'!L118 | N103: ='Business Plan'!M118 | O103: ='Business Plan'!N118 | ... R103: ='Business Plan'!Q118 | S103: ='Business Plan'!D118 | T103: ='Business Plan'!R118 | U103: ='Business Plan'!W118 | V103: ='Business Plan'!X118 | W103: ='Business Plan'!Y118 | X103: ='Business Plan'!Z118
A104: ='Business Plan'!C119 | B104: ='Business Plan'!E119 | F104: ='Business Plan'!F119 | H104: ='Business Plan'!G119 | I104: ='Business Plan'!H119 | J104: ='Business Plan'!I119 | K104: ='Business Plan'!J119 | L104: ='Business Plan'!K119 | M104: ='Business Plan'!L119 | N104: ='Business Plan'!M119 | O104: ='Business Plan'!N119 | ... R104: ='Business Plan'!Q119 | S104: ='Business Plan'!D119 | T104: ='Business Plan'!R119 | U104: ='Business Plan'!W119 | V104: ='Business Plan'!X119 | W104: ='Business Plan'!Y119 | X104: ='Business Plan'!Z119
A105: ='Business Plan'!C120 | B105: ='Business Plan'!E120 | F105: ='Business Plan'!F120 | H105: ='Business Plan'!G120 | I105: ='Business Plan'!H120 | J105: ='Business Plan'!I120 | K105: ='Business Plan'!J120 | L105: ='Business Plan'!K120 | M105: ='Business Plan'!L120 | N105: ='Business Plan'!M120 | O105: ='Business Plan'!N120 | ... R105: ='Business Plan'!Q120 | S105: ='Business Plan'!D120 | T105: ='Business Plan'!R120 | U105: ='Business Plan'!W120 | V105: ='Business Plan'!X120 | W105: ='Business Plan'!Y120 | X105: ='Business Plan'!Z120
A106: ='Business Plan'!C121 | B106: ='Business Plan'!E121 | F106: ='Business Plan'!F121 | H106: ='Business Plan'!G121 | I106: ='Business Plan'!H121 | J106: ='Business Plan'!I121 | K106: ='Business Plan'!J121 | L106: ='Business Plan'!K121 | M106: ='Business Plan'!L121 | N106: ='Business Plan'!M121 | O106: ='Business Plan'!N121 | ... R106: ='Business Plan'!Q121 | S106: ='Business Plan'!D121 | T106: ='Business Plan'!R121 | U106: ='Business Plan'!W121 | V106: ='Business Plan'!X121 | W106: ='Business Plan'!Y121 | X106: ='Business Plan'!Z121
A107: ='Business Plan'!C122 | B107: ='Business Plan'!E122 | F107: ='Business Plan'!F122 | H107: ='Business Plan'!G122 | I107: ='Business Plan'!H122 | J107: ='Business Plan'!I122 | K107: ='Business Plan'!J122 | L107: ='Business Plan'!K122 | M107: ='Business Plan'!L122 | N107: ='Business Plan'!M122 | O107: ='Business Plan'!N122 | ... R107: ='Business Plan'!Q122 | S107: ='Business Plan'!D122 | T107: ='Business Plan'!R122 | U107: ='Business Plan'!W122 | V107: ='Business Plan'!X122 | W107: ='Business Plan'!Y122 | X107: ='Business Plan'!Z122
A108: ='Business Plan'!C123 | B108: ='Business Plan'!E123 | F108: ='Business Plan'!F123 | H108: ='Business Plan'!G123 | I108: ='Business Plan'!H123 | J108: ='Business Plan'!I123 | K108: ='Business Plan'!J123 | L108: ='Business Plan'!K123 | M108: ='Business Plan'!L123 | N108: ='Business Plan'!M123 | O108: ='Business Plan'!N123 | ... R108: ='Business Plan'!Q123 | S108: ='Business Plan'!D123 | T108: ='Business Plan'!R123 | U108: ='Business Plan'!W123 | V108: ='Business Plan'!X123 | W108: ='Business Plan'!Y123 | X108: ='Business Plan'!Z123
A109: ='Business Plan'!C124 | B109: ='Business Plan'!E124 | F109: ='Business Plan'!F124 | H109: ='Business Plan'!G124 | I109: ='Business Plan'!H124 | J109: ='Business Plan'!I124 | K109: ='Business Plan'!J124 | L109: ='Business Plan'!K124 | M109: ='Business Plan'!L124 | N109: ='Business Plan'!M124 | O109: ='Business Plan'!N124 | ... R109: ='Business Plan'!Q124 | S109: ='Business Plan'!D124 | T109: ='Business Plan'!R124 | U109: ='Business Plan'!W124 | V109: ='Business Plan'!X124 | W109: ='Business Plan'!Y124 | X109: ='Business Plan'!Z124
A110: ='Business Plan'!C125 | B110: ='Business Plan'!E125 | F110: ='Business Plan'!F125 | H110: ='Business Plan'!G125 | I110: ='Business Plan'!H125 | J110: ='Business Plan'!I125 | K110: ='Business Plan'!J125 | L110: ='Business Plan'!K125 | M110: ='Business Plan'!L125 | N110: ='Business Plan'!M125 | O110: ='Business Plan'!N125 | ... R110: ='Business Plan'!Q125 | S110: ='Business Plan'!D125 | T110: ='Business Plan'!R125 | U110: ='Business Plan'!W125 | V110: ='Business Plan'!X125 | W110: ='Business Plan'!Y125 | X110: ='Business Plan'!Z125
A111: ='Business Plan'!C126 | B111: ='Business Plan'!E126 | F111: ='Business Plan'!F126 | H111: ='Business Plan'!G126 | I111: ='Business Plan'!H126 | J111: ='Business Plan'!I126 | K111: ='Business Plan'!J126 | L111: ='Business Plan'!K126 | M111: ='Business Plan'!L126 | N111: ='Business Plan'!M126 | O111: ='Business Plan'!N126 | ... R111: ='Business Plan'!Q126 | S111: ='Business Plan'!D126 | T111: ='Business Plan'!R126 | U111: ='Business Plan'!W126 | V111: ='Business Plan'!X126 | W111: ='Business Plan'!Y126 | X111: ='Business Plan'!Z126
A112: ='Business Plan'!C127 | B112: ='Business Plan'!E127 | F112: ='Business Plan'!F127 | H112: ='Business Plan'!G127 | I112: ='Business Plan'!H127 | J112: ='Business Plan'!I127 | K112: ='Business Plan'!J127 | L112: ='Business Plan'!K127 | M112: ='Business Plan'!L127 | N112: ='Business Plan'!M127 | O112: ='Business Plan'!N127 | ... R112: ='Business Plan'!Q127 | S112: ='Business Plan'!D127 | T112: ='Business Plan'!R127 | U112: ='Business Plan'!W127 | V112: ='Business Plan'!X127 | W112: ='Business Plan'!Y127 | X112: ='Business Plan'!Z127
... A193: ='Business Plan'!C208 | B193: ='Business Plan'!E208 | F193: ='Business Plan'!F208 | H193: ='Business Plan'!G208 | I193: ='Business Plan'!H208 | J193: ='Business Plan'!I208 | K193: ='Business Plan'!J208 | L193: ='Business Plan'!K208 | M193: ='Business Plan'!L208 | N193: ='Business Plan'!M208 | O193: ='Business Plan'!N208 | ... R193: ='Business Plan'!Q208 | S193: ='Business Plan'!D208 | T193: ='Business Plan'!R208 | U193: ='Business Plan'!W208 | V193: ='Business Plan'!X208 | W193: ='Business Plan'!Y208 | X193: ='Business Plan'!Z208

Sheet MKT-EXP
A1: Country Code | B1: Name | C1: Marketing Manager | D1: Action Name | E1: Quarter | F1: Month | G1: Type of action | H1: Planned Cost | I1: Demos Goal | J1: M0 | K1: M1 | L1: M2 | M1: Demos Actual | N1: M0 | O1: M1 | P1: M2 | Q1: Leads Actual | R1: Clients Won | S1: Total Cost | T1: Partner Actual Cost | U1: MRR won | V1: ROI (on ARR) | W1: % Lead to Demo | X1: % Demo to Won | Y1: CAC | Z1: Cost per Demo
A2: {=IF(D2:D1000 <> "", {'Partnership Info'!$D$10, 'Partnership Info'!$D$2, 'Partnership Info'!$D$7}, {"", "", ""} )} -> ROW | B2: Partner | C2: Agata Lech | D2: =IFERROR(__xludf.DUMMYFUNCTION("FILTER('Demand Generation Plan'!B4:Y1000,'Demand Generation Plan'!E4:E1000>1)"),"Outbound Q1") -> Outbound Q1 | E2: =IFERROR(__xludf.DUMMYFUNCTION("""COMPUTED_VALUE"""),"Q1") -> Q1 | F2: =IFERROR(__xludf.DUMMYFUNCTION("""COMPUTED_VALUE"""),"January") -> January | G2: =IFERROR(__xludf.DUMMYFUNCTION("""COMPUTED_VALUE"""),"Outbound Actions") -> Outbound Actions | H2: =IFERROR(__xludf.DUMMYFUNCTION("""COMPUTED_VALUE"""),500.0) -> 500 | I2: =IFERROR(__xludf.DUMMYFUNCTION("""COMPUTED_VALUE"""),9.0) -> 9 | J2: =IFERROR(__xludf.DUMMYFUNCTION("""COMPUTED_VALUE"""),3.0) -> 3 | K2: =IFERROR(__xludf.DUMMYFUNCTION("""COMPUTED_VALUE"""),3.0) -> 3 | L2: =IFERROR(__xludf.DUMMYFUNCTION("""COMPUTED_VALUE"""),3.0) -> 3 | M2: =IFERROR(__xludf.DUMMYFUNCTION("""COMPUTED_VALUE"""),55.55555555555556) -> 55.555556 | N2: =IFERROR(__xludf.DUMMYFUNCTION("""COMPUTED_VALUE"""),0.0) -> 0 | O2: =IFERROR(__xludf.DUMMYFUNCTION("""COMPUTED_VALUE"""),0.0) -> 0 | P2: =IFERROR(__xludf.DUMMYFUNCTION("""COMPUTED_VALUE"""),0.0) -> 0 | Q2: =IFERROR(__xludf.DUMMYFUNCTION("""COMPUTED_VALUE"""),0.0) -> 0 | R2: =IFERROR(__xludf.DUMMYFUNCTION("""COMPUTED_VALUE"""),0.0) -> 0 | S2: =IFERROR(__xludf.DUMMYFUNCTION("""COMPUTED_VALUE"""),0.0) -> 0 | T2: =IFERROR(__xludf.DUMMYFUNCTION("""COMPUTED_VALUE"""),0.0) -> 0 | V2: =IFERROR(__xludf.DUMMYFUNCTION("""COMPUTED_VALUE"""),0.0) -> 0 | W2: =IFERROR(__xludf.DUMMYFUNCTION("""COMPUTED_VALUE"""),"") | X2: =IFERROR(__xludf.DUMMYFUNCTION("""COMPUTED_VALUE"""),"") | Y2: =IFERROR(__xludf.DUMMYFUNCTION("""COMPUTED_VALUE"""),"") | Z2: =IFERROR(__xludf.DUMMYFUNCTION("""COMPUTED_VALUE"""),"") | AA2: =IFERROR(__xludf.DUMMYFUNCTION("""COMPUTED_VALUE"""),"")
A3: ROW | B3: Partner | C3: Agata Lech | D3: =IFERROR(__xludf.DUMMYFUNCTION("""COMPUTED_VALUE"""),"Outbound Q2") -> Outbound Q2 | E3: =IFERROR(__xludf.DUMMYFUNCTION("""COMPUTED_VALUE"""),"Q2") -> Q2 | F3: =IFERROR(__xludf.DUMMYFUNCTION("""COMPUTED_VALUE"""),"April") -> April | G3: =IFERROR(__xludf.DUMMYFUNCTION("""COMPUTED_VALUE"""),"Outbound Actions") -> Outbound Actions | H3: =IFERROR(__xludf.DUMMYFUNCTION("""COMPUTED_VALUE"""),500.0) -> 500 | I3: =IFERROR(__xludf.DUMMYFUNCTION("""COMPUTED_VALUE"""),12.0) -> 12 | J3: =IFERROR(__xludf.DUMMYFUNCTION("""COMPUTED_VALUE"""),4.0) -> 4 | K3: =IFERROR(__xludf.DUMMYFUNCTION("""COMPUTED_VALUE"""),4.0) -> 4 | L3: =IFERROR(__xludf.DUMMYFUNCTION("""COMPUTED_VALUE"""),4.0) -> 4 | M3: =IFERROR(__xludf.DUMMYFUNCTION("""COMPUTED_VALUE"""),41.666666666666664) -> 41.666667 | N3: =IFERROR(__xludf.DUMMYFUNCTION("""COMPUTED_VALUE"""),0.0) -> 0 | W3: =IFERROR(__xludf.DUMMYFUNCTION("""COMPUTED_VALUE"""),"") | X3: =IFERROR(__xludf.DUMMYFUNCTION("""COMPUTED_VALUE"""),"") | Y3: =IFERROR(__xludf.DUMMYFUNCTION("""COMPUTED_VALUE"""),"") | Z3: =IFERROR(__xludf.DUMMYFUNCTION("""COMPUTED_VALUE"""),"") | AA3: =IFERROR(__xludf.DUMMYFUNCTION("""COMPUTED_VALUE"""),"")
